<rows profile='color'><head><columns><column  rowspan="4"  width='45' align='right' type='ron' hidden='false' sort='na' color=''><![CDATA[No.]]></column><column  rowspan="4"  width='120' align='left' type='ro' hidden='false' sort='na' color=''><![CDATA[Divisi Bisnis/Cabang]]></column><column  colspan="2"  width='120' align='justify' type='ron' hidden='false' sort='na' color=''><![CDATA[Project]]></column><column  width='230' align='justify' type='ron' hidden='false' sort='na' color=''><![CDATA[]]></column><column  rowspan="4"  width='190' align='justify' type='ron' hidden='false' sort='na' color=''><![CDATA[Klien]]></column><column  rowspan="4"  width='80' align='center' type='ro' hidden='false' sort='na' color=''><![CDATA[P (7/4)]]></column><column  rowspan="4"  width='80' align='center' type='ro' hidden='false' sort='na' color=''><![CDATA[L (9/6)]]></column><column  colspan="2"  width='110' align='center' type='ron' hidden='false' sort='na' color=''><![CDATA[Jangka Waktu]]></column><column  width='110' align='center' type='ron' hidden='false' sort='na' color=''><![CDATA[]]></column><column  rowspan="4"  width='110' align='right' type='ron' hidden='false' sort='na' color=''><![CDATA[Nilai Kontrak]]></column><column  colspan="6"  width='110' align='right' type='ron' hidden='false' sort='na' color=''><![CDATA[ RAB]]></column><column  width='110' align='right' type='ron' hidden='false' sort='na' color=''><![CDATA[]]></column><column  width='110' align='right' type='ron' hidden='false' sort='na' color=''><![CDATA[]]></column><column  width='110' align='right' type='ron' hidden='false' sort='na' color=''><![CDATA[]]></column><column  width='110' align='right' type='ron' hidden='false' sort='na' color=''><![CDATA[]]></column><column  width='110' align='right' type='ron' hidden='false' sort='na' color=''><![CDATA[]]></column><column  colspan="3"  width='110' align='right' type='ron' hidden='false' sort='na' color=''><![CDATA[Realisasi]]></column><column  width='110' align='right' type='ron' hidden='false' sort='na' color=''><![CDATA[]]></column><column  width='110' align='right' type='ron' hidden='false' sort='na' color=''><![CDATA[]]></column><column  colspan="6"  width='110' align='right' type='ron' hidden='false' sort='na' color=''><![CDATA[Prosentase Progress 2021]]></column><column  width='110' align='right' type='ron' hidden='false' sort='na' color=''><![CDATA[]]></column><column  width='110' align='right' type='ron' hidden='false' sort='na' color=''><![CDATA[]]></column><column  width='90' align='right' type='ron' hidden='false' sort='na' color=''><![CDATA[]]></column><column  width='90' align='center' type='ro' hidden='false' sort='na' color=''><![CDATA[]]></column><column  width='110' align='center' type='ro' hidden='false' sort='na' color=''><![CDATA[]]></column><column  rowspan="4"  width='110' align='right' type='ron' hidden='false' sort='na' color=''><![CDATA[  Piutang]]></column><column  rowspan="4"  width='110' align='right' type='ron' hidden='false' sort='na' color=''><![CDATA[ Proforma]]></column><column  rowspan="4"  width='110' align='right' type='ron' hidden='false' sort='na' color=''><![CDATA[ Uang Muka]]></column><column  rowspan="4"  width='110' align='right' type='ron' hidden='false' sort='na' color=''><![CDATA[ ByDM]]></column><column  rowspan="4"  width='90' align='center' type='ro' hidden='false' sort='na' color=''><![CDATA[ PPU dan ByDM Detail]]></column><column  rowspan="4"  width='90' align='center' type='ro' hidden='false' sort='na' color=''><![CDATA[ Chart Pendapatan]]></column></columns>
<columns><column><![CDATA[]]></column><column><![CDATA[]]></column><column rowspan="3" ><![CDATA[Kode]]></column><column rowspan="3" ><![CDATA[Nama]]></column><column><![CDATA[]]></column><column><![CDATA[]]></column><column><![CDATA[]]></column><column rowspan="3" ><![CDATA[Awal]]></column><column rowspan="3" ><![CDATA[Akhir]]></column><column><![CDATA[]]></column><column><![CDATA[Pendapatan]]></column><column><![CDATA[Beban Jasa]]></column><column><![CDATA[Laba]]></column><column><![CDATA[Pendapatan]]></column><column><![CDATA[Beban Jasa]]></column><column><![CDATA[Laba]]></column><column><![CDATA[Pendapatan]]></column><column><![CDATA[Beban Jasa]]></column><column><![CDATA[Laba]]></column><column><![CDATA[Realisasi Pendapatan Vs RAB Setahun]]></column><column><![CDATA[Realisasi Pendapatan Vs RAB Bulan Berjalan]]></column><column><![CDATA[Realisasi Beban Vs RAB Setahun]]></column><column><![CDATA[Realisasi Beban Vs RAB Bulan Berjalan]]></column><column><![CDATA[Progress Fisik]]></column><column><![CDATA[QAQC]]></column><column><![CDATA[]]></column><column><![CDATA[]]></column><column><![CDATA[]]></column><column><![CDATA[]]></column><column><![CDATA[]]></column><column><![CDATA[]]></column></columns>
<columns><column><![CDATA[]]></column><column><![CDATA[]]></column><column><![CDATA[]]></column><column><![CDATA[]]></column><column><![CDATA[]]></column><column><![CDATA[]]></column><column><![CDATA[]]></column><column><![CDATA[]]></column><column><![CDATA[]]></column><column><![CDATA[]]></column><column colspan="3" ><![CDATA[2021]]></column><column><![CDATA[]]></column><column><![CDATA[]]></column><column colspan="6" ><![CDATA[s/d Bulan Mei]]></column><column><![CDATA[]]></column><column><![CDATA[]]></column><column><![CDATA[]]></column><column><![CDATA[]]></column><column><![CDATA[]]></column><column colspan="6" ><![CDATA[2021]]></column><column><![CDATA[]]></column><column><![CDATA[]]></column><column><![CDATA[]]></column><column><![CDATA[]]></column><column><![CDATA[]]></column><column><![CDATA[]]></column><column><![CDATA[]]></column><column><![CDATA[]]></column><column><![CDATA[]]></column><column><![CDATA[]]></column><column><![CDATA[]]></column></columns>
<columns><column><![CDATA[]]></column><column><![CDATA[]]></column><column><![CDATA[]]></column><column><![CDATA[]]></column><column><![CDATA[]]></column><column><![CDATA[]]></column><column><![CDATA[]]></column><column><![CDATA[]]></column><column><![CDATA[]]></column><column><![CDATA[]]></column><column><![CDATA[(1)]]></column><column><![CDATA[(2)]]></column><column><![CDATA[(3)]]></column><column><![CDATA[(4)]]></column><column><![CDATA[(5)]]></column><column><![CDATA[(6)]]></column><column><![CDATA[(7)]]></column><column><![CDATA[(8)]]></column><column><![CDATA[(9)]]></column><column><![CDATA[(7/1)]]></column><column><![CDATA[(7/4)]]></column><column><![CDATA[(8/2)]]></column><column><![CDATA[(8/5)]]></column><column><![CDATA[(15)]]></column><column><![CDATA[(16)]]></column><column><![CDATA[]]></column><column><![CDATA[]]></column><column><![CDATA[]]></column><column><![CDATA[]]></column><column><![CDATA[]]></column><column><![CDATA[]]></column></columns></head>
<foot>
<columns>
<column colspan='9' ><![CDATA[TOTAL]]></column>
<column><![CDATA[]]></column>
<column><![CDATA[]]></column>
<column><![CDATA[]]></column>
<column><![CDATA[]]></column>
<column><![CDATA[]]></column>
<column><![CDATA[]]></column>
<column><![CDATA[]]></column>
<column><![CDATA[]]></column>
<column><![CDATA[222,351,689,428.0]]></column>
<column><![CDATA[87,576,512,771.4]]></column>
<column><![CDATA[60,856,188,371.7]]></column>
<column><![CDATA[26,720,324,399.7]]></column>
<column><![CDATA[76,213,338,768.6]]></column>
<column><![CDATA[51,733,424,205.1]]></column>
<column><![CDATA[24,479,914,563.4]]></column>
<column><![CDATA[36,333,631,954.0]]></column>
<column><![CDATA[25,221,496,635.7]]></column>
<column><![CDATA[11,112,135,318.3]]></column>
<column colspan='6' ><![CDATA[ ]]></column>
<column><![CDATA[]]></column>
<column><![CDATA[]]></column>
<column><![CDATA[]]></column>
<column><![CDATA[]]></column>
<column><![CDATA[]]></column>
<column><![CDATA[31,098,860,550.0]]></column>
<column><![CDATA[1,341,575,000.0]]></column>
<column><![CDATA[1,725,994,811.0]]></column>
<column><![CDATA[12,437,711,026.0]]></column>
<column><![CDATA[ ]]></column>
<column><![CDATA[ ]]></column>
</columns>
</foot><row><cell><![CDATA[1]]></cell><cell><![CDATA[SI CAB JAKARTA]]></cell><cell><![CDATA[0716040080
                        
                         Penjelasan]]></cell><cell><![CDATA[16067_BUT STAR ENERGY GEOTHERMAL (WAYANG WINDU) LTD_NDE Services]]></cell><cell><![CDATA[BUT STAR ENERGY GEOTHERMAL (WAYANG WINDU) LTD]]></cell><cell><![CDATA[
            
            ]]></cell><cell><![CDATA[
            
            ]]></cell><cell><![CDATA[16-08-2016]]></cell><cell><![CDATA[31-12-2019]]></cell><cell><![CDATA[1,673,672,700.0]]></cell><cell><![CDATA[0.0]]></cell><cell><![CDATA[16,814,251.0]]></cell><cell><![CDATA[-16,814,251.0]]></cell><cell><![CDATA[0.0]]></cell><cell><![CDATA[16,814,251.0]]></cell><cell><![CDATA[-16,814,251.0]]></cell><cell><![CDATA[-15,021,750.0]]></cell><cell><![CDATA[-15,021,750.0]]></cell><cell><![CDATA[0.0]]></cell><cell><![CDATA[0]]></cell><cell><![CDATA[0]]></cell><cell><![CDATA[-89.3]]></cell><cell><![CDATA[-89.3]]></cell><cell><![CDATA[ ]]></cell><cell><![CDATA[]]></cell><cell><![CDATA[16,523,925.0]]></cell><cell><![CDATA[0.0]]></cell><cell><![CDATA[16,612,653.0]]></cell><cell><![CDATA[0.0]]></cell><cell><![CDATA[ 
            PPUB]]></cell><cell><![CDATA[
                ]]></cell></row>
<row><cell><![CDATA[2]]></cell><cell><![CDATA[SI CAB JAKARTA]]></cell><cell><![CDATA[0717030077
                        
                         Penjelasan]]></cell><cell><![CDATA[17074_PEARL OIL (SEBUKU) LIMITED Provision Of Technical Inspection Services (CO)]]></cell><cell><![CDATA[PEARL OIL (SEBUKU) LTD]]></cell><cell><![CDATA[
            
            ]]></cell><cell><![CDATA[
            
            ]]></cell><cell><![CDATA[03-07-2017]]></cell><cell><![CDATA[02-07-2021]]></cell><cell><![CDATA[4,156,950,000.0]]></cell><cell><![CDATA[1,471,345,714.3]]></cell><cell><![CDATA[1,122,436,128.8]]></cell><cell><![CDATA[348,909,585.5]]></cell><cell><![CDATA[1,226,121,428.6]]></cell><cell><![CDATA[1,035,447,777.4]]></cell><cell><![CDATA[190,673,651.2]]></cell><cell><![CDATA[890,725,000.0]]></cell><cell><![CDATA[841,522,818.0]]></cell><cell><![CDATA[49,202,182.0]]></cell><cell><![CDATA[60.54]]></cell><cell><![CDATA[72.65]]></cell><cell><![CDATA[75.0]]></cell><cell><![CDATA[81.3]]></cell><cell><![CDATA[80 %]]></cell><cell><![CDATA[]]></cell><cell><![CDATA[965,662,500.0]]></cell><cell><![CDATA[0.0]]></cell><cell><![CDATA[73,463,000.0]]></cell><cell><![CDATA[0.0]]></cell><cell><![CDATA[ 
            PPUB]]></cell><cell><![CDATA[
                ]]></cell></row>
<row><cell><![CDATA[3]]></cell><cell><![CDATA[SI CAB JAKARTA]]></cell><cell><![CDATA[0718020063
                        
                         Penjelasan]]></cell><cell><![CDATA[18047_KOM2_FREEPORT INDONESIA_Survey & Laboratory for Various Commodities]]></cell><cell><![CDATA[FREEPORT INDONESIA]]></cell><cell><![CDATA[
            
            ]]></cell><cell><![CDATA[
            
            ]]></cell><cell><![CDATA[03-08-2018]]></cell><cell><![CDATA[28-02-2021]]></cell><cell><![CDATA[3,408,900,000.0]]></cell><cell><![CDATA[1,602,155,200.0]]></cell><cell><![CDATA[993,650,239.6]]></cell><cell><![CDATA[608,504,960.4]]></cell><cell><![CDATA[1,602,155,200.0]]></cell><cell><![CDATA[993,650,239.6]]></cell><cell><![CDATA[608,504,960.4]]></cell><cell><![CDATA[549,000,000.0]]></cell><cell><![CDATA[398,961,442.0]]></cell><cell><![CDATA[150,038,558.0]]></cell><cell><![CDATA[34.27]]></cell><cell><![CDATA[34.27]]></cell><cell><![CDATA[40.2]]></cell><cell><![CDATA[40.2]]></cell><cell><![CDATA[100 %]]></cell><cell><![CDATA[]]></cell><cell><![CDATA[132,000,000.0]]></cell><cell><![CDATA[0.0]]></cell><cell><![CDATA[78,200,000.0]]></cell><cell><![CDATA[0.0]]></cell><cell><![CDATA[ 
            PPUB]]></cell><cell><![CDATA[
                ]]></cell></row>
<row><cell><![CDATA[4]]></cell><cell><![CDATA[SI CAB JAKARTA]]></cell><cell><![CDATA[0718020145
                        
                         Penjelasan]]></cell><cell><![CDATA[18155_PERTAMINA RU III PLAJU _Studi dan Penyusunan Dokumen Amdal Project Crude Open Access RU III Plaju]]></cell><cell><![CDATA[PERTAMINA (PERSERO)]]></cell><cell><![CDATA[SR
            
            ]]></cell><cell><![CDATA[
            
            ]]></cell><cell><![CDATA[01-09-2018]]></cell><cell><![CDATA[31-10-2021]]></cell><cell><![CDATA[3,401,737,500.0]]></cell><cell><![CDATA[2,146,737,500.0]]></cell><cell><![CDATA[0.0]]></cell><cell><![CDATA[2,146,737,500.0]]></cell><cell><![CDATA[0.0]]></cell><cell><![CDATA[0.0]]></cell><cell><![CDATA[0.0]]></cell><cell><![CDATA[0.0]]></cell><cell><![CDATA[0.0]]></cell><cell><![CDATA[0.0]]></cell><cell><![CDATA[0]]></cell><cell><![CDATA[0]]></cell><cell><![CDATA[0.0]]></cell><cell><![CDATA[0.0]]></cell><cell><![CDATA[0 %]]></cell><cell><![CDATA[]]></cell><cell><![CDATA[0.0]]></cell><cell><![CDATA[0.0]]></cell><cell><![CDATA[0.0]]></cell><cell><![CDATA[0.0]]></cell><cell><![CDATA[ 
            PPUB]]></cell><cell><![CDATA[
                ]]></cell></row>
<row><cell><![CDATA[5]]></cell><cell><![CDATA[SI CAB JAKARTA]]></cell><cell><![CDATA[0718040034
                        
                         Penjelasan]]></cell><cell><![CDATA[18027_POSO ENERGI_project Monitoring Pembangunan PLTA Poso 515MW (Poso-1 Stage-1 4 x 30 MW+Poso-2 Stage-2 4 X 50 MW & PLTA Poso2  Existing 3 x 65 MW)]]></cell><cell><![CDATA[POSO ENERGI SATU PAMONA]]></cell><cell><![CDATA[
            
            ]]></cell><cell><![CDATA[
            
            ]]></cell><cell><![CDATA[05-02-2018]]></cell><cell><![CDATA[31-03-2022]]></cell><cell><![CDATA[2,776,000,000.0]]></cell><cell><![CDATA[325,004,571.4]]></cell><cell><![CDATA[246,418,648.7]]></cell><cell><![CDATA[78,585,922.8]]></cell><cell><![CDATA[270,837,142.9]]></cell><cell><![CDATA[243,001,009.5]]></cell><cell><![CDATA[27,836,133.4]]></cell><cell><![CDATA[202,224,000.0]]></cell><cell><![CDATA[132,675,985.0]]></cell><cell><![CDATA[69,548,015.0]]></cell><cell><![CDATA[62.22]]></cell><cell><![CDATA[74.67]]></cell><cell><![CDATA[53.8]]></cell><cell><![CDATA[54.6]]></cell><cell><![CDATA[80 %]]></cell><cell><![CDATA[]]></cell><cell><![CDATA[222,446,400.0]]></cell><cell><![CDATA[0.0]]></cell><cell><![CDATA[37,050,000.0]]></cell><cell><![CDATA[0.0]]></cell><cell><![CDATA[ 
            PPUB]]></cell><cell><![CDATA[
                ]]></cell></row>
<row><cell><![CDATA[6]]></cell><cell><![CDATA[SI CAB JAKARTA]]></cell><cell><![CDATA[0718040051
                        
                         Penjelasan]]></cell><cell><![CDATA[18031_PETRONAS_NDT & INSPECTION SERVICES KEPODANG &BUKIT TUA]]></cell><cell><![CDATA[PETRONAS]]></cell><cell><![CDATA[
            
            ]]></cell><cell><![CDATA[
            
            ]]></cell><cell><![CDATA[20-02-2018]]></cell><cell><![CDATA[19-02-2022]]></cell><cell><![CDATA[11,195,000,000.0]]></cell><cell><![CDATA[3,060,230,000.0]]></cell><cell><![CDATA[2,437,907,302.5]]></cell><cell><![CDATA[622,322,697.5]]></cell><cell><![CDATA[3,060,230,000.0]]></cell><cell><![CDATA[2,253,460,326.5]]></cell><cell><![CDATA[806,769,673.5]]></cell><cell><![CDATA[683,600,000.0]]></cell><cell><![CDATA[674,881,041.0]]></cell><cell><![CDATA[8,718,959.0]]></cell><cell><![CDATA[22.34]]></cell><cell><![CDATA[22.34]]></cell><cell><![CDATA[27.7]]></cell><cell><![CDATA[30.0]]></cell><cell><![CDATA[0 %]]></cell><cell><![CDATA[]]></cell><cell><![CDATA[378,950,000.0]]></cell><cell><![CDATA[63,000,000.0]]></cell><cell><![CDATA[144,160,000.0]]></cell><cell><![CDATA[317,049,379.0]]></cell><cell><![CDATA[ 
            PPUB]]></cell><cell><![CDATA[
                ]]></cell></row>
<row><cell><![CDATA[7]]></cell><cell><![CDATA[SI CAB JAKARTA]]></cell><cell><![CDATA[0719020131
                        
                         Penjelasan]]></cell><cell><![CDATA[19112_KOM1_PHE Ogan Komering_Pekerjaan manajemen Proyek QA/QC & NDT Services]]></cell><cell><![CDATA[PHE RAJA TEMPIRAI]]></cell><cell><![CDATA[
            
            ]]></cell><cell><![CDATA[
            
            ]]></cell><cell><![CDATA[21-10-2019]]></cell><cell><![CDATA[20-10-2022]]></cell><cell><![CDATA[6,033,210,000.0]]></cell><cell><![CDATA[774,397,500.0]]></cell><cell><![CDATA[705,178,597.8]]></cell><cell><![CDATA[69,218,902.2]]></cell><cell><![CDATA[483,998,437.5]]></cell><cell><![CDATA[427,237,763.2]]></cell><cell><![CDATA[56,760,674.3]]></cell><cell><![CDATA[839,235,000.0]]></cell><cell><![CDATA[588,892,340.0]]></cell><cell><![CDATA[250,342,660.0]]></cell><cell><![CDATA[108.37]]></cell><cell><![CDATA[173.4]]></cell><cell><![CDATA[83.5]]></cell><cell><![CDATA[137.8]]></cell><cell><![CDATA[0 %]]></cell><cell><![CDATA[]]></cell><cell><![CDATA[456,343,250.0]]></cell><cell><![CDATA[662,375,000.0]]></cell><cell><![CDATA[81,315,000.0]]></cell><cell><![CDATA[0.0]]></cell><cell><![CDATA[ 
            PPUB]]></cell><cell><![CDATA[
                ]]></cell></row>
<row><cell><![CDATA[8]]></cell><cell><![CDATA[SI CAB JAKARTA]]></cell><cell><![CDATA[0719020142
                        
                         Penjelasan]]></cell><cell><![CDATA[19111_KOM2_PLN (Pesero) UIP ISJ_Penyusunan dan Sertifikat ISO 9001:2015]]></cell><cell><![CDATA[PLN (PERSERO) UIP INTERKONEKSI SUMATERA JAWA (UIP IV)]]></cell><cell><![CDATA[
            
            ]]></cell><cell><![CDATA[
            
            ]]></cell><cell><![CDATA[10-10-2019]]></cell><cell><![CDATA[31-03-2021]]></cell><cell><![CDATA[343,475,000.0]]></cell><cell><![CDATA[140,512,500.0]]></cell><cell><![CDATA[75,835,214.0]]></cell><cell><![CDATA[64,677,286.0]]></cell><cell><![CDATA[140,512,500.0]]></cell><cell><![CDATA[75,835,214.0]]></cell><cell><![CDATA[64,677,286.0]]></cell><cell><![CDATA[109,287,500.0]]></cell><cell><![CDATA[14,933,500.0]]></cell><cell><![CDATA[94,354,000.0]]></cell><cell><![CDATA[77.78]]></cell><cell><![CDATA[77.78]]></cell><cell><![CDATA[19.7]]></cell><cell><![CDATA[19.7]]></cell><cell><![CDATA[0 %]]></cell><cell><![CDATA[]]></cell><cell><![CDATA[0.0]]></cell><cell><![CDATA[0.0]]></cell><cell><![CDATA[0.0]]></cell><cell><![CDATA[0.0]]></cell><cell><![CDATA[ 
            PPUB]]></cell><cell><![CDATA[
                ]]></cell></row>
<row><cell><![CDATA[9]]></cell><cell><![CDATA[SI CAB JAKARTA]]></cell><cell><![CDATA[0719040036
                        
                         Penjelasan]]></cell><cell><![CDATA[19024_KOM1_Pertamina EP CEPU_ Inspeksi QA/QC untuk Material dan Peralatan Proyek JTB]]></cell><cell><![CDATA[PERTAMINA EP CEPU ADK]]></cell><cell><![CDATA[
            
            ]]></cell><cell><![CDATA[
            
            ]]></cell><cell><![CDATA[02-10-2017]]></cell><cell><![CDATA[31-05-2021]]></cell><cell><![CDATA[56,961,500,000.0]]></cell><cell><![CDATA[22,543,080,000.0]]></cell><cell><![CDATA[11,114,516,277.4]]></cell><cell><![CDATA[11,428,563,722.6]]></cell><cell><![CDATA[22,543,080,000.0]]></cell><cell><![CDATA[9,800,169,731.5]]></cell><cell><![CDATA[12,742,910,268.5]]></cell><cell><![CDATA[10,804,787,500.0]]></cell><cell><![CDATA[5,887,958,094.0]]></cell><cell><![CDATA[4,916,829,406.0]]></cell><cell><![CDATA[47.93]]></cell><cell><![CDATA[47.93]]></cell><cell><![CDATA[53.0]]></cell><cell><![CDATA[60.1]]></cell><cell><![CDATA[0 %]]></cell><cell><![CDATA[]]></cell><cell><![CDATA[15,220,947,500.0]]></cell><cell><![CDATA[0.0]]></cell><cell><![CDATA[92,865,000.0]]></cell><cell><![CDATA[0.0]]></cell><cell><![CDATA[ 
            PPUB]]></cell><cell><![CDATA[
                ]]></cell></row>
<row><cell><![CDATA[10]]></cell><cell><![CDATA[SI CAB JAKARTA]]></cell><cell><![CDATA[0719040093
                        
                         Penjelasan]]></cell><cell><![CDATA[19078_KOM2_Cahaya Mining Services_Supervisi Loading, Unloading HSD dan Analisa]]></cell><cell><![CDATA[CAHAYA MINING SERVICES]]></cell><cell><![CDATA[SR
            
            ]]></cell><cell><![CDATA[
            
            ]]></cell><cell><![CDATA[22-07-2019]]></cell><cell><![CDATA[23-08-2019]]></cell><cell><![CDATA[22,000,000.0]]></cell><cell><![CDATA[0.0]]></cell><cell><![CDATA[10,100,000.0]]></cell><cell><![CDATA[-10,100,000.0]]></cell><cell><![CDATA[0.0]]></cell><cell><![CDATA[10,100,000.0]]></cell><cell><![CDATA[-10,100,000.0]]></cell><cell><![CDATA[0.0]]></cell><cell><![CDATA[0.0]]></cell><cell><![CDATA[0.0]]></cell><cell><![CDATA[0]]></cell><cell><![CDATA[0]]></cell><cell><![CDATA[0.0]]></cell><cell><![CDATA[0.0]]></cell><cell><![CDATA[ ]]></cell><cell><![CDATA[]]></cell><cell><![CDATA[0.0]]></cell><cell><![CDATA[0.0]]></cell><cell><![CDATA[0.0]]></cell><cell><![CDATA[10,100,000.0]]></cell><cell><![CDATA[ 
            PPUB]]></cell><cell><![CDATA[
                ]]></cell></row>
<row><cell><![CDATA[11]]></cell><cell><![CDATA[SI CAB JAKARTA]]></cell><cell><![CDATA[0719040097
                        
                         Penjelasan]]></cell><cell><![CDATA[19057_KOM1_Kerinci Merangin Hidro_Pekerjaan pengawasan Kredir Investasi Proyek pembangunan HEPP Kerinci Merangin KAP. 4x87,5 MW di Kabupaten Kerinci - jambi]]></cell><cell><![CDATA[KERINCI MERANGIN HYDRO]]></cell><cell><![CDATA[TSR
            
            ]]></cell><cell><![CDATA[TSR
            
            ]]></cell><cell><![CDATA[21-05-2019]]></cell><cell><![CDATA[20-05-2025]]></cell><cell><![CDATA[3,240,000,000.0]]></cell><cell><![CDATA[756,000,000.0]]></cell><cell><![CDATA[518,868,198.3]]></cell><cell><![CDATA[237,131,801.7]]></cell><cell><![CDATA[472,500,000.0]]></cell><cell><![CDATA[343,391,094.7]]></cell><cell><![CDATA[129,108,905.4]]></cell><cell><![CDATA[0.0]]></cell><cell><![CDATA[24,056,469.7]]></cell><cell><![CDATA[-24,056,469.7]]></cell><cell><![CDATA[0]]></cell><cell><![CDATA[0]]></cell><cell><![CDATA[4.6]]></cell><cell><![CDATA[7.0]]></cell><cell><![CDATA[55 %]]></cell><cell><![CDATA[]]></cell><cell><![CDATA[0.0]]></cell><cell><![CDATA[0.0]]></cell><cell><![CDATA[74,445,250.0]]></cell><cell><![CDATA[0.0]]></cell><cell><![CDATA[ 
            PPUB]]></cell><cell><![CDATA[
                ]]></cell></row>
<row><cell><![CDATA[12]]></cell><cell><![CDATA[SI CAB JAKARTA]]></cell><cell><![CDATA[0719040106
                        
                         Penjelasan]]></cell><cell><![CDATA[19090_KOM2_Eka Nusa Dwi Sapta_Draught Survey]]></cell><cell><![CDATA[EKA NUSA DWI SAPTA]]></cell><cell><![CDATA[
            
            ]]></cell><cell><![CDATA[
            
            ]]></cell><cell><![CDATA[13-10-2020]]></cell><cell><![CDATA[12-08-2021]]></cell><cell><![CDATA[72,000,000.0]]></cell><cell><![CDATA[46,000,000.0]]></cell><cell><![CDATA[32,624,000.0]]></cell><cell><![CDATA[13,376,000.0]]></cell><cell><![CDATA[24,700,000.0]]></cell><cell><![CDATA[18,776,000.0]]></cell><cell><![CDATA[5,924,000.0]]></cell><cell><![CDATA[12,000,000.0]]></cell><cell><![CDATA[7,000,000.0]]></cell><cell><![CDATA[5,000,000.0]]></cell><cell><![CDATA[26.09]]></cell><cell><![CDATA[48.58]]></cell><cell><![CDATA[21.5]]></cell><cell><![CDATA[37.3]]></cell><cell><![CDATA[ ]]></cell><cell><![CDATA[]]></cell><cell><![CDATA[6,800,000.0]]></cell><cell><![CDATA[0.0]]></cell><cell><![CDATA[0.0]]></cell><cell><![CDATA[0.0]]></cell><cell><![CDATA[ 
            PPUB]]></cell><cell><![CDATA[
                ]]></cell></row>
<row><cell><![CDATA[13]]></cell><cell><![CDATA[SI CAB JAKARTA]]></cell><cell><![CDATA[0719040118
                        
                         Penjelasan]]></cell><cell><![CDATA[19097_KOM1_Premier Oil_ Provision Of NDT and QA/QC Inspection Services]]></cell><cell><![CDATA[PREMIER OIL NATUNA SEA BV]]></cell><cell><![CDATA[
            
            ]]></cell><cell><![CDATA[
            
            ]]></cell><cell><![CDATA[19-08-2019]]></cell><cell><![CDATA[18-08-2022]]></cell><cell><![CDATA[43,838,737,170.0]]></cell><cell><![CDATA[8,491,985,466.8]]></cell><cell><![CDATA[10,111,990,298.0]]></cell><cell><![CDATA[-1,620,004,831.1]]></cell><cell><![CDATA[8,491,985,466.8]]></cell><cell><![CDATA[7,001,126,460.0]]></cell><cell><![CDATA[1,490,859,006.9]]></cell><cell><![CDATA[4,730,120,000.0]]></cell><cell><![CDATA[4,357,367,578.0]]></cell><cell><![CDATA[372,752,422.0]]></cell><cell><![CDATA[55.7]]></cell><cell><![CDATA[55.7]]></cell><cell><![CDATA[43.1]]></cell><cell><![CDATA[62.2]]></cell><cell><![CDATA[0 %]]></cell><cell><![CDATA[]]></cell><cell><![CDATA[1,807,228,500.0]]></cell><cell><![CDATA[616,200,000.0]]></cell><cell><![CDATA[303,937,500.0]]></cell><cell><![CDATA[3,110,099,230.0]]></cell><cell><![CDATA[ 
            PPUB]]></cell><cell><![CDATA[
                ]]></cell></row>
<row><cell><![CDATA[14]]></cell><cell><![CDATA[SI CAB JAKARTA]]></cell><cell><![CDATA[0719040144
                        
                         Penjelasan]]></cell><cell><![CDATA[19130_KOM1_PT.NPCT1_SERTIFIKASI DISNAKER DAN HUBLA]]></cell><cell><![CDATA[NEW PRIOK CONTAINER TERMINAL ONE]]></cell><cell><![CDATA[
            
            ]]></cell><cell><![CDATA[
            
            ]]></cell><cell><![CDATA[21-11-2019]]></cell><cell><![CDATA[21-02-2022]]></cell><cell><![CDATA[76,875,000.0]]></cell><cell><![CDATA[48,125,000.0]]></cell><cell><![CDATA[29,134,222.0]]></cell><cell><![CDATA[18,990,778.0]]></cell><cell><![CDATA[36,093,750.0]]></cell><cell><![CDATA[20,733,797.0]]></cell><cell><![CDATA[15,359,953.0]]></cell><cell><![CDATA[21,087,500.0]]></cell><cell><![CDATA[11,945,000.0]]></cell><cell><![CDATA[9,142,500.0]]></cell><cell><![CDATA[43.82]]></cell><cell><![CDATA[58.42]]></cell><cell><![CDATA[41.0]]></cell><cell><![CDATA[57.6]]></cell><cell><![CDATA[0 %]]></cell><cell><![CDATA[]]></cell><cell><![CDATA[0.0]]></cell><cell><![CDATA[0.0]]></cell><cell><![CDATA[9,990,000.0]]></cell><cell><![CDATA[0.0]]></cell><cell><![CDATA[ 
            PPUB]]></cell><cell><![CDATA[
                ]]></cell></row>
<row><cell><![CDATA[15]]></cell><cell><![CDATA[SI CAB JAKARTA]]></cell><cell><![CDATA[0719040153
                        
                         Penjelasan]]></cell><cell><![CDATA[19133_KOM1_SPEKTRA MEGA SEMESTA_KERJASAMA ASSET INTEGRITY ENGINEERING, INSPECTION AND CERTIFICATIONSERVICES MEDCO E&P NATUNA PROJECT]]></cell><cell><![CDATA[SPEKTRA MEGAH SEMESTA]]></cell><cell><![CDATA[TSR
            
            ]]></cell><cell><![CDATA[TSR
            
            ]]></cell><cell><![CDATA[31-12-2019]]></cell><cell><![CDATA[30-11-2021]]></cell><cell><![CDATA[780,000,000.0]]></cell><cell><![CDATA[216,666,666.0]]></cell><cell><![CDATA[103,238,882.0]]></cell><cell><![CDATA[113,427,784.0]]></cell><cell><![CDATA[216,666,666.0]]></cell><cell><![CDATA[100,183,325.0]]></cell><cell><![CDATA[116,483,341.0]]></cell><cell><![CDATA[0.0]]></cell><cell><![CDATA[0.0]]></cell><cell><![CDATA[0.0]]></cell><cell><![CDATA[0]]></cell><cell><![CDATA[0]]></cell><cell><![CDATA[0.0]]></cell><cell><![CDATA[0.0]]></cell><cell><![CDATA[0 %]]></cell><cell><![CDATA[]]></cell><cell><![CDATA[66,000,000.0]]></cell><cell><![CDATA[0.0]]></cell><cell><![CDATA[0.0]]></cell><cell><![CDATA[0.0]]></cell><cell><![CDATA[ 
            PPUB]]></cell><cell><![CDATA[
                ]]></cell></row>
<row><cell><![CDATA[16]]></cell><cell><![CDATA[SI CAB JAKARTA]]></cell><cell><![CDATA[0719990009
                        
                         Penjelasan]]></cell><cell><![CDATA[SHGI]]></cell><cell><![CDATA[AICHIKIKI AUTOPARTS INDONESIA]]></cell><cell><![CDATA[SR
            
            ]]></cell><cell><![CDATA[
            
            ]]></cell><cell><![CDATA[01-01-2019]]></cell><cell><![CDATA[31-12-2019]]></cell><cell><![CDATA[25,000,000,000.0]]></cell><cell><![CDATA[0.0]]></cell><cell><![CDATA[45,000,000.0]]></cell><cell><![CDATA[-45,000,000.0]]></cell><cell><![CDATA[0.0]]></cell><cell><![CDATA[45,000,000.0]]></cell><cell><![CDATA[-45,000,000.0]]></cell><cell><![CDATA[0.0]]></cell><cell><![CDATA[0.0]]></cell><cell><![CDATA[0.0]]></cell><cell><![CDATA[0]]></cell><cell><![CDATA[0]]></cell><cell><![CDATA[0.0]]></cell><cell><![CDATA[0.0]]></cell><cell><![CDATA[ ]]></cell><cell><![CDATA[]]></cell><cell><![CDATA[71,595,000.0]]></cell><cell><![CDATA[0.0]]></cell><cell><![CDATA[138,752,608.0]]></cell><cell><![CDATA[0.0]]></cell><cell><![CDATA[ 
            PPUB]]></cell><cell><![CDATA[
                ]]></cell></row>
<row><cell><![CDATA[17]]></cell><cell><![CDATA[SI CAB JAKARTA]]></cell><cell><![CDATA[0720010034
                        
                         Penjelasan]]></cell><cell><![CDATA[KOM2_20035_BPDAS dan Hutan Lindung Ketahun_PENGAWASAN DAN PENILAIAN PEMELIHARAAN TANAMAN RHL (P1) PAKET 1 SELUAS 2.950 HA PADA WILAYAH KPHL MEKAKAU SAKA KABUPATEN OGAN KOMERING ULU SELATAN (OKUS) PROVINSI SUMATERA SELATAN]]></cell><cell><![CDATA[BPDAS DAN HUTAN LINDUNG KETAHUN]]></cell><cell><![CDATA[
            
            ]]></cell><cell><![CDATA[
            
            ]]></cell><cell><![CDATA[13-03-2020]]></cell><cell><![CDATA[31-01-2021]]></cell><cell><![CDATA[1,204,000,000.0]]></cell><cell><![CDATA[180,600,000.0]]></cell><cell><![CDATA[71,083,013.0]]></cell><cell><![CDATA[109,516,987.0]]></cell><cell><![CDATA[180,600,000.0]]></cell><cell><![CDATA[71,083,013.0]]></cell><cell><![CDATA[109,516,987.0]]></cell><cell><![CDATA[180,600,000.0]]></cell><cell><![CDATA[52,129,375.0]]></cell><cell><![CDATA[128,470,625.0]]></cell><cell><![CDATA[100]]></cell><cell><![CDATA[100]]></cell><cell><![CDATA[73.3]]></cell><cell><![CDATA[73.3]]></cell><cell><![CDATA[100 %]]></cell><cell><![CDATA[]]></cell><cell><![CDATA[0.0]]></cell><cell><![CDATA[0.0]]></cell><cell><![CDATA[24,000,000.0]]></cell><cell><![CDATA[0.0]]></cell><cell><![CDATA[ 
            PPUB]]></cell><cell><![CDATA[
                ]]></cell></row>
<row><cell><![CDATA[18]]></cell><cell><![CDATA[SI CAB JAKARTA]]></cell><cell><![CDATA[0720020013
                        
                         Penjelasan]]></cell><cell><![CDATA[20011_PT PERTAMINA MOR II_KONSULTANSI STUDI & PENYUSUNAN DOKUMEN AMDAL PEMASANGAN JALUR PIPA TBBM PULAU BAAI]]></cell><cell><![CDATA[PERTAMINA (PERSERO) MOR II]]></cell><cell><![CDATA[
            
            ]]></cell><cell><![CDATA[
            
            ]]></cell><cell><![CDATA[01-02-2020]]></cell><cell><![CDATA[28-02-2021]]></cell><cell><![CDATA[1,357,752,000.0]]></cell><cell><![CDATA[689,700,000.0]]></cell><cell><![CDATA[551,541,714.0]]></cell><cell><![CDATA[138,158,286.0]]></cell><cell><![CDATA[689,700,000.0]]></cell><cell><![CDATA[551,541,714.0]]></cell><cell><![CDATA[138,158,286.0]]></cell><cell><![CDATA[689,700,000.0]]></cell><cell><![CDATA[551,079,735.0]]></cell><cell><![CDATA[138,620,265.0]]></cell><cell><![CDATA[100]]></cell><cell><![CDATA[100]]></cell><cell><![CDATA[99.9]]></cell><cell><![CDATA[99.9]]></cell><cell><![CDATA[100 %]]></cell><cell><![CDATA[]]></cell><cell><![CDATA[758,670,000.0]]></cell><cell><![CDATA[0.0]]></cell><cell><![CDATA[15,000,000.0]]></cell><cell><![CDATA[0.0]]></cell><cell><![CDATA[ 
            PPUB]]></cell><cell><![CDATA[
                ]]></cell></row>
<row><cell><![CDATA[19]]></cell><cell><![CDATA[SI CAB JAKARTA]]></cell><cell><![CDATA[0720020024
                        
                         Penjelasan]]></cell><cell><![CDATA[20022_KOM1_PT PERTAMINA MOR II_STUDI PENYUSUNAN DOKUMEN AMDAL PENGEMBANGAN TBBM JAMBI]]></cell><cell><![CDATA[PERTAMINA (PERSERO) MOR II]]></cell><cell><![CDATA[
            
            ]]></cell><cell><![CDATA[
            
            ]]></cell><cell><![CDATA[01-02-2020]]></cell><cell><![CDATA[28-02-2021]]></cell><cell><![CDATA[1,352,200,000.0]]></cell><cell><![CDATA[406,100,000.0]]></cell><cell><![CDATA[533,426,834.0]]></cell><cell><![CDATA[-127,326,834.0]]></cell><cell><![CDATA[406,100,000.0]]></cell><cell><![CDATA[533,426,834.0]]></cell><cell><![CDATA[-127,326,834.0]]></cell><cell><![CDATA[676,100,000.0]]></cell><cell><![CDATA[533,330,120.0]]></cell><cell><![CDATA[142,769,880.0]]></cell><cell><![CDATA[166.49]]></cell><cell><![CDATA[166.49]]></cell><cell><![CDATA[100.0]]></cell><cell><![CDATA[100.0]]></cell><cell><![CDATA[100 %]]></cell><cell><![CDATA[]]></cell><cell><![CDATA[743,710,000.0]]></cell><cell><![CDATA[0.0]]></cell><cell><![CDATA[0.0]]></cell><cell><![CDATA[0.0]]></cell><cell><![CDATA[ 
            PPUB]]></cell><cell><![CDATA[
                ]]></cell></row>
<row><cell><![CDATA[20]]></cell><cell><![CDATA[SI CAB JAKARTA]]></cell><cell><![CDATA[0720020038
                        
                         Penjelasan]]></cell><cell><![CDATA[20091_KOM1_PT PERTAMINA MOR III_PEKERJAAN JASA KONSULTANSI PERIZINAN, DAN PENYUSUNAN ENGINEERING ALIGNMENT SHEET PADA PEMBANGUNAN TBBM & JALUR PIPA SUKABUMI]]></cell><cell><![CDATA[PERTAMINA (PERSERO) MOR III]]></cell><cell><![CDATA[
            
            ]]></cell><cell><![CDATA[
            
            ]]></cell><cell><![CDATA[01-05-2020]]></cell><cell><![CDATA[31-08-2021]]></cell><cell><![CDATA[8,256,700,000.0]]></cell><cell><![CDATA[8,256,700,000.0]]></cell><cell><![CDATA[5,976,247,820.0]]></cell><cell><![CDATA[2,280,452,180.0]]></cell><cell><![CDATA[5,111,603,500.0]]></cell><cell><![CDATA[5,298,685,862.2]]></cell><cell><![CDATA[-187,082,362.2]]></cell><cell><![CDATA[1,407,600,000.0]]></cell><cell><![CDATA[1,223,479,265.0]]></cell><cell><![CDATA[184,120,735.0]]></cell><cell><![CDATA[17.05]]></cell><cell><![CDATA[27.54]]></cell><cell><![CDATA[20.5]]></cell><cell><![CDATA[23.1]]></cell><cell><![CDATA[42 %]]></cell><cell><![CDATA[]]></cell><cell><![CDATA[1,548,360,000.0]]></cell><cell><![CDATA[0.0]]></cell><cell><![CDATA[86,150,000.0]]></cell><cell><![CDATA[1,242,250,000.0]]></cell><cell><![CDATA[ 
            PPUB]]></cell><cell><![CDATA[
                ]]></cell></row>
<row><cell><![CDATA[21]]></cell><cell><![CDATA[SI CAB JAKARTA]]></cell><cell><![CDATA[0720020069
                        
                         Penjelasan]]></cell><cell><![CDATA[20068_KOM1_PERTAMINA MOR III_SURVEY SOUNDING BATIMETIK PERAIRAN TUKS MIGAS TANJUNG SEKONG]]></cell><cell><![CDATA[PERTAMINA (PERSERO) MOR III]]></cell><cell><![CDATA[SR
            
            ]]></cell><cell><![CDATA[SR
            
            ]]></cell><cell><![CDATA[01-08-2020]]></cell><cell><![CDATA[30-09-2020]]></cell><cell><![CDATA[132,000,000.0]]></cell><cell><![CDATA[0.0]]></cell><cell><![CDATA[1,570,000.0]]></cell><cell><![CDATA[-1,570,000.0]]></cell><cell><![CDATA[0.0]]></cell><cell><![CDATA[1,570,000.0]]></cell><cell><![CDATA[-1,570,000.0]]></cell><cell><![CDATA[0.0]]></cell><cell><![CDATA[1,570,000.0]]></cell><cell><![CDATA[-1,570,000.0]]></cell><cell><![CDATA[0]]></cell><cell><![CDATA[0]]></cell><cell><![CDATA[100.0]]></cell><cell><![CDATA[100.0]]></cell><cell><![CDATA[ ]]></cell><cell><![CDATA[]]></cell><cell><![CDATA[0.0]]></cell><cell><![CDATA[0.0]]></cell><cell><![CDATA[0.0]]></cell><cell><![CDATA[0.0]]></cell><cell><![CDATA[ 
            PPUB]]></cell><cell><![CDATA[
                ]]></cell></row>
<row><cell><![CDATA[22]]></cell><cell><![CDATA[SI CAB JAKARTA]]></cell><cell><![CDATA[0720020075
                        
                         Penjelasan]]></cell><cell><![CDATA[20070_KOM1_PT PERTAMINA (PERSERO)_pekerjaan Jasa Survey Metocean, Bathymetry, Soil Investigasi, Analisa Kajian Kelayakan dan FEED Jetty di TBBM Manggis]]></cell><cell><![CDATA[PERTAMINA (PERSERO)]]></cell><cell><![CDATA[TSR
            
            ]]></cell><cell><![CDATA[TSR
            
            ]]></cell><cell><![CDATA[12-08-2020]]></cell><cell><![CDATA[09-04-2021]]></cell><cell><![CDATA[5,190,000,000.0]]></cell><cell><![CDATA[5,190,000,000.0]]></cell><cell><![CDATA[4,203,375,000.0]]></cell><cell><![CDATA[986,625,000.0]]></cell><cell><![CDATA[5,190,000,000.0]]></cell><cell><![CDATA[4,189,836,875.0]]></cell><cell><![CDATA[1,000,163,125.0]]></cell><cell><![CDATA[0.0]]></cell><cell><![CDATA[345,965.0]]></cell><cell><![CDATA[-345,965.0]]></cell><cell><![CDATA[0]]></cell><cell><![CDATA[0]]></cell><cell><![CDATA[0.0]]></cell><cell><![CDATA[0.0]]></cell><cell><![CDATA[80 %]]></cell><cell><![CDATA[]]></cell><cell><![CDATA[0.0]]></cell><cell><![CDATA[0.0]]></cell><cell><![CDATA[14,100,000.0]]></cell><cell><![CDATA[2,137,723,295.0]]></cell><cell><![CDATA[ 
            PPUB]]></cell><cell><![CDATA[
                ]]></cell></row>
<row><cell><![CDATA[23]]></cell><cell><![CDATA[SI CAB JAKARTA]]></cell><cell><![CDATA[0720020079
                        
                         Penjelasan]]></cell><cell><![CDATA[20055_KOM1_ PT PERTAMINA (PERSERO) MOR I_KONSULTASI SURVEY METOCEAN, BATHMETRY, DAN REVIEW DESIGN DERMAGA BESERTA FEED VERTICAL TURBINE PUMP]]></cell><cell><![CDATA[PERTAMINA (PERSERO) MOR I]]></cell><cell><![CDATA[
            
            ]]></cell><cell><![CDATA[
            
            ]]></cell><cell><![CDATA[01-07-2020]]></cell><cell><![CDATA[31-01-2021]]></cell><cell><![CDATA[6,623,670,000.0]]></cell><cell><![CDATA[6,623,670,000.0]]></cell><cell><![CDATA[5,100,842,039.0]]></cell><cell><![CDATA[1,522,827,961.0]]></cell><cell><![CDATA[6,623,670,000.0]]></cell><cell><![CDATA[5,100,842,039.0]]></cell><cell><![CDATA[1,522,827,961.0]]></cell><cell><![CDATA[5,451,050,000.0]]></cell><cell><![CDATA[4,142,726,174.0]]></cell><cell><![CDATA[1,308,323,826.0]]></cell><cell><![CDATA[82.3]]></cell><cell><![CDATA[82.3]]></cell><cell><![CDATA[81.2]]></cell><cell><![CDATA[81.2]]></cell><cell><![CDATA[100 %]]></cell><cell><![CDATA[]]></cell><cell><![CDATA[2,668,655,000.0]]></cell><cell><![CDATA[0.0]]></cell><cell><![CDATA[10,200,000.0]]></cell><cell><![CDATA[0.0]]></cell><cell><![CDATA[ 
            PPUB]]></cell><cell><![CDATA[
                ]]></cell></row>
<row><cell><![CDATA[24]]></cell><cell><![CDATA[SI CAB JAKARTA]]></cell><cell><![CDATA[0720020080
                        
                         Penjelasan]]></cell><cell><![CDATA[20078_KOM2_PT. Kereta Commuter Indonesa_Pengadaan Jasa Survey Roda KRL Bekas]]></cell><cell><![CDATA[KERETA COMMUTER INDONESIA]]></cell><cell><![CDATA[
            
            ]]></cell><cell><![CDATA[
            
            ]]></cell><cell><![CDATA[01-09-2020]]></cell><cell><![CDATA[31-12-2020]]></cell><cell><![CDATA[189,058,533.0]]></cell><cell><![CDATA[14,873,896.0]]></cell><cell><![CDATA[14,144,741.0]]></cell><cell><![CDATA[729,155.0]]></cell><cell><![CDATA[14,873,896.0]]></cell><cell><![CDATA[14,144,741.0]]></cell><cell><![CDATA[729,155.0]]></cell><cell><![CDATA[14,873,896.0]]></cell><cell><![CDATA[13,644,741.0]]></cell><cell><![CDATA[1,229,155.0]]></cell><cell><![CDATA[100]]></cell><cell><![CDATA[100]]></cell><cell><![CDATA[96.5]]></cell><cell><![CDATA[96.5]]></cell><cell><![CDATA[ ]]></cell><cell><![CDATA[]]></cell><cell><![CDATA[0.0]]></cell><cell><![CDATA[0.0]]></cell><cell><![CDATA[5,500,000.0]]></cell><cell><![CDATA[0.0]]></cell><cell><![CDATA[ 
            PPUB]]></cell><cell><![CDATA[
                ]]></cell></row>
<row><cell><![CDATA[25]]></cell><cell><![CDATA[SI CAB JAKARTA]]></cell><cell><![CDATA[0720020095
                        
                         Penjelasan]]></cell><cell><![CDATA[20097_KOM2_PLN (Persero) UID Lampung_Izin Lingkungan Pengelolaan Limbah B3 PLN UP3 Kotabumi]]></cell><cell><![CDATA[PLN (PERSERO) UNIT INDUK DISTRIBUSI LAMPUNG]]></cell><cell><![CDATA[
            
            ]]></cell><cell><![CDATA[
            
            ]]></cell><cell><![CDATA[01-10-2020]]></cell><cell><![CDATA[31-01-2021]]></cell><cell><![CDATA[36,363,636.0]]></cell><cell><![CDATA[36,363,636.0]]></cell><cell><![CDATA[24,360,000.0]]></cell><cell><![CDATA[12,003,636.0]]></cell><cell><![CDATA[36,363,636.0]]></cell><cell><![CDATA[24,360,000.0]]></cell><cell><![CDATA[12,003,636.0]]></cell><cell><![CDATA[36,363,637.0]]></cell><cell><![CDATA[24,137,950.0]]></cell><cell><![CDATA[12,225,687.0]]></cell><cell><![CDATA[100]]></cell><cell><![CDATA[100]]></cell><cell><![CDATA[99.1]]></cell><cell><![CDATA[99.1]]></cell><cell><![CDATA[ ]]></cell><cell><![CDATA[]]></cell><cell><![CDATA[40,000,000.0]]></cell><cell><![CDATA[0.0]]></cell><cell><![CDATA[0.0]]></cell><cell><![CDATA[0.0]]></cell><cell><![CDATA[ 
            PPUB]]></cell><cell><![CDATA[
                ]]></cell></row>
<row><cell><![CDATA[26]]></cell><cell><![CDATA[SI CAB JAKARTA]]></cell><cell><![CDATA[0720020096
                        
                         Penjelasan]]></cell><cell><![CDATA[20098_KOM2_PLN (Persero) UID Lampung_Izin Lingkungan Pengelolaan Limbah B3 (Kalianda dan Gedung Rajabasa)]]></cell><cell><![CDATA[PLN (PERSERO) UNIT INDUK DISTRIBUSI LAMPUNG]]></cell><cell><![CDATA[
            
            ]]></cell><cell><![CDATA[
            
            ]]></cell><cell><![CDATA[01-10-2020]]></cell><cell><![CDATA[31-01-2021]]></cell><cell><![CDATA[72,727,273.0]]></cell><cell><![CDATA[72,727,273.0]]></cell><cell><![CDATA[48,720,000.0]]></cell><cell><![CDATA[24,007,273.0]]></cell><cell><![CDATA[72,727,273.0]]></cell><cell><![CDATA[48,720,000.0]]></cell><cell><![CDATA[24,007,273.0]]></cell><cell><![CDATA[72,727,273.0]]></cell><cell><![CDATA[48,442,150.0]]></cell><cell><![CDATA[24,285,123.0]]></cell><cell><![CDATA[100]]></cell><cell><![CDATA[100]]></cell><cell><![CDATA[99.4]]></cell><cell><![CDATA[99.4]]></cell><cell><![CDATA[ ]]></cell><cell><![CDATA[]]></cell><cell><![CDATA[80,000,000.0]]></cell><cell><![CDATA[0.0]]></cell><cell><![CDATA[0.0]]></cell><cell><![CDATA[0.0]]></cell><cell><![CDATA[ 
            PPUB]]></cell><cell><![CDATA[
                ]]></cell></row>
<row><cell><![CDATA[27]]></cell><cell><![CDATA[SI CAB JAKARTA]]></cell><cell><![CDATA[0720020097
                        
                         Penjelasan]]></cell><cell><![CDATA[20088_KOM1_PERTAMINA MOR II_STUDI PENYUSUNAN DOKUMEN EVALUASI LINGKUNGAN HIDUP PEMBANGUNAN JALUR PIPA FT PULAU BAAI]]></cell><cell><![CDATA[PERTAMINA (PERSERO) MOR II]]></cell><cell><![CDATA[
            
            ]]></cell><cell><![CDATA[
            
            ]]></cell><cell><![CDATA[01-10-2020]]></cell><cell><![CDATA[28-02-2021]]></cell><cell><![CDATA[298,155,000.0]]></cell><cell><![CDATA[298,155,000.0]]></cell><cell><![CDATA[214,400,000.0]]></cell><cell><![CDATA[83,755,000.0]]></cell><cell><![CDATA[298,155,000.0]]></cell><cell><![CDATA[214,400,000.0]]></cell><cell><![CDATA[83,755,000.0]]></cell><cell><![CDATA[298,155,000.0]]></cell><cell><![CDATA[214,351,655.0]]></cell><cell><![CDATA[83,803,345.0]]></cell><cell><![CDATA[100]]></cell><cell><![CDATA[100]]></cell><cell><![CDATA[100.0]]></cell><cell><![CDATA[100.0]]></cell><cell><![CDATA[100 %]]></cell><cell><![CDATA[]]></cell><cell><![CDATA[0.0]]></cell><cell><![CDATA[0.0]]></cell><cell><![CDATA[0.0]]></cell><cell><![CDATA[0.0]]></cell><cell><![CDATA[ 
            PPUB]]></cell><cell><![CDATA[
                ]]></cell></row>
<row><cell><![CDATA[28]]></cell><cell><![CDATA[SI CAB JAKARTA]]></cell><cell><![CDATA[0720020104
                        
                         Penjelasan]]></cell><cell><![CDATA[20106_KOM2_PT. Krakatau Steel_Resertifikasi Boiler BFC # 2]]></cell><cell><![CDATA[KRAKATAU STEEL (PERSERO) TBK]]></cell><cell><![CDATA[TSR
            
            ]]></cell><cell><![CDATA[TSR
            
            ]]></cell><cell><![CDATA[02-12-2020]]></cell><cell><![CDATA[28-02-2021]]></cell><cell><![CDATA[60,435,600.0]]></cell><cell><![CDATA[60,435,800.0]]></cell><cell><![CDATA[43,292,000.0]]></cell><cell><![CDATA[17,143,800.0]]></cell><cell><![CDATA[60,435,800.0]]></cell><cell><![CDATA[43,292,000.0]]></cell><cell><![CDATA[17,143,800.0]]></cell><cell><![CDATA[0.0]]></cell><cell><![CDATA[0.0]]></cell><cell><![CDATA[0.0]]></cell><cell><![CDATA[0]]></cell><cell><![CDATA[0]]></cell><cell><![CDATA[0.0]]></cell><cell><![CDATA[0.0]]></cell><cell><![CDATA[0 %]]></cell><cell><![CDATA[]]></cell><cell><![CDATA[0.0]]></cell><cell><![CDATA[0.0]]></cell><cell><![CDATA[0.0]]></cell><cell><![CDATA[25,222,859.0]]></cell><cell><![CDATA[ 
            PPUB]]></cell><cell><![CDATA[
                ]]></cell></row>
<row><cell><![CDATA[29]]></cell><cell><![CDATA[SI CAB JAKARTA]]></cell><cell><![CDATA[0720020106
                        
                         Penjelasan]]></cell><cell><![CDATA[20103_KOM2_PT. Krakatau Steel_Resertifikasi Boiler BF # 1]]></cell><cell><![CDATA[KRAKATAU STEEL (PERSERO) TBK]]></cell><cell><![CDATA[
            
            ]]></cell><cell><![CDATA[
            
            ]]></cell><cell><![CDATA[20-11-2020]]></cell><cell><![CDATA[31-01-2021]]></cell><cell><![CDATA[60,435,600.0]]></cell><cell><![CDATA[60,435,600.0]]></cell><cell><![CDATA[43,292,000.0]]></cell><cell><![CDATA[17,143,600.0]]></cell><cell><![CDATA[60,435,600.0]]></cell><cell><![CDATA[43,292,000.0]]></cell><cell><![CDATA[17,143,600.0]]></cell><cell><![CDATA[60,435,600.0]]></cell><cell><![CDATA[42,991,416.0]]></cell><cell><![CDATA[17,444,184.0]]></cell><cell><![CDATA[100]]></cell><cell><![CDATA[100]]></cell><cell><![CDATA[99.3]]></cell><cell><![CDATA[99.3]]></cell><cell><![CDATA[0 %]]></cell><cell><![CDATA[]]></cell><cell><![CDATA[66,479,160.0]]></cell><cell><![CDATA[0.0]]></cell><cell><![CDATA[0.0]]></cell><cell><![CDATA[0.0]]></cell><cell><![CDATA[ 
            PPUB]]></cell><cell><![CDATA[
                ]]></cell></row>
<row><cell><![CDATA[30]]></cell><cell><![CDATA[SI CAB JAKARTA]]></cell><cell><![CDATA[0720020107
                        
                         Penjelasan]]></cell><cell><![CDATA[20109_KOM2_PT. Krakatau Steel_Resertifikasi Boiler D]]></cell><cell><![CDATA[KRAKATAU STEEL (PERSERO) TBK]]></cell><cell><![CDATA[TSR
            
            ]]></cell><cell><![CDATA[TSR
            
            ]]></cell><cell><![CDATA[01-12-2020]]></cell><cell><![CDATA[30-05-2021]]></cell><cell><![CDATA[65,000,000.0]]></cell><cell><![CDATA[65,000,000.0]]></cell><cell><![CDATA[46,609,000.0]]></cell><cell><![CDATA[18,391,000.0]]></cell><cell><![CDATA[65,000,000.0]]></cell><cell><![CDATA[46,609,000.0]]></cell><cell><![CDATA[18,391,000.0]]></cell><cell><![CDATA[0.0]]></cell><cell><![CDATA[0.0]]></cell><cell><![CDATA[0.0]]></cell><cell><![CDATA[0]]></cell><cell><![CDATA[0]]></cell><cell><![CDATA[0.0]]></cell><cell><![CDATA[0.0]]></cell><cell><![CDATA[0 %]]></cell><cell><![CDATA[]]></cell><cell><![CDATA[0.0]]></cell><cell><![CDATA[0.0]]></cell><cell><![CDATA[6,885,000.0]]></cell><cell><![CDATA[10,731,200.0]]></cell><cell><![CDATA[ 
            PPUB]]></cell><cell><![CDATA[
                ]]></cell></row>
<row><cell><![CDATA[31]]></cell><cell><![CDATA[SI CAB JAKARTA]]></cell><cell><![CDATA[0720020108
                        
                         Penjelasan]]></cell><cell><![CDATA[20110_KOM2_PT. Krakatau Steel_Resertiikasi Tanki D]]></cell><cell><![CDATA[KRAKATAU STEEL (PERSERO) TBK]]></cell><cell><![CDATA[
            
            ]]></cell><cell><![CDATA[
            
            ]]></cell><cell><![CDATA[01-12-2020]]></cell><cell><![CDATA[28-02-2021]]></cell><cell><![CDATA[30,543,100.0]]></cell><cell><![CDATA[30,543,100.0]]></cell><cell><![CDATA[21,914,000.0]]></cell><cell><![CDATA[8,629,100.0]]></cell><cell><![CDATA[30,543,100.0]]></cell><cell><![CDATA[21,914,000.0]]></cell><cell><![CDATA[8,629,100.0]]></cell><cell><![CDATA[30,543,100.0]]></cell><cell><![CDATA[21,912,500.0]]></cell><cell><![CDATA[8,630,600.0]]></cell><cell><![CDATA[100]]></cell><cell><![CDATA[100]]></cell><cell><![CDATA[100.0]]></cell><cell><![CDATA[100.0]]></cell><cell><![CDATA[0 %]]></cell><cell><![CDATA[]]></cell><cell><![CDATA[33,597,410.0]]></cell><cell><![CDATA[0.0]]></cell><cell><![CDATA[0.0]]></cell><cell><![CDATA[0.0]]></cell><cell><![CDATA[ 
            PPUB]]></cell><cell><![CDATA[
                ]]></cell></row>
<row><cell><![CDATA[32]]></cell><cell><![CDATA[SI CAB JAKARTA]]></cell><cell><![CDATA[0720020110
                        
                         Penjelasan]]></cell><cell><![CDATA[20112_KOM2_PT. Krakatau Steel_Resertifikasi Boiler BFC #3]]></cell><cell><![CDATA[KRAKATAU STEEL (PERSERO) TBK]]></cell><cell><![CDATA[TSR
            
            ]]></cell><cell><![CDATA[TSR
            
            ]]></cell><cell><![CDATA[14-12-2020]]></cell><cell><![CDATA[28-02-2021]]></cell><cell><![CDATA[48,584,000.0]]></cell><cell><![CDATA[48,584,000.0]]></cell><cell><![CDATA[34,554,000.0]]></cell><cell><![CDATA[14,030,000.0]]></cell><cell><![CDATA[48,584,000.0]]></cell><cell><![CDATA[34,554,000.0]]></cell><cell><![CDATA[14,030,000.0]]></cell><cell><![CDATA[0.0]]></cell><cell><![CDATA[0.0]]></cell><cell><![CDATA[0.0]]></cell><cell><![CDATA[0]]></cell><cell><![CDATA[0]]></cell><cell><![CDATA[0.0]]></cell><cell><![CDATA[0.0]]></cell><cell><![CDATA[0 %]]></cell><cell><![CDATA[]]></cell><cell><![CDATA[0.0]]></cell><cell><![CDATA[0.0]]></cell><cell><![CDATA[6,705,000.0]]></cell><cell><![CDATA[12,250,000.0]]></cell><cell><![CDATA[ 
            PPUB]]></cell><cell><![CDATA[
                ]]></cell></row>
<row><cell><![CDATA[33]]></cell><cell><![CDATA[SI CAB JAKARTA]]></cell><cell><![CDATA[0720040007
                        
                         Penjelasan]]></cell><cell><![CDATA[KOM1_20004_PEKERJAAN RESERTIFIKASI PERALATAN]]></cell><cell><![CDATA[SOUTH PACIFIC VISCOSE]]></cell><cell><![CDATA[
            
            ]]></cell><cell><![CDATA[
            
            ]]></cell><cell><![CDATA[01-01-2020]]></cell><cell><![CDATA[28-02-2021]]></cell><cell><![CDATA[2,999,000,000.0]]></cell><cell><![CDATA[2,534,136,363.0]]></cell><cell><![CDATA[1,701,950,459.0]]></cell><cell><![CDATA[832,185,904.0]]></cell><cell><![CDATA[2,534,136,363.0]]></cell><cell><![CDATA[1,701,950,459.0]]></cell><cell><![CDATA[832,185,904.0]]></cell><cell><![CDATA[33,700,000.0]]></cell><cell><![CDATA[23,007,470.0]]></cell><cell><![CDATA[10,692,530.0]]></cell><cell><![CDATA[1.33]]></cell><cell><![CDATA[1.33]]></cell><cell><![CDATA[1.4]]></cell><cell><![CDATA[1.4]]></cell><cell><![CDATA[100 %]]></cell><cell><![CDATA[]]></cell><cell><![CDATA[0.0]]></cell><cell><![CDATA[0.0]]></cell><cell><![CDATA[1,700,000.0]]></cell><cell><![CDATA[0.0]]></cell><cell><![CDATA[ 
            PPUB]]></cell><cell><![CDATA[
                ]]></cell></row>
<row><cell><![CDATA[34]]></cell><cell><![CDATA[SI CAB JAKARTA]]></cell><cell><![CDATA[0720040027
                        
                         Penjelasan]]></cell><cell><![CDATA[20015_KOM2_Freeport Indonesia_Quality & Quantity Nomination for Diesel Fuel Shipment]]></cell><cell><![CDATA[FREEPORT INDONESIA]]></cell><cell><![CDATA[
            
            ]]></cell><cell><![CDATA[
            
            ]]></cell><cell><![CDATA[26-02-2020]]></cell><cell><![CDATA[31-01-2021]]></cell><cell><![CDATA[724,000,000.0]]></cell><cell><![CDATA[532,520,000.0]]></cell><cell><![CDATA[358,846,900.0]]></cell><cell><![CDATA[173,673,100.0]]></cell><cell><![CDATA[532,520,000.0]]></cell><cell><![CDATA[358,846,900.0]]></cell><cell><![CDATA[173,673,100.0]]></cell><cell><![CDATA[265,500,000.0]]></cell><cell><![CDATA[178,919,380.0]]></cell><cell><![CDATA[86,580,620.0]]></cell><cell><![CDATA[49.86]]></cell><cell><![CDATA[49.86]]></cell><cell><![CDATA[49.9]]></cell><cell><![CDATA[49.9]]></cell><cell><![CDATA[100 %]]></cell><cell><![CDATA[]]></cell><cell><![CDATA[292,050,000.0]]></cell><cell><![CDATA[0.0]]></cell><cell><![CDATA[4,600,000.0]]></cell><cell><![CDATA[0.0]]></cell><cell><![CDATA[ 
            PPUB]]></cell><cell><![CDATA[
                ]]></cell></row>
<row><cell><![CDATA[35]]></cell><cell><![CDATA[SI CAB JAKARTA]]></cell><cell><![CDATA[0720040029
                        
                         Penjelasan]]></cell><cell><![CDATA[20023_KOM1_PT SOUTH PACIFIC VISCOSE_CERTIFICATION VESSEL AND TANK]]></cell><cell><![CDATA[SOUTH PACIFIC VISCOSE]]></cell><cell><![CDATA[
            
            ]]></cell><cell><![CDATA[
            
            ]]></cell><cell><![CDATA[01-01-2020]]></cell><cell><![CDATA[31-01-2021]]></cell><cell><![CDATA[315,000,000.0]]></cell><cell><![CDATA[120,000,000.0]]></cell><cell><![CDATA[145,867,548.0]]></cell><cell><![CDATA[-25,867,548.0]]></cell><cell><![CDATA[120,000,000.0]]></cell><cell><![CDATA[145,867,548.0]]></cell><cell><![CDATA[-25,867,548.0]]></cell><cell><![CDATA[142,500,000.0]]></cell><cell><![CDATA[123,834,205.0]]></cell><cell><![CDATA[18,665,795.0]]></cell><cell><![CDATA[118.75]]></cell><cell><![CDATA[118.75]]></cell><cell><![CDATA[84.9]]></cell><cell><![CDATA[84.9]]></cell><cell><![CDATA[0 %]]></cell><cell><![CDATA[]]></cell><cell><![CDATA[0.0]]></cell><cell><![CDATA[0.0]]></cell><cell><![CDATA[0.0]]></cell><cell><![CDATA[0.0]]></cell><cell><![CDATA[ 
            PPUB]]></cell><cell><![CDATA[
                ]]></cell></row>
<row><cell><![CDATA[36]]></cell><cell><![CDATA[SI CAB JAKARTA]]></cell><cell><![CDATA[0720040033
                        
                         Penjelasan]]></cell><cell><![CDATA[KOM2_20029_Panca Amara Utama_PROYEK JASA PEMBUATAN LAPORAN PELAKSANAAN RKL/RPLDI BANGGAI AMONIAK PLAN TAHUN 2020 (TRIWULANAN)]]></cell><cell><![CDATA[PANCA AMARA UTAMA]]></cell><cell><![CDATA[
            
            ]]></cell><cell><![CDATA[
            
            ]]></cell><cell><![CDATA[01-01-2020]]></cell><cell><![CDATA[31-01-2021]]></cell><cell><![CDATA[1,698,200,000.0]]></cell><cell><![CDATA[849,100,000.0]]></cell><cell><![CDATA[1,121,312,430.0]]></cell><cell><![CDATA[-272,212,430.0]]></cell><cell><![CDATA[849,100,000.0]]></cell><cell><![CDATA[1,121,312,430.0]]></cell><cell><![CDATA[-272,212,430.0]]></cell><cell><![CDATA[849,100,000.0]]></cell><cell><![CDATA[688,482,120.0]]></cell><cell><![CDATA[160,617,880.0]]></cell><cell><![CDATA[100]]></cell><cell><![CDATA[100]]></cell><cell><![CDATA[61.4]]></cell><cell><![CDATA[61.4]]></cell><cell><![CDATA[100 %]]></cell><cell><![CDATA[]]></cell><cell><![CDATA[84,910,000.0]]></cell><cell><![CDATA[0.0]]></cell><cell><![CDATA[0.0]]></cell><cell><![CDATA[0.0]]></cell><cell><![CDATA[ 
            PPUB]]></cell><cell><![CDATA[
                ]]></cell></row>
<row><cell><![CDATA[37]]></cell><cell><![CDATA[SI CAB JAKARTA]]></cell><cell><![CDATA[0720040039
                        
                         Penjelasan]]></cell><cell><![CDATA[20090_KOM1_PERTAMINA EP ASET 3_JASA KONSULTANSI MANAJEMEN PROYEK & KONSTRUKSI SURFACE FACILITIES]]></cell><cell><![CDATA[PERTAMINA EP]]></cell><cell><![CDATA[
            
            ]]></cell><cell><![CDATA[
            
            ]]></cell><cell><![CDATA[02-05-2020]]></cell><cell><![CDATA[02-05-2022]]></cell><cell><![CDATA[9,800,000,000.0]]></cell><cell><![CDATA[7,945,149,000.0]]></cell><cell><![CDATA[6,381,042,772.5]]></cell><cell><![CDATA[1,564,106,227.5]]></cell><cell><![CDATA[3,310,478,750.0]]></cell><cell><![CDATA[3,241,279,108.1]]></cell><cell><![CDATA[69,199,641.9]]></cell><cell><![CDATA[3,632,888,791.0]]></cell><cell><![CDATA[1,698,892,556.0]]></cell><cell><![CDATA[1,933,996,235.0]]></cell><cell><![CDATA[45.72]]></cell><cell><![CDATA[109.74]]></cell><cell><![CDATA[26.6]]></cell><cell><![CDATA[52.4]]></cell><cell><![CDATA[54 %]]></cell><cell><![CDATA[]]></cell><cell><![CDATA[2,565,428,569.0]]></cell><cell><![CDATA[0.0]]></cell><cell><![CDATA[393,942,000.0]]></cell><cell><![CDATA[3,341,218,936.0]]></cell><cell><![CDATA[ 
            PPUB]]></cell><cell><![CDATA[
                ]]></cell></row>
<row><cell><![CDATA[38]]></cell><cell><![CDATA[SI CAB JAKARTA]]></cell><cell><![CDATA[0720040040
                        
                         Penjelasan]]></cell><cell><![CDATA[20086_KOM1_PT PERTAMINA MOR V_ Jasa Konsultansi Survey Soil Investigation di TBBM Ampenan, Tuban, Madiun, Tanjungwangi, Atapupu ISG, Ende dan BPG Gresik]]></cell><cell><![CDATA[PERTAMINA (PERSERO) MOR V]]></cell><cell><![CDATA[TSR
            
            ]]></cell><cell><![CDATA[TSR
            
            ]]></cell><cell><![CDATA[01-03-2020]]></cell><cell><![CDATA[31-03-2021]]></cell><cell><![CDATA[2,260,428,716.0]]></cell><cell><![CDATA[2,260,428,716.0]]></cell><cell><![CDATA[1,606,705,168.0]]></cell><cell><![CDATA[653,723,548.0]]></cell><cell><![CDATA[2,260,428,716.0]]></cell><cell><![CDATA[1,606,705,168.0]]></cell><cell><![CDATA[653,723,548.0]]></cell><cell><![CDATA[0.0]]></cell><cell><![CDATA[0.0]]></cell><cell><![CDATA[0.0]]></cell><cell><![CDATA[0]]></cell><cell><![CDATA[0]]></cell><cell><![CDATA[0.0]]></cell><cell><![CDATA[0.0]]></cell><cell><![CDATA[100 %]]></cell><cell><![CDATA[]]></cell><cell><![CDATA[0.0]]></cell><cell><![CDATA[0.0]]></cell><cell><![CDATA[3,000,000.0]]></cell><cell><![CDATA[1,596,993,642.0]]></cell><cell><![CDATA[ 
            PPUB]]></cell><cell><![CDATA[
                ]]></cell></row>
<row><cell><![CDATA[39]]></cell><cell><![CDATA[SI CAB JAKARTA]]></cell><cell><![CDATA[0720040047
                        
                         Penjelasan]]></cell><cell><![CDATA[KOM2_20043_Satria Bahana Sarana_Uji Emisi Alat Berat 14 titik x 8 kali Pengujian]]></cell><cell><![CDATA[SATRIA BAHANA SARANA]]></cell><cell><![CDATA[
            
            ]]></cell><cell><![CDATA[
            
            ]]></cell><cell><![CDATA[01-04-2020]]></cell><cell><![CDATA[30-04-2022]]></cell><cell><![CDATA[179,200,000.0]]></cell><cell><![CDATA[44,800,000.0]]></cell><cell><![CDATA[202,649,857.2]]></cell><cell><![CDATA[-157,849,857.2]]></cell><cell><![CDATA[44,800,000.0]]></cell><cell><![CDATA[200,459,857.2]]></cell><cell><![CDATA[-155,659,857.1]]></cell><cell><![CDATA[22,400,000.0]]></cell><cell><![CDATA[14,766,000.0]]></cell><cell><![CDATA[7,634,000.0]]></cell><cell><![CDATA[50]]></cell><cell><![CDATA[50]]></cell><cell><![CDATA[7.3]]></cell><cell><![CDATA[7.4]]></cell><cell><![CDATA[0 %]]></cell><cell><![CDATA[]]></cell><cell><![CDATA[49,280,000.0]]></cell><cell><![CDATA[0.0]]></cell><cell><![CDATA[0.0]]></cell><cell><![CDATA[0.0]]></cell><cell><![CDATA[ 
            PPUB]]></cell><cell><![CDATA[
                ]]></cell></row>
<row><cell><![CDATA[40]]></cell><cell><![CDATA[SI CAB JAKARTA]]></cell><cell><![CDATA[0720040050
                        
                         Penjelasan]]></cell><cell><![CDATA[KOM2_20040_BEST_SIP dan SIPA]]></cell><cell><![CDATA[BUKIT ENERGI SERVIS TERPADU]]></cell><cell><![CDATA[SR
            
            ]]></cell><cell><![CDATA[
            
            ]]></cell><cell><![CDATA[02-04-2020]]></cell><cell><![CDATA[31-08-2020]]></cell><cell><![CDATA[27,500,000.0]]></cell><cell><![CDATA[0.0]]></cell><cell><![CDATA[50,000.0]]></cell><cell><![CDATA[-50,000.0]]></cell><cell><![CDATA[0.0]]></cell><cell><![CDATA[50,000.0]]></cell><cell><![CDATA[-50,000.0]]></cell><cell><![CDATA[0.0]]></cell><cell><![CDATA[0.0]]></cell><cell><![CDATA[0.0]]></cell><cell><![CDATA[0]]></cell><cell><![CDATA[0]]></cell><cell><![CDATA[0.0]]></cell><cell><![CDATA[0.0]]></cell><cell><![CDATA[ ]]></cell><cell><![CDATA[]]></cell><cell><![CDATA[0.0]]></cell><cell><![CDATA[0.0]]></cell><cell><![CDATA[0.0]]></cell><cell><![CDATA[0.0]]></cell><cell><![CDATA[ 
            PPUB]]></cell><cell><![CDATA[
                ]]></cell></row>
<row><cell><![CDATA[41]]></cell><cell><![CDATA[SI CAB JAKARTA]]></cell><cell><![CDATA[0720040057
                        
                         Penjelasan]]></cell><cell><![CDATA[20049_KOM1_JAKARTA INTERNATIONAL CONTAINER TERMINAL_RESERTIFIKASI PESAWAT ANGKAT ANGKUT HUBLA DAN DISNAKER]]></cell><cell><![CDATA[JAKARTA INTERNATIONAL CONTAINER TERMINAL]]></cell><cell><![CDATA[
            
            ]]></cell><cell><![CDATA[
            
            ]]></cell><cell><![CDATA[12-06-2020]]></cell><cell><![CDATA[31-01-2021]]></cell><cell><![CDATA[1,092,460,000.0]]></cell><cell><![CDATA[1,092,460,000.0]]></cell><cell><![CDATA[751,657,945.0]]></cell><cell><![CDATA[340,802,055.0]]></cell><cell><![CDATA[1,092,460,000.0]]></cell><cell><![CDATA[751,657,945.0]]></cell><cell><![CDATA[340,802,055.0]]></cell><cell><![CDATA[1,092,460,000.0]]></cell><cell><![CDATA[744,195,920.0]]></cell><cell><![CDATA[348,264,080.0]]></cell><cell><![CDATA[100]]></cell><cell><![CDATA[100]]></cell><cell><![CDATA[99.0]]></cell><cell><![CDATA[99.0]]></cell><cell><![CDATA[100 %]]></cell><cell><![CDATA[]]></cell><cell><![CDATA[0.0]]></cell><cell><![CDATA[0.0]]></cell><cell><![CDATA[0.0]]></cell><cell><![CDATA[0.0]]></cell><cell><![CDATA[ 
            PPUB]]></cell><cell><![CDATA[
                ]]></cell></row>
<row><cell><![CDATA[42]]></cell><cell><![CDATA[SI CAB JAKARTA]]></cell><cell><![CDATA[0720040061
                        
                         Penjelasan]]></cell><cell><![CDATA[KOM1_20058_PT SUPREME ENERGY_PROVISION OF ON CALL INSPECTION SERVICES]]></cell><cell><![CDATA[SUPREME ENERGY]]></cell><cell><![CDATA[
            
            ]]></cell><cell><![CDATA[
            
            ]]></cell><cell><![CDATA[01-06-2020]]></cell><cell><![CDATA[31-05-2021]]></cell><cell><![CDATA[250,000,000.0]]></cell><cell><![CDATA[127,650,000.0]]></cell><cell><![CDATA[89,582,293.0]]></cell><cell><![CDATA[38,067,707.0]]></cell><cell><![CDATA[127,650,000.0]]></cell><cell><![CDATA[89,582,293.0]]></cell><cell><![CDATA[38,067,707.0]]></cell><cell><![CDATA[21,600,000.0]]></cell><cell><![CDATA[16,373,000.0]]></cell><cell><![CDATA[5,227,000.0]]></cell><cell><![CDATA[16.92]]></cell><cell><![CDATA[16.92]]></cell><cell><![CDATA[18.3]]></cell><cell><![CDATA[18.3]]></cell><cell><![CDATA[0 %]]></cell><cell><![CDATA[]]></cell><cell><![CDATA[23,760,000.0]]></cell><cell><![CDATA[163,900,000.0]]></cell><cell><![CDATA[0.0]]></cell><cell><![CDATA[0.0]]></cell><cell><![CDATA[ 
            PPUB]]></cell><cell><![CDATA[
                ]]></cell></row>
<row><cell><![CDATA[43]]></cell><cell><![CDATA[SI CAB JAKARTA]]></cell><cell><![CDATA[0720040063
                        
                         Penjelasan]]></cell><cell><![CDATA[20061_KOM2_PT. Chandra Asih Petrochemical_Annual Contract for Resestification of Static Requirement, Safety Device Lifting Equipment at all CAP Plants 2020 (3000017184)]]></cell><cell><![CDATA[CHANDRA ASRI PETROCHEMICAL TBK]]></cell><cell><![CDATA[
            
            ]]></cell><cell><![CDATA[
            
            ]]></cell><cell><![CDATA[05-08-2020]]></cell><cell><![CDATA[31-12-2021]]></cell><cell><![CDATA[818,000,000.0]]></cell><cell><![CDATA[285,975,000.0]]></cell><cell><![CDATA[247,721,582.8]]></cell><cell><![CDATA[38,253,417.3]]></cell><cell><![CDATA[285,975,000.0]]></cell><cell><![CDATA[247,721,582.8]]></cell><cell><![CDATA[38,253,417.3]]></cell><cell><![CDATA[53,600,000.0]]></cell><cell><![CDATA[43,648,800.0]]></cell><cell><![CDATA[9,951,200.0]]></cell><cell><![CDATA[18.74]]></cell><cell><![CDATA[18.74]]></cell><cell><![CDATA[17.6]]></cell><cell><![CDATA[17.6]]></cell><cell><![CDATA[41 %]]></cell><cell><![CDATA[]]></cell><cell><![CDATA[58,960,000.0]]></cell><cell><![CDATA[0.0]]></cell><cell><![CDATA[2,000,000.0]]></cell><cell><![CDATA[0.0]]></cell><cell><![CDATA[ 
            PPUB]]></cell><cell><![CDATA[
                ]]></cell></row>
<row><cell><![CDATA[44]]></cell><cell><![CDATA[SI CAB JAKARTA]]></cell><cell><![CDATA[0720040064
                        
                         Penjelasan]]></cell><cell><![CDATA[20064_KOM2_PT.RECKITT BENCKISER INDONESIA_PROJECT BOREWELL]]></cell><cell><![CDATA[RECKITT BENCKISER INDONESIA]]></cell><cell><![CDATA[TSR
            
            ]]></cell><cell><![CDATA[TSR
            
            ]]></cell><cell><![CDATA[01-08-2020]]></cell><cell><![CDATA[31-01-2021]]></cell><cell><![CDATA[575,000,000.0]]></cell><cell><![CDATA[460,000,000.0]]></cell><cell><![CDATA[314,315,630.0]]></cell><cell><![CDATA[145,684,370.0]]></cell><cell><![CDATA[460,000,000.0]]></cell><cell><![CDATA[314,315,630.0]]></cell><cell><![CDATA[145,684,370.0]]></cell><cell><![CDATA[0.0]]></cell><cell><![CDATA[0.0]]></cell><cell><![CDATA[0.0]]></cell><cell><![CDATA[0]]></cell><cell><![CDATA[0]]></cell><cell><![CDATA[0.0]]></cell><cell><![CDATA[0.0]]></cell><cell><![CDATA[100 %]]></cell><cell><![CDATA[]]></cell><cell><![CDATA[0.0]]></cell><cell><![CDATA[0.0]]></cell><cell><![CDATA[3,050,000.0]]></cell><cell><![CDATA[183,150,000.0]]></cell><cell><![CDATA[ 
            PPUB]]></cell><cell><![CDATA[
                ]]></cell></row>
<row><cell><![CDATA[45]]></cell><cell><![CDATA[SI CAB JAKARTA]]></cell><cell><![CDATA[0720040067
                        
                         Penjelasan]]></cell><cell><![CDATA[20062_KOM2_PT. Soci Mas_Sertifikasi layak Operasi 7 Unit Genset]]></cell><cell><![CDATA[SOCI MAS]]></cell><cell><![CDATA[
            
            ]]></cell><cell><![CDATA[
            
            ]]></cell><cell><![CDATA[15-07-2020]]></cell><cell><![CDATA[28-02-2021]]></cell><cell><![CDATA[110,000,000.0]]></cell><cell><![CDATA[24,000,000.0]]></cell><cell><![CDATA[19,223,723.0]]></cell><cell><![CDATA[4,776,277.0]]></cell><cell><![CDATA[24,000,000.0]]></cell><cell><![CDATA[19,223,723.0]]></cell><cell><![CDATA[4,776,277.0]]></cell><cell><![CDATA[24,000,000.0]]></cell><cell><![CDATA[19,223,723.0]]></cell><cell><![CDATA[4,776,277.0]]></cell><cell><![CDATA[100]]></cell><cell><![CDATA[100]]></cell><cell><![CDATA[100.0]]></cell><cell><![CDATA[100.0]]></cell><cell><![CDATA[0 %]]></cell><cell><![CDATA[]]></cell><cell><![CDATA[0.0]]></cell><cell><![CDATA[0.0]]></cell><cell><![CDATA[0.0]]></cell><cell><![CDATA[0.0]]></cell><cell><![CDATA[ 
            PPUB]]></cell><cell><![CDATA[
                ]]></cell></row>
<row><cell><![CDATA[46]]></cell><cell><![CDATA[SI CAB JAKARTA]]></cell><cell><![CDATA[0720040068
                        
                         Penjelasan]]></cell><cell><![CDATA[20066_KOM1_PT SOUTH PACIFIC VISCOSE_NDT & UT FLAW TESTING]]></cell><cell><![CDATA[SOUTH PACIFIC VISCOSE]]></cell><cell><![CDATA[TSR
            
            ]]></cell><cell><![CDATA[TSR
            
            ]]></cell><cell><![CDATA[01-08-2020]]></cell><cell><![CDATA[31-05-2021]]></cell><cell><![CDATA[127,500,000.0]]></cell><cell><![CDATA[121,350,000.0]]></cell><cell><![CDATA[67,581,806.0]]></cell><cell><![CDATA[53,768,194.0]]></cell><cell><![CDATA[121,350,000.0]]></cell><cell><![CDATA[67,581,806.0]]></cell><cell><![CDATA[53,768,194.0]]></cell><cell><![CDATA[0.0]]></cell><cell><![CDATA[5,868,126.0]]></cell><cell><![CDATA[-5,868,126.0]]></cell><cell><![CDATA[0]]></cell><cell><![CDATA[0]]></cell><cell><![CDATA[8.7]]></cell><cell><![CDATA[8.7]]></cell><cell><![CDATA[0 %]]></cell><cell><![CDATA[]]></cell><cell><![CDATA[0.0]]></cell><cell><![CDATA[0.0]]></cell><cell><![CDATA[0.0]]></cell><cell><![CDATA[16,188,497.0]]></cell><cell><![CDATA[ 
            PPUB]]></cell><cell><![CDATA[
                ]]></cell></row>
<row><cell><![CDATA[47]]></cell><cell><![CDATA[SI CAB JAKARTA]]></cell><cell><![CDATA[0720040073
                        
                         Penjelasan]]></cell><cell><![CDATA[20071_KOM1_PT MALEA HYDROPOWER_PROJECT MONITORING]]></cell><cell><![CDATA[MALEA HYDROPOWER]]></cell><cell><![CDATA[TSR
            
            ]]></cell><cell><![CDATA[TSR
            
            ]]></cell><cell><![CDATA[01-07-2020]]></cell><cell><![CDATA[31-01-2021]]></cell><cell><![CDATA[300,000,000.0]]></cell><cell><![CDATA[200,000,000.0]]></cell><cell><![CDATA[124,305,633.0]]></cell><cell><![CDATA[75,694,367.0]]></cell><cell><![CDATA[200,000,000.0]]></cell><cell><![CDATA[124,305,633.0]]></cell><cell><![CDATA[75,694,367.0]]></cell><cell><![CDATA[0.0]]></cell><cell><![CDATA[3,243,660.0]]></cell><cell><![CDATA[-3,243,660.0]]></cell><cell><![CDATA[0]]></cell><cell><![CDATA[0]]></cell><cell><![CDATA[2.6]]></cell><cell><![CDATA[2.6]]></cell><cell><![CDATA[100 %]]></cell><cell><![CDATA[]]></cell><cell><![CDATA[110,000,000.0]]></cell><cell><![CDATA[0.0]]></cell><cell><![CDATA[7,400,000.0]]></cell><cell><![CDATA[0.0]]></cell><cell><![CDATA[ 
            PPUB]]></cell><cell><![CDATA[
                ]]></cell></row>
<row><cell><![CDATA[48]]></cell><cell><![CDATA[SI CAB JAKARTA]]></cell><cell><![CDATA[0720040082
                        
                         Penjelasan]]></cell><cell><![CDATA[20074_KOM1_PT SUPREME ENERGY MUARA LABOH_PROVISION OF INSPECTION TECHNICAL EXPERTISE FOR FYI]]></cell><cell><![CDATA[SUPREME ENERGY MUARA LABOH]]></cell><cell><![CDATA[TSR
            
            ]]></cell><cell><![CDATA[TSR
            
            ]]></cell><cell><![CDATA[25-08-2020]]></cell><cell><![CDATA[24-06-2021]]></cell><cell><![CDATA[400,000,000.0]]></cell><cell><![CDATA[204,900,000.0]]></cell><cell><![CDATA[122,159,172.0]]></cell><cell><![CDATA[82,740,828.0]]></cell><cell><![CDATA[204,900,000.0]]></cell><cell><![CDATA[122,159,172.0]]></cell><cell><![CDATA[82,740,828.0]]></cell><cell><![CDATA[0.0]]></cell><cell><![CDATA[0.0]]></cell><cell><![CDATA[0.0]]></cell><cell><![CDATA[0]]></cell><cell><![CDATA[0]]></cell><cell><![CDATA[0.0]]></cell><cell><![CDATA[0.0]]></cell><cell><![CDATA[0 %]]></cell><cell><![CDATA[]]></cell><cell><![CDATA[0.0]]></cell><cell><![CDATA[-163,900,000.0]]></cell><cell><![CDATA[1,350,000.0]]></cell><cell><![CDATA[4,433,310.0]]></cell><cell><![CDATA[ 
            PPUB]]></cell><cell><![CDATA[
                ]]></cell></row>
<row><cell><![CDATA[49]]></cell><cell><![CDATA[SI CAB JAKARTA]]></cell><cell><![CDATA[0720040083
                        
                         Penjelasan]]></cell><cell><![CDATA[20060_KOM2_PT. Panca Amara Utama_Regulation Compliance Recertification 2020]]></cell><cell><![CDATA[PANCA AMARA UTAMA]]></cell><cell><![CDATA[
            
            ]]></cell><cell><![CDATA[
            
            ]]></cell><cell><![CDATA[15-07-2020]]></cell><cell><![CDATA[28-02-2021]]></cell><cell><![CDATA[437,850,000.0]]></cell><cell><![CDATA[68,200,000.0]]></cell><cell><![CDATA[31,000,000.0]]></cell><cell><![CDATA[37,200,000.0]]></cell><cell><![CDATA[68,200,000.0]]></cell><cell><![CDATA[31,000,000.0]]></cell><cell><![CDATA[37,200,000.0]]></cell><cell><![CDATA[68,200,000.0]]></cell><cell><![CDATA[31,000,000.0]]></cell><cell><![CDATA[37,200,000.0]]></cell><cell><![CDATA[100]]></cell><cell><![CDATA[100]]></cell><cell><![CDATA[100.0]]></cell><cell><![CDATA[100.0]]></cell><cell><![CDATA[100 %]]></cell><cell><![CDATA[]]></cell><cell><![CDATA[43,785,000.0]]></cell><cell><![CDATA[0.0]]></cell><cell><![CDATA[0.0]]></cell><cell><![CDATA[0.0]]></cell><cell><![CDATA[ 
            PPUB]]></cell><cell><![CDATA[
                ]]></cell></row>
<row><cell><![CDATA[50]]></cell><cell><![CDATA[SI CAB JAKARTA]]></cell><cell><![CDATA[0720040085
                        
                         Penjelasan]]></cell><cell><![CDATA[20048_KOM2_PT VALE INDONESIA_STRUCTURE ASSET INTEGRITY ASSESMENT]]></cell><cell><![CDATA[VALE INDONESIA TBK]]></cell><cell><![CDATA[
            
            ]]></cell><cell><![CDATA[
            
            ]]></cell><cell><![CDATA[01-07-2020]]></cell><cell><![CDATA[01-07-2022]]></cell><cell><![CDATA[9,026,631,800.0]]></cell><cell><![CDATA[4,710,081,862.8]]></cell><cell><![CDATA[1,766,931,662.7]]></cell><cell><![CDATA[2,943,150,200.1]]></cell><cell><![CDATA[4,710,081,862.8]]></cell><cell><![CDATA[1,766,931,662.7]]></cell><cell><![CDATA[2,943,150,200.1]]></cell><cell><![CDATA[1,491,147,160.0]]></cell><cell><![CDATA[1,259,271,364.0]]></cell><cell><![CDATA[231,875,796.0]]></cell><cell><![CDATA[31.66]]></cell><cell><![CDATA[31.66]]></cell><cell><![CDATA[71.3]]></cell><cell><![CDATA[71.3]]></cell><cell><![CDATA[29 %]]></cell><cell><![CDATA[]]></cell><cell><![CDATA[2,053,899,111.0]]></cell><cell><![CDATA[0.0]]></cell><cell><![CDATA[0.0]]></cell><cell><![CDATA[0.0]]></cell><cell><![CDATA[ 
            PPUB]]></cell><cell><![CDATA[
                ]]></cell></row>
<row><cell><![CDATA[51]]></cell><cell><![CDATA[SI CAB JAKARTA]]></cell><cell><![CDATA[0720040086
                        
                         Penjelasan]]></cell><cell><![CDATA[20083_KOM1_PT BHIMASENA_FACTORY MONTORING INSPECTION]]></cell><cell><![CDATA[BHIMASENA POWER INDONESIA]]></cell><cell><![CDATA[
            
            ]]></cell><cell><![CDATA[
            
            ]]></cell><cell><![CDATA[01-09-2020]]></cell><cell><![CDATA[31-10-2021]]></cell><cell><![CDATA[1,310,200,000.0]]></cell><cell><![CDATA[945,550,000.0]]></cell><cell><![CDATA[355,365,123.6]]></cell><cell><![CDATA[590,184,876.4]]></cell><cell><![CDATA[472,775,000.0]]></cell><cell><![CDATA[293,694,519.0]]></cell><cell><![CDATA[179,080,481.0]]></cell><cell><![CDATA[388,750,000.0]]></cell><cell><![CDATA[234,431,154.0]]></cell><cell><![CDATA[154,318,846.0]]></cell><cell><![CDATA[41.11]]></cell><cell><![CDATA[82.23]]></cell><cell><![CDATA[66.0]]></cell><cell><![CDATA[79.8]]></cell><cell><![CDATA[63 %]]></cell><cell><![CDATA[]]></cell><cell><![CDATA[84,700,000.0]]></cell><cell><![CDATA[0.0]]></cell><cell><![CDATA[13,000,000.0]]></cell><cell><![CDATA[0.0]]></cell><cell><![CDATA[ 
            PPUB]]></cell><cell><![CDATA[
                ]]></cell></row>
<row><cell><![CDATA[52]]></cell><cell><![CDATA[SI CAB JAKARTA]]></cell><cell><![CDATA[0720040087
                        
                         Penjelasan]]></cell><cell><![CDATA[20082_KOM2_PT. Reckitt Benckiser_Dokumen Kedaruratan Pengelolaan Limbah B3]]></cell><cell><![CDATA[RECKITT BENCKISER INDONESIA]]></cell><cell><![CDATA[
            
            ]]></cell><cell><![CDATA[
            
            ]]></cell><cell><![CDATA[01-10-2020]]></cell><cell><![CDATA[31-12-2020]]></cell><cell><![CDATA[135,300,000.0]]></cell><cell><![CDATA[135,300,000.0]]></cell><cell><![CDATA[98,700,000.0]]></cell><cell><![CDATA[36,600,000.0]]></cell><cell><![CDATA[135,300,000.0]]></cell><cell><![CDATA[98,700,000.0]]></cell><cell><![CDATA[36,600,000.0]]></cell><cell><![CDATA[135,300,000.0]]></cell><cell><![CDATA[96,500,000.0]]></cell><cell><![CDATA[38,800,000.0]]></cell><cell><![CDATA[100]]></cell><cell><![CDATA[100]]></cell><cell><![CDATA[97.8]]></cell><cell><![CDATA[97.8]]></cell><cell><![CDATA[ ]]></cell><cell><![CDATA[]]></cell><cell><![CDATA[148,830,000.0]]></cell><cell><![CDATA[0.0]]></cell><cell><![CDATA[2,200,000.0]]></cell><cell><![CDATA[0.0]]></cell><cell><![CDATA[ 
            PPUB]]></cell><cell><![CDATA[
                ]]></cell></row>
<row><cell><![CDATA[53]]></cell><cell><![CDATA[SI CAB JAKARTA]]></cell><cell><![CDATA[0720040092
                        
                         Penjelasan]]></cell><cell><![CDATA[20095_KOM1_PT KALTIM NITRATE INDONESIA_VERIFIKASI DAN WITNESS PEMBUATAN SHELL  AMMONIA STRIPPER 12E003]]></cell><cell><![CDATA[KALTIM NITRATE INDONESIA]]></cell><cell><![CDATA[TSR
            
            ]]></cell><cell><![CDATA[TSR
            
            ]]></cell><cell><![CDATA[09-10-2020]]></cell><cell><![CDATA[30-04-2021]]></cell><cell><![CDATA[75,400,000.0]]></cell><cell><![CDATA[75,400,000.0]]></cell><cell><![CDATA[49,564,919.0]]></cell><cell><![CDATA[25,835,081.0]]></cell><cell><![CDATA[75,400,000.0]]></cell><cell><![CDATA[49,564,919.0]]></cell><cell><![CDATA[25,835,081.0]]></cell><cell><![CDATA[0.0]]></cell><cell><![CDATA[0.0]]></cell><cell><![CDATA[0.0]]></cell><cell><![CDATA[0]]></cell><cell><![CDATA[0]]></cell><cell><![CDATA[0.0]]></cell><cell><![CDATA[0.0]]></cell><cell><![CDATA[0 %]]></cell><cell><![CDATA[]]></cell><cell><![CDATA[0.0]]></cell><cell><![CDATA[0.0]]></cell><cell><![CDATA[0.0]]></cell><cell><![CDATA[29,768,354.0]]></cell><cell><![CDATA[ 
            PPUB]]></cell><cell><![CDATA[
                ]]></cell></row>
<row><cell><![CDATA[54]]></cell><cell><![CDATA[SI CAB JAKARTA]]></cell><cell><![CDATA[0720040094
                        
                         Penjelasan]]></cell><cell><![CDATA[20080_KOM1_MALEA ENERGY_PEKERJAAN SLO]]></cell><cell><![CDATA[MALEA ENERGY]]></cell><cell><![CDATA[TSR
            
            ]]></cell><cell><![CDATA[TSR
            
            ]]></cell><cell><![CDATA[01-02-2021]]></cell><cell><![CDATA[31-07-2021]]></cell><cell><![CDATA[590,000,000.0]]></cell><cell><![CDATA[590,000,000.0]]></cell><cell><![CDATA[411,650,000.0]]></cell><cell><![CDATA[178,350,000.0]]></cell><cell><![CDATA[590,000,000.0]]></cell><cell><![CDATA[411,650,000.0]]></cell><cell><![CDATA[178,350,000.0]]></cell><cell><![CDATA[0.0]]></cell><cell><![CDATA[0.0]]></cell><cell><![CDATA[0.0]]></cell><cell><![CDATA[0]]></cell><cell><![CDATA[0]]></cell><cell><![CDATA[0.0]]></cell><cell><![CDATA[0.0]]></cell><cell><![CDATA[70 %]]></cell><cell><![CDATA[]]></cell><cell><![CDATA[0.0]]></cell><cell><![CDATA[0.0]]></cell><cell><![CDATA[0.0]]></cell><cell><![CDATA[380,964,025.0]]></cell><cell><![CDATA[ 
            PPUB]]></cell><cell><![CDATA[
                ]]></cell></row>
<row><cell><![CDATA[55]]></cell><cell><![CDATA[SI CAB JAKARTA]]></cell><cell><![CDATA[0720040098
                        
                         Penjelasan]]></cell><cell><![CDATA[20099_KOM1_ARSYNERGY RESOURCES_INSPECTION SERVICES]]></cell><cell><![CDATA[ARSYNERGY RESOURCES]]></cell><cell><![CDATA[
            
            ]]></cell><cell><![CDATA[
            
            ]]></cell><cell><![CDATA[13-10-2020]]></cell><cell><![CDATA[28-02-2021]]></cell><cell><![CDATA[130,800,000.0]]></cell><cell><![CDATA[114,000,000.0]]></cell><cell><![CDATA[75,142,123.0]]></cell><cell><![CDATA[38,857,877.0]]></cell><cell><![CDATA[114,000,000.0]]></cell><cell><![CDATA[75,142,123.0]]></cell><cell><![CDATA[38,857,877.0]]></cell><cell><![CDATA[114,000,000.0]]></cell><cell><![CDATA[75,142,123.0]]></cell><cell><![CDATA[38,857,877.0]]></cell><cell><![CDATA[100]]></cell><cell><![CDATA[100]]></cell><cell><![CDATA[100.0]]></cell><cell><![CDATA[100.0]]></cell><cell><![CDATA[0 %]]></cell><cell><![CDATA[]]></cell><cell><![CDATA[76,560,000.0]]></cell><cell><![CDATA[0.0]]></cell><cell><![CDATA[0.0]]></cell><cell><![CDATA[0.0]]></cell><cell><![CDATA[ 
            PPUB]]></cell><cell><![CDATA[
                ]]></cell></row>
<row><cell><![CDATA[56]]></cell><cell><![CDATA[SI CAB JAKARTA]]></cell><cell><![CDATA[0720040100
                        
                         Penjelasan]]></cell><cell><![CDATA[20100_KOM2_PT. Polytama & PT. Pertamina (Persero)_Proyek Jasa Peninjauan Propylene]]></cell><cell><![CDATA[POLYTAMA PROPINDO]]></cell><cell><![CDATA[SR
            
            ]]></cell><cell><![CDATA[
            
            ]]></cell><cell><![CDATA[01-11-2020]]></cell><cell><![CDATA[30-11-2020]]></cell><cell><![CDATA[172,200,000.0]]></cell><cell><![CDATA[0.0]]></cell><cell><![CDATA[0.0]]></cell><cell><![CDATA[0.0]]></cell><cell><![CDATA[0.0]]></cell><cell><![CDATA[0.0]]></cell><cell><![CDATA[0.0]]></cell><cell><![CDATA[0.0]]></cell><cell><![CDATA[0.0]]></cell><cell><![CDATA[0.0]]></cell><cell><![CDATA[0]]></cell><cell><![CDATA[0]]></cell><cell><![CDATA[0.0]]></cell><cell><![CDATA[0.0]]></cell><cell><![CDATA[ ]]></cell><cell><![CDATA[]]></cell><cell><![CDATA[88,529,225.0]]></cell><cell><![CDATA[0.0]]></cell><cell><![CDATA[6,250,000.0]]></cell><cell><![CDATA[0.0]]></cell><cell><![CDATA[ 
            PPUB]]></cell><cell><![CDATA[
                ]]></cell></row>
<row><cell><![CDATA[57]]></cell><cell><![CDATA[SI CAB JAKARTA]]></cell><cell><![CDATA[0720040102
                        
                         Penjelasan]]></cell><cell><![CDATA[20102_KOM1_PT KOMATSU MARKETING AND SUPPORT INDONESIA_UT FLAW KOMATSU]]></cell><cell><![CDATA[KOMATSU MARKETING AND SUPPORT INDONESIA]]></cell><cell><![CDATA[
            
            ]]></cell><cell><![CDATA[
            
            ]]></cell><cell><![CDATA[13-11-2020]]></cell><cell><![CDATA[31-03-2021]]></cell><cell><![CDATA[6,000,000.0]]></cell><cell><![CDATA[6,000,000.0]]></cell><cell><![CDATA[3,960,133.0]]></cell><cell><![CDATA[2,039,867.0]]></cell><cell><![CDATA[6,000,000.0]]></cell><cell><![CDATA[3,960,133.0]]></cell><cell><![CDATA[2,039,867.0]]></cell><cell><![CDATA[6,000,000.0]]></cell><cell><![CDATA[3,960,133.0]]></cell><cell><![CDATA[2,039,867.0]]></cell><cell><![CDATA[100]]></cell><cell><![CDATA[100]]></cell><cell><![CDATA[100.0]]></cell><cell><![CDATA[100.0]]></cell><cell><![CDATA[ ]]></cell><cell><![CDATA[]]></cell><cell><![CDATA[6,600,000.0]]></cell><cell><![CDATA[0.0]]></cell><cell><![CDATA[0.0]]></cell><cell><![CDATA[0.0]]></cell><cell><![CDATA[ 
            PPUB]]></cell><cell><![CDATA[
                ]]></cell></row>
<row><cell><![CDATA[58]]></cell><cell><![CDATA[SI CAB JAKARTA]]></cell><cell><![CDATA[0720040103
                        
                         Penjelasan]]></cell><cell><![CDATA[20104_KOM2_PT. Bold Mining Resources_Condition &Trial Survey]]></cell><cell><![CDATA[BOLD MINING RESOURCES]]></cell><cell><![CDATA[
            
            ]]></cell><cell><![CDATA[
            
            ]]></cell><cell><![CDATA[01-11-2020]]></cell><cell><![CDATA[31-12-2020]]></cell><cell><![CDATA[78,400,000.0]]></cell><cell><![CDATA[57,000,000.0]]></cell><cell><![CDATA[37,946,317.0]]></cell><cell><![CDATA[19,053,683.0]]></cell><cell><![CDATA[57,000,000.0]]></cell><cell><![CDATA[37,946,317.0]]></cell><cell><![CDATA[19,053,683.0]]></cell><cell><![CDATA[60,000,000.0]]></cell><cell><![CDATA[37,946,317.0]]></cell><cell><![CDATA[22,053,683.0]]></cell><cell><![CDATA[105.26]]></cell><cell><![CDATA[105.26]]></cell><cell><![CDATA[100.0]]></cell><cell><![CDATA[100.0]]></cell><cell><![CDATA[ ]]></cell><cell><![CDATA[]]></cell><cell><![CDATA[0.0]]></cell><cell><![CDATA[0.0]]></cell><cell><![CDATA[12,000,000.0]]></cell><cell><![CDATA[0.0]]></cell><cell><![CDATA[ 
            PPUB]]></cell><cell><![CDATA[
                ]]></cell></row>
<row><cell><![CDATA[59]]></cell><cell><![CDATA[SI CAB JAKARTA]]></cell><cell><![CDATA[0720040105
                        
                         Penjelasan]]></cell><cell><![CDATA[20105_KOM2_PT. Ratu Pola Bumi_Pemeriksaan dan Riksa Uji PAA Crane]]></cell><cell><![CDATA[RATU POLA BUMI]]></cell><cell><![CDATA[
            
            ]]></cell><cell><![CDATA[
            
            ]]></cell><cell><![CDATA[01-11-2020]]></cell><cell><![CDATA[31-01-2021]]></cell><cell><![CDATA[27,000,000.0]]></cell><cell><![CDATA[27,000,000.0]]></cell><cell><![CDATA[18,075,000.0]]></cell><cell><![CDATA[8,925,000.0]]></cell><cell><![CDATA[27,000,000.0]]></cell><cell><![CDATA[18,075,000.0]]></cell><cell><![CDATA[8,925,000.0]]></cell><cell><![CDATA[27,000,000.0]]></cell><cell><![CDATA[8,064,100.0]]></cell><cell><![CDATA[18,935,900.0]]></cell><cell><![CDATA[100]]></cell><cell><![CDATA[100]]></cell><cell><![CDATA[44.6]]></cell><cell><![CDATA[44.6]]></cell><cell><![CDATA[ ]]></cell><cell><![CDATA[]]></cell><cell><![CDATA[0.0]]></cell><cell><![CDATA[0.0]]></cell><cell><![CDATA[9,850,000.0]]></cell><cell><![CDATA[0.0]]></cell><cell><![CDATA[ 
            PPUB]]></cell><cell><![CDATA[
                ]]></cell></row>
<row><cell><![CDATA[60]]></cell><cell><![CDATA[SI CAB JAKARTA]]></cell><cell><![CDATA[0720040109
                        
                         Penjelasan]]></cell><cell><![CDATA[20107_KOM2_PT. Polytama & PT. Pertamina (Persero)_Proyek Jasa Peninjauan Propylene]]></cell><cell><![CDATA[POLYTAMA PROPINDO]]></cell><cell><![CDATA[
            
            ]]></cell><cell><![CDATA[
            
            ]]></cell><cell><![CDATA[01-12-2020]]></cell><cell><![CDATA[31-12-2020]]></cell><cell><![CDATA[169,750,000.0]]></cell><cell><![CDATA[169,750,000.0]]></cell><cell><![CDATA[115,325,000.0]]></cell><cell><![CDATA[54,425,000.0]]></cell><cell><![CDATA[169,750,000.0]]></cell><cell><![CDATA[115,325,000.0]]></cell><cell><![CDATA[54,425,000.0]]></cell><cell><![CDATA[141,542,219.0]]></cell><cell><![CDATA[90,465,053.0]]></cell><cell><![CDATA[51,077,166.0]]></cell><cell><![CDATA[83.38]]></cell><cell><![CDATA[83.38]]></cell><cell><![CDATA[78.4]]></cell><cell><![CDATA[78.4]]></cell><cell><![CDATA[ ]]></cell><cell><![CDATA[]]></cell><cell><![CDATA[0.0]]></cell><cell><![CDATA[0.0]]></cell><cell><![CDATA[14,000,000.0]]></cell><cell><![CDATA[0.0]]></cell><cell><![CDATA[ 
            PPUB]]></cell><cell><![CDATA[
                ]]></cell></row>
<row><cell><![CDATA[61]]></cell><cell><![CDATA[SI CAB JAKARTA]]></cell><cell><![CDATA[0720040157
                        
                         Penjelasan]]></cell><cell><![CDATA[19137_KOM2_Palugada Berkah Bersama_Draugh Survey]]></cell><cell><![CDATA[PALUGADA BERKAH BERSAMA]]></cell><cell><![CDATA[
            
            ]]></cell><cell><![CDATA[
            
            ]]></cell><cell><![CDATA[02-11-2020]]></cell><cell><![CDATA[01-11-2021]]></cell><cell><![CDATA[200,000,000.0]]></cell><cell><![CDATA[89,999,998.0]]></cell><cell><![CDATA[79,981,812.0]]></cell><cell><![CDATA[10,018,186.0]]></cell><cell><![CDATA[32,727,272.0]]></cell><cell><![CDATA[30,727,268.0]]></cell><cell><![CDATA[2,000,004.0]]></cell><cell><![CDATA[32,000,000.0]]></cell><cell><![CDATA[28,440,888.0]]></cell><cell><![CDATA[3,559,112.0]]></cell><cell><![CDATA[35.56]]></cell><cell><![CDATA[97.78]]></cell><cell><![CDATA[35.6]]></cell><cell><![CDATA[92.6]]></cell><cell><![CDATA[0 %]]></cell><cell><![CDATA[]]></cell><cell><![CDATA[127,600,000.0]]></cell><cell><![CDATA[0.0]]></cell><cell><![CDATA[0.0]]></cell><cell><![CDATA[0.0]]></cell><cell><![CDATA[ 
            PPUB]]></cell><cell><![CDATA[
                ]]></cell></row>
<row><cell><![CDATA[62]]></cell><cell><![CDATA[SI CAB JAKARTA]]></cell><cell><![CDATA[0720050074
                        
                         Penjelasan]]></cell><cell><![CDATA[20069_KOM2_PD Pasar Jaya_Pengadaan Jasa Konsultansi Inventarisasi Aset]]></cell><cell><![CDATA[PASAR JAYA]]></cell><cell><![CDATA[
            
            ]]></cell><cell><![CDATA[TSR
            
            ]]></cell><cell><![CDATA[01-08-2020]]></cell><cell><![CDATA[31-03-2021]]></cell><cell><![CDATA[358,186,800.0]]></cell><cell><![CDATA[129,633,408.0]]></cell><cell><![CDATA[64,488,941.0]]></cell><cell><![CDATA[65,144,467.0]]></cell><cell><![CDATA[129,633,408.0]]></cell><cell><![CDATA[64,488,941.0]]></cell><cell><![CDATA[65,144,467.0]]></cell><cell><![CDATA[-13,249,472.0]]></cell><cell><![CDATA[506,980.0]]></cell><cell><![CDATA[-13,756,452.0]]></cell><cell><![CDATA[-10.22]]></cell><cell><![CDATA[-10.22]]></cell><cell><![CDATA[0.8]]></cell><cell><![CDATA[0.8]]></cell><cell><![CDATA[ ]]></cell><cell><![CDATA[]]></cell><cell><![CDATA[0.0]]></cell><cell><![CDATA[0.0]]></cell><cell><![CDATA[32,321,800.0]]></cell><cell><![CDATA[19,568,299.0]]></cell><cell><![CDATA[ 
            PPUB]]></cell><cell><![CDATA[
                ]]></cell></row></rows>