<rows profile='color'><head><columns><column  width='50' align='right' type='ron' hidden='false' sort='int' color=''><![CDATA[No.]]></column><column  width='220' align='left' type='ro' hidden='false' sort='str' color=''><![CDATA[ Nama Klien]]></column><column  width='300' align='left' type='ron' hidden='false' sort='int' color=''><![CDATA[ Nama Proyek]]></column><column  width='120' align='right' type='ron' hidden='false' sort='int' color=''><![CDATA[ Nilai Kontrak]]></column></columns></head>
<foot>
<columns>
<column colspan='3' ><![CDATA[TOTAL]]></column>
<column><![CDATA[]]></column>
<column><![CDATA[]]></column>
<column><![CDATA[10,537,579,000]]></column>
</columns>
</foot><row><cell><![CDATA[1]]></cell><cell><![CDATA[PERTAMINA (PERSERO) REFINERY UNIT IV CILACAP, PERTAMINA (PERSERO) DIREKTORAT PENGOLAHAN, PERTAMINA (PERSERO)]]></cell><cell><![CDATA[Sertifikasi SMK3]]></cell><cell><![CDATA[200,000,000]]></cell></row>
<row><cell><![CDATA[2]]></cell><cell><![CDATA[PJB UBJOM PLTU REMBANG, PEMBANGKITAN JAWA BALI (PJB), PLN (PERSERO)]]></cell><cell><![CDATA[Pengadaan Kontrak Payung Pemantauan Udara Dan Limbah B3 Tahun 2021]]></cell><cell><![CDATA[500,000,000]]></cell></row>
<row><cell><![CDATA[3]]></cell><cell><![CDATA[PJB UBJOM PLTU PAITON, PEMBANGKITAN JAWA BALI (PJB), PLN (PERSERO)]]></cell><cell><![CDATA[Jasa Survey Analisa Kuantitas dan Kualitas HSD Biodiesel Melalui Jalur Darat]]></cell><cell><![CDATA[50,000,000]]></cell></row>
<row><cell><![CDATA[4]]></cell><cell><![CDATA[PJB UP CIRATA, PEMBANGKITAN JAWA BALI (PJB), PLN (PERSERO)]]></cell><cell><![CDATA[Resertifikasi Alat Berat (Tadano, Loader, Crane, Forklift dan Lift Car), OHC, Penangkal Petir, Gantry, Fire Alarm, Chain Block SY, PH, & Turbin]]></cell><cell><![CDATA[50,000,000]]></cell></row>
<row><cell><![CDATA[5]]></cell><cell><![CDATA[ENI MUARA BAKAU]]></cell><cell><![CDATA[Inspection Recertification and Maintenance Service For LSA And SE For Operation]]></cell><cell><![CDATA[100,000,000]]></cell></row>
<row><cell><![CDATA[6]]></cell><cell><![CDATA[MEDCO ENERGI]]></cell><cell><![CDATA[Front End Engineering Design (FEED) Study For Flare Gas Recovery]]></cell><cell><![CDATA[100,000,000]]></cell></row>
<row><cell><![CDATA[7]]></cell><cell><![CDATA[PERTAMINA EP, ASSET 4 CEPU, PERTAMINA EP, PERTAMINA (PERSERO)]]></cell><cell><![CDATA[Jasa Tenaga Kerja Third Party Contract Utuk Mendukung Project Pengembangan Lapangan Tiung Biru]]></cell><cell><![CDATA[100,000,000]]></cell></row>
<row><cell><![CDATA[8]]></cell><cell><![CDATA[PERTAMINA EP, PERTAMINA (PERSERO)]]></cell><cell><![CDATA[Kontrak Sertifikasi, Kalibrasi, dan Assesment]]></cell><cell><![CDATA[100,000,000]]></cell></row>
<row><cell><![CDATA[9]]></cell><cell><![CDATA[PERTAMINA EP ASSET 1, PERTAMINA EP, PERTAMINA (PERSERO)]]></cell><cell><![CDATA[Project Management Consultant (PMC) Untuk Membantu Pengawasan Konstruksi & QA/QC di Fungsi Asset 1 Surface Facilities PT Pertamina EP Tahun 2020-2021]]></cell><cell><![CDATA[100,000,000]]></cell></row>
<row><cell><![CDATA[10]]></cell><cell><![CDATA[PERTAMINA EP ASSET 2, PERTAMINA EP, PERTAMINA (PERSERO)]]></cell><cell><![CDATA[Call Of Order Jasa Inspeksi dan Pengetesan di Pertamina EP Asset 2]]></cell><cell><![CDATA[100,000,000]]></cell></row>
<row><cell><![CDATA[11]]></cell><cell><![CDATA[PERTAMINA EP, ASSET 5 SANGASANGA, PERTAMINA EP ASSET 5, PERTAMINA EP, PERTAMINA (PERSERO)]]></cell><cell><![CDATA[Penyediaan Pekerja Jasa Penunjang Untuk Fungsi RAM Sangasanga Field]]></cell><cell><![CDATA[100,000,000]]></cell></row>
<row><cell><![CDATA[12]]></cell><cell><![CDATA[PERTAMINA EP ASSET 2, PERTAMINA EP, PERTAMINA (PERSERO)]]></cell><cell><![CDATA[Jasa Inpeksi COI dan Reserfikasi PLO Migas PT Pertamina EP Asset 2 Selama 2 Tahun]]></cell><cell><![CDATA[100,000,000]]></cell></row>
<row><cell><![CDATA[13]]></cell><cell><![CDATA[PERTAMINA EP ASSET 3, PERTAMINA EP, PERTAMINA (PERSERO)]]></cell><cell><![CDATA[Kontrak Payung (COO) Pekerjaan Geophysical Survey Fungsi Surface Facilities Asset 3 Periode Tahun 2020-2022 PT. Pertamina EP Asset 3]]></cell><cell><![CDATA[100,000,000]]></cell></row>
<row><cell><![CDATA[14]]></cell><cell><![CDATA[PERTAMINA EP, ASSET 5 TANJUNG, PERTAMINA EP ASSET 5, PERTAMINA (PERSERO), PT]]></cell><cell><![CDATA[Jasa Penyediaan Tenaga Kerja Jasa Penunjang Fungsi Engineering & Planing, Workover/Well Services, Production Operation PT PErtamina EP Asset 5 Tanjung Field Periode tahun 2021-2023]]></cell><cell><![CDATA[100,000,000]]></cell></row>
<row><cell><![CDATA[15]]></cell><cell><![CDATA[PERTAMINA EP ASSET 2 FIELD ADERA, PERTAMINA EP ASSET 2, PERTAMINA EP, PERTAMINA (PERSERO)]]></cell><cell><![CDATA[Jasa Pemantauan Kualitas Lingkungan (Pelaksanaan RKL/RPL Dan UKL/UPL Dan Uji Emisi Kendaraan Tahun 2021-2022 Field Adera]]></cell><cell><![CDATA[100,000,000]]></cell></row>
<row><cell><![CDATA[16]]></cell><cell><![CDATA[PERTAMINA EP ASSET 5, PERTAMINA EP, PERTAMINA (PERSERO)]]></cell><cell><![CDATA[Jasa Front End Engineering Design (FEED) Dan Detailed Engineering Design (DED) PT Pertamina EP Asset 5]]></cell><cell><![CDATA[100,000,000]]></cell></row>
<row><cell><![CDATA[17]]></cell><cell><![CDATA[PERTAMINA EP ASSET 4, PERTAMINA EP, PERTAMINA (PERSERO)]]></cell><cell><![CDATA[Jasa Pelaksanaan Pemantauan Lingkungan Dan Analisa Laboratorium PT Pertamina EP Asset 4 Donggi Matindok Field]]></cell><cell><![CDATA[100,000,000]]></cell></row>
<row><cell><![CDATA[18]]></cell><cell><![CDATA[PERTAMINA EP, PERTAMINA (PERSERO)]]></cell><cell><![CDATA[Jasa Pengembangan Aplikasi Dan Sistem Informasi PT Pertamina EP Selama 36 Bulan]]></cell><cell><![CDATA[100,000,000]]></cell></row>
<row><cell><![CDATA[19]]></cell><cell><![CDATA[PERTAMINA EP, PERTAMINA (PERSERO)]]></cell><cell><![CDATA[Jasa Manajemen Proyek Dan Assesment Teknis SF PEP 2021 (Selama 3 Tahun)]]></cell><cell><![CDATA[100,000,000]]></cell></row>
<row><cell><![CDATA[20]]></cell><cell><![CDATA[PERTAMINA EP, PERTAMINA (PERSERO)]]></cell><cell><![CDATA[Inspeksi Subsea Trunkline Gas Bunyu-Tarakan]]></cell><cell><![CDATA[100,000,000]]></cell></row>
<row><cell><![CDATA[21]]></cell><cell><![CDATA[PERTAMINA EP, ASSET 5 TANJUNG, PERTAMINA EP ASSET 5, PERTAMINA (PERSERO), PT]]></cell><cell><![CDATA[Jasa Penyediaan Tenaga Kerja Jasa Penunjang Fungsi RAM, HSSE, HR, LR, SCM, Finance, Dan ICT Di PT Pertamina EP Asset 5 Tanjung Field Periode Tahun 2021-2023]]></cell><cell><![CDATA[100,000,000]]></cell></row>
<row><cell><![CDATA[22]]></cell><cell><![CDATA[PERTAMINA EP ASSET 5, PERTAMINA EP, PERTAMINA (PERSERO)]]></cell><cell><![CDATA[PROJECT ENGINEERING & CONSTRUCTION MANAGEMENT SERVICES DI PT PERTAMINA EP WILAYAH KERJA ASSET 5]]></cell><cell><![CDATA[100,000,000]]></cell></row>
<row><cell><![CDATA[23]]></cell><cell><![CDATA[PLN (PERSERO) TRANSMISI JAWA BAGIAN TENGAH, PLN (PERSERO) DIVISI OPERASI REGIONAL JAWA BAGIAN TENGAH, PLN (PERSERO) BISNIS REGIONAL JAWA BAGIAN TENGAH, PLN (PERSERO)]]></cell><cell><![CDATA[Jasa Sertifikasi Laik Operasi (SLO) Jaringan Transmisi Tenaga Listrik (SUTT & SUTET) dan Gardu Induk di Seluruh UPT Jawa Bagian Tengah]]></cell><cell><![CDATA[100,000,000]]></cell></row>
<row><cell><![CDATA[24]]></cell><cell><![CDATA[PELABUHAN INDONESIA III (PERSERO) CABANG SEMARANG, PELABUHAN INDONESIA III (PERSERO)]]></cell><cell><![CDATA[Pekerjaan Pemantauan Lingkungan Tahun 2021 Pelabuhan Tanjung Emas]]></cell><cell><![CDATA[350,000,000]]></cell></row>
<row><cell><![CDATA[25]]></cell><cell><![CDATA[PLN (PERSERO) AREA PENGATURAN BEBAN JAWA TENGAH DAN DIY, PLN (PERSERO) PENYALUR DAN PUSAT PENGATUR BEBAN, PLN (PERSERO)]]></cell><cell><![CDATA[Pemeliharaan Dan Pengelolaan SMK3-Biaya Sertifikasi, Perijinan Dan Retribusi (Sertifikasi Peralatan K3)]]></cell><cell><![CDATA[75,000,000]]></cell></row>
<row><cell><![CDATA[26]]></cell><cell><![CDATA[PELABUHAN INDONESIA III (PERSERO) CABANG TANJUNG INTAN, PELABUHAN INDONESIA III (PERSERO)]]></cell><cell><![CDATA[Resertifikasi Peralatan]]></cell><cell><![CDATA[250,000,000]]></cell></row>
<row><cell><![CDATA[27]]></cell><cell><![CDATA[PJB UBJOM PLTU REMBANG, PEMBANGKITAN JAWA BALI (PJB), PLN (PERSERO)]]></cell><cell><![CDATA[Jasa Survey Analisa Kuantitas dan Kualitas HSD Biodiesel Melalui Jalur Darat]]></cell><cell><![CDATA[150,000,000]]></cell></row>
<row><cell><![CDATA[28]]></cell><cell><![CDATA[PERTAMINA (PERSERO) MOR IV, PERTAMINA (PERSERO) DIREKTORAT PEMASARAN DAN NIAGA, PERTAMINA (PERSERO)]]></cell><cell><![CDATA[Jasa Penyusunan Kajian Lokasi Pertashop Tahun 2021]]></cell><cell><![CDATA[450,000,000]]></cell></row>
<row><cell><![CDATA[29]]></cell><cell><![CDATA[PJB UBJOM PLTU REMBANG, PEMBANGKITAN JAWA BALI (PJB), PLN (PERSERO)]]></cell><cell><![CDATA[Jasa Sertifikasi Kalibrasi Belt Weigher untuk Monitoring Stock Batubara Unloading]]></cell><cell><![CDATA[150,000,000]]></cell></row>
<row><cell><![CDATA[30]]></cell><cell><![CDATA[PJB UBJOM PLTU INDRAMAYU, PEMBANGKITAN JAWA BALI (PJB), PLN (PERSERO)]]></cell><cell><![CDATA[Resertifikasi Peralatan]]></cell><cell><![CDATA[450,000,000]]></cell></row>
<row><cell><![CDATA[31]]></cell><cell><![CDATA[INDONESIA POWER UP MRICA, INDONESIA POWER UNIT PEMBANGKITAN (UP), INDONESIA POWER, PLN (PERSERO)]]></cell><cell><![CDATA[Resertifikasi Peralatan]]></cell><cell><![CDATA[250,000,000]]></cell></row>
<row><cell><![CDATA[32]]></cell><cell><![CDATA[PJB UBJOM PLTU REMBANG, PEMBANGKITAN JAWA BALI (PJB), PLN (PERSERO)]]></cell><cell><![CDATA[Jasa Pengukuran Data Kualitas Lingkungan Kerja]]></cell><cell><![CDATA[50,000,000]]></cell></row>
<row><cell><![CDATA[33]]></cell><cell><![CDATA[DHARMAPALA USAHA SUKSES]]></cell><cell><![CDATA[Resertifikasi Peralatan]]></cell><cell><![CDATA[75,000,000]]></cell></row>
<row><cell><![CDATA[34]]></cell><cell><![CDATA[INDONESIA POWER UP SEMARANG, INDONESIA POWER UNIT PEMBANGKITAN (UP), INDONESIA POWER, PLN (PERSERO)]]></cell><cell><![CDATA[2021 K3L Jasa Sertifikasi Valve PRV Dan PSV Main Line Gas PLTGU]]></cell><cell><![CDATA[20,000,000]]></cell></row>
<row><cell><![CDATA[35]]></cell><cell><![CDATA[RECKITT BENCKISER INDONESIA]]></cell><cell><![CDATA[Resertifikasi Peralatan]]></cell><cell><![CDATA[50,000,000]]></cell></row>
<row><cell><![CDATA[36]]></cell><cell><![CDATA[ADHI GUNA PUTERA]]></cell><cell><![CDATA[Resertifikasi Peralatan]]></cell><cell><![CDATA[100,000,000]]></cell></row>
<row><cell><![CDATA[37]]></cell><cell><![CDATA[INDONESIA POWER UJP PLTU JAWA TENGAH 2 ADIPALA, INDONESIA POWER UNIT JASA PEMBANGKITAN (UJP), INDONESIA POWER, PLN (PERSERO)]]></cell><cell><![CDATA[Resertifikasi Peralatan]]></cell><cell><![CDATA[100,000,000]]></cell></row>
<row><cell><![CDATA[38]]></cell><cell><![CDATA[UNZA VITALIS]]></cell><cell><![CDATA[Resertifikasi Peralatan]]></cell><cell><![CDATA[50,000,000]]></cell></row>
<row><cell><![CDATA[39]]></cell><cell><![CDATA[PEMBANGKITAN JAWA BALI SERVICES, PJB SERVICES, PEMBANGKITAN JAWA BALI (PJB), PLN (PERSERO)]]></cell><cell><![CDATA[Resertifikasi Peralatan PLTU Bangka, PLTU Belitung, PLTU Tembilahan]]></cell><cell><![CDATA[450,000,000]]></cell></row>
<row><cell><![CDATA[40]]></cell><cell><![CDATA[PLN (PERSERO) SEKTOR PEMBANGKITAN TARAHAN, PLN (PERSERO) PEMBANGKITAN SUMATERA BAGIAN SELATAN, PLN (PERSERO) DIVISI OPERASI REGIONAL SUMATERA, PLN (PERSERO) BISNIS REGIONAL SUMATERA, PLN (PERSERO)]]></cell><cell><![CDATA[Sertifikasi Peralatan K3 ( Alat Angkat Angkut, Safety Valve, Bejana Bertekanan )]]></cell><cell><![CDATA[450,000,000]]></cell></row>
<row><cell><![CDATA[41]]></cell><cell><![CDATA[PLN (PERSERO) TRANSMISI JAWA BAGIAN TENGAH, PLN (PERSERO) DIVISI OPERASI REGIONAL JAWA BAGIAN TENGAH, PLN (PERSERO) BISNIS REGIONAL JAWA BAGIAN TENGAH, PLN (PERSERO)]]></cell><cell><![CDATA[Pekerjaan Survey, Pemberkasan, Dan Sosialisasi ROW SUTT 150 KV Kudus - Jepara]]></cell><cell><![CDATA[1,500,000,000]]></cell></row>
<row><cell><![CDATA[42]]></cell><cell><![CDATA[PJB UBJOM PLTU TANJUNG AWAR-AWAR, PEMBANGKITAN JAWA BALI (PJB), PLN (PERSERO)]]></cell><cell><![CDATA[Resertifikasi Peralatan]]></cell><cell><![CDATA[500,000,000]]></cell></row>
<row><cell><![CDATA[43]]></cell><cell><![CDATA[NAGABHUANA ANEKA PIRANTI]]></cell><cell><![CDATA[Pemeriksaan Kayu]]></cell><cell><![CDATA[700,000,000]]></cell></row>
<row><cell><![CDATA[44]]></cell><cell><![CDATA[KEMENTERIAN LINGKUNGAN HIDUP DAN KEHUTANAN]]></cell><cell><![CDATA[Pengawasan dan Penilaian Tanaman RHL (PO) Tahun 2021]]></cell><cell><![CDATA[419,397,000]]></cell></row>
<row><cell><![CDATA[45]]></cell><cell><![CDATA[PJB UBJOM PLTU REMBANG, PEMBANGKITAN JAWA BALI (PJB), PLN (PERSERO)]]></cell><cell><![CDATA[JASA PEMANTAUAN LINGKUNGAN KERJA FAKTOR BIOLOGI, ERGONOMI, KIMIA, FISIKA (GETARAN) DAN PSIKOLOGI]]></cell><cell><![CDATA[100,000,000]]></cell></row>
<row><cell><![CDATA[46]]></cell><cell><![CDATA[KEMENTERIAN PERENCANAAN PEMBANGGUNAN (PPN/BAPPENAS)]]></cell><cell><![CDATA[Belanja Jasa Konsultan]]></cell><cell><![CDATA[100,000,000]]></cell></row>
<row><cell><![CDATA[47]]></cell><cell><![CDATA[KEMENTERIAN KOMUNIKASI DAN INFORMATIKA]]></cell><cell><![CDATA[Penyusunan Kajian Pembentukan Kelembagaan Pusat Data Nasional]]></cell><cell><![CDATA[100,000,000]]></cell></row>
<row><cell><![CDATA[48]]></cell><cell><![CDATA[KEMENTERIAN PEKERJAAN UMUM & PERUMAHAN RAKYAT]]></cell><cell><![CDATA[Toll Road Development Of Semarang - Demak 1A]]></cell><cell><![CDATA[100,000,000]]></cell></row>
<row><cell><![CDATA[49]]></cell><cell><![CDATA[KEMENTERIAN PEKERJAAN UMUM & PERUMAHAN RAKYAT]]></cell><cell><![CDATA[Toll Road Development Of Semarang - Demak 1C]]></cell><cell><![CDATA[100,000,000]]></cell></row>
<row><cell><![CDATA[50]]></cell><cell><![CDATA[KEMENTERIAN PEKERJAAN UMUM & PERUMAHAN RAKYAT]]></cell><cell><![CDATA[Toll Road Development Of Semarang - Demak 1B]]></cell><cell><![CDATA[100,000,000]]></cell></row>
<row><cell><![CDATA[51]]></cell><cell><![CDATA[PLN (PERSERO) UP3 KAPUAS, PLN (PERSERO) PEMBANGKITAN DAN PENYALURAN KALIMANTAN, PLN (PERSERO) WILAYAH KALIMANTAN SELATAN DAN TENGAH, PLN (PERSERO) DIVISI OPERASI REGIONAL KALIMANTAN, PLN (PERSERO) BISNIS REGIONAL KALIMANTAN, PLN (PERSERO)]]></cell><cell><![CDATA[Pengadaan Jasa Penentuan Kuantitas dan Analisa Kualtias Penerimaan Batubara]]></cell><cell><![CDATA[100,000,000]]></cell></row>
<row><cell><![CDATA[52]]></cell><cell><![CDATA[PJB UBJOM PLTU TANJUNG AWAR-AWAR, PEMBANGKITAN JAWA BALI (PJB), PLN (PERSERO)]]></cell><cell><![CDATA[Eddy Current Test Tube LP Heater 5, 6, 7 dan 8 SE #1 2021]]></cell><cell><![CDATA[100,000,000]]></cell></row>
<row><cell><![CDATA[53]]></cell><cell><![CDATA[PLN (PERSERO) UPDK BENGKULU, PLN (PERSERO) WILAYAH SUMSEL, JAMBI & BENGKULU, PLN (PERSERO) DIVISI OPERASI REGIONAL SUMATERA, PLN (PERSERO) BISNIS REGIONAL SUMATERA, PLN (PERSERO)]]></cell><cell><![CDATA[Pemantauan Lingkungan PLTA Musi dan PLTA Tes 2021 (RKL - RPL)]]></cell><cell><![CDATA[100,000,000]]></cell></row>
<row><cell><![CDATA[54]]></cell><cell><![CDATA[PLN (PERSERO) TRANSMISI JAWA BAGIAN TENGAH, PLN (PERSERO) DIVISI OPERASI REGIONAL JAWA BAGIAN TENGAH, PLN (PERSERO) BISNIS REGIONAL JAWA BAGIAN TENGAH, PLN (PERSERO)]]></cell><cell><![CDATA[PELAKSANAAN PENATAAN BATAS AREAL IPPKH JALUR SUTET 500 KV BANDUNG SELATAN - MANDIRANCAN SESUAI DENGAN PEDOMAN KERJA DAN INSTRUKSI KERJA TATA BATAS NO. INS.60/BPKH.XI/2/PLA.2/9/2020 (9 POLIGON)]]></cell><cell><![CDATA[100,000,000]]></cell></row>
<row><cell><![CDATA[55]]></cell><cell><![CDATA[PLN (PERSERO) TRANSMISI JAWA BAGIAN TENGAH, PLN (PERSERO) DIVISI OPERASI REGIONAL JAWA BAGIAN TENGAH, PLN (PERSERO) BISNIS REGIONAL JAWA BAGIAN TENGAH, PLN (PERSERO)]]></cell><cell><![CDATA[PENYUSUNAN DAN PENGESAHAN LAPORAN PELAKSANAAN PENATAAN BATAS AREAL IPPKH JALUR SUTET 500 KV BANDUNG SELATAN - MANDIRANCAN OLEH KLHK]]></cell><cell><![CDATA[50,000,000]]></cell></row>
<row><cell><![CDATA[56]]></cell><cell><![CDATA[PJB UBJOM LUAR JAWA 2, PEMBANGKITAN JAWA BALI (PJB), PLN (PERSERO)]]></cell><cell><![CDATA[Welder Test dan Supervisi Re Tubbing]]></cell><cell><![CDATA[25,000,000]]></cell></row>
<row><cell><![CDATA[57]]></cell><cell><![CDATA[PJB UBJOM LUAR JAWA 2, PEMBANGKITAN JAWA BALI (PJB), PLN (PERSERO)]]></cell><cell><![CDATA[Radiography Tube Boiler PLTU Ropa Ende Flores]]></cell><cell><![CDATA[60,000,000]]></cell></row>
<row><cell><![CDATA[58]]></cell><cell><![CDATA[PJB UBJOM PLTU PAITON, PEMBANGKITAN JAWA BALI (PJB), PLN (PERSERO)]]></cell><cell><![CDATA[Jasa Konsultan Kajian Kelayakan Pengembangan Kawasan Industri Paiton PJB Pusat]]></cell><cell><![CDATA[50,000,000]]></cell></row>
<row><cell><![CDATA[59]]></cell><cell><![CDATA[PEMBANGKITAN JAWA BALI (PJB), PLN (PERSERO)]]></cell><cell><![CDATA[Penyusunan Dokumen Analisis Dampak Lalu Lintas - Cirata Floating PV Power Plant 145 MWac - PJBI - Abu Dhabi Future Energy Company PJSE - Masdar]]></cell><cell><![CDATA[50,000,000]]></cell></row>
<row><cell><![CDATA[60]]></cell><cell><![CDATA[DWIPA KONEKTRA]]></cell><cell><![CDATA[Sertifikasi Peralatan - OHC 35 Ton, Hydrant, Fire Alarm]]></cell><cell><![CDATA[13,182,000]]></cell></row></rows><rows profile='color'><head><columns><column  width='50' align='right' type='ron' hidden='false' sort='int' color=''><![CDATA[No.]]></column><column  width='220' align='left' type='ro' hidden='false' sort='str' color=''><![CDATA[ Nama Klien]]></column><column  width='300' align='left' type='ron' hidden='false' sort='int' color=''><![CDATA[ Nama Proyek]]></column><column  width='120' align='right' type='ron' hidden='false' sort='int' color=''><![CDATA[ Nilai Kontrak]]></column></columns></head>
<foot>
<columns>
<column colspan='3' ><![CDATA[TOTAL]]></column>
<column><![CDATA[]]></column>
<column><![CDATA[]]></column>
<column><![CDATA[10,537,579,000]]></column>
</columns>
</foot><row><cell><![CDATA[1]]></cell><cell><![CDATA[PERTAMINA (PERSERO) REFINERY UNIT IV CILACAP, PERTAMINA (PERSERO) DIREKTORAT PENGOLAHAN, PERTAMINA (PERSERO)]]></cell><cell><![CDATA[Sertifikasi SMK3]]></cell><cell><![CDATA[200,000,000]]></cell></row>
<row><cell><![CDATA[2]]></cell><cell><![CDATA[PJB UBJOM PLTU REMBANG, PEMBANGKITAN JAWA BALI (PJB), PLN (PERSERO)]]></cell><cell><![CDATA[Pengadaan Kontrak Payung Pemantauan Udara Dan Limbah B3 Tahun 2021]]></cell><cell><![CDATA[500,000,000]]></cell></row>
<row><cell><![CDATA[3]]></cell><cell><![CDATA[PJB UBJOM PLTU PAITON, PEMBANGKITAN JAWA BALI (PJB), PLN (PERSERO)]]></cell><cell><![CDATA[Jasa Survey Analisa Kuantitas dan Kualitas HSD Biodiesel Melalui Jalur Darat]]></cell><cell><![CDATA[50,000,000]]></cell></row>
<row><cell><![CDATA[4]]></cell><cell><![CDATA[PJB UP CIRATA, PEMBANGKITAN JAWA BALI (PJB), PLN (PERSERO)]]></cell><cell><![CDATA[Resertifikasi Alat Berat (Tadano, Loader, Crane, Forklift dan Lift Car), OHC, Penangkal Petir, Gantry, Fire Alarm, Chain Block SY, PH, & Turbin]]></cell><cell><![CDATA[50,000,000]]></cell></row>
<row><cell><![CDATA[5]]></cell><cell><![CDATA[ENI MUARA BAKAU]]></cell><cell><![CDATA[Inspection Recertification and Maintenance Service For LSA And SE For Operation]]></cell><cell><![CDATA[100,000,000]]></cell></row>
<row><cell><![CDATA[6]]></cell><cell><![CDATA[MEDCO ENERGI]]></cell><cell><![CDATA[Front End Engineering Design (FEED) Study For Flare Gas Recovery]]></cell><cell><![CDATA[100,000,000]]></cell></row>
<row><cell><![CDATA[7]]></cell><cell><![CDATA[PERTAMINA EP, ASSET 4 CEPU, PERTAMINA EP, PERTAMINA (PERSERO)]]></cell><cell><![CDATA[Jasa Tenaga Kerja Third Party Contract Utuk Mendukung Project Pengembangan Lapangan Tiung Biru]]></cell><cell><![CDATA[100,000,000]]></cell></row>
<row><cell><![CDATA[8]]></cell><cell><![CDATA[PERTAMINA EP, PERTAMINA (PERSERO)]]></cell><cell><![CDATA[Kontrak Sertifikasi, Kalibrasi, dan Assesment]]></cell><cell><![CDATA[100,000,000]]></cell></row>
<row><cell><![CDATA[9]]></cell><cell><![CDATA[PERTAMINA EP ASSET 1, PERTAMINA EP, PERTAMINA (PERSERO)]]></cell><cell><![CDATA[Project Management Consultant (PMC) Untuk Membantu Pengawasan Konstruksi & QA/QC di Fungsi Asset 1 Surface Facilities PT Pertamina EP Tahun 2020-2021]]></cell><cell><![CDATA[100,000,000]]></cell></row>
<row><cell><![CDATA[10]]></cell><cell><![CDATA[PERTAMINA EP ASSET 2, PERTAMINA EP, PERTAMINA (PERSERO)]]></cell><cell><![CDATA[Call Of Order Jasa Inspeksi dan Pengetesan di Pertamina EP Asset 2]]></cell><cell><![CDATA[100,000,000]]></cell></row>
<row><cell><![CDATA[11]]></cell><cell><![CDATA[PERTAMINA EP, ASSET 5 SANGASANGA, PERTAMINA EP ASSET 5, PERTAMINA EP, PERTAMINA (PERSERO)]]></cell><cell><![CDATA[Penyediaan Pekerja Jasa Penunjang Untuk Fungsi RAM Sangasanga Field]]></cell><cell><![CDATA[100,000,000]]></cell></row>
<row><cell><![CDATA[12]]></cell><cell><![CDATA[PERTAMINA EP ASSET 2, PERTAMINA EP, PERTAMINA (PERSERO)]]></cell><cell><![CDATA[Jasa Inpeksi COI dan Reserfikasi PLO Migas PT Pertamina EP Asset 2 Selama 2 Tahun]]></cell><cell><![CDATA[100,000,000]]></cell></row>
<row><cell><![CDATA[13]]></cell><cell><![CDATA[PERTAMINA EP ASSET 3, PERTAMINA EP, PERTAMINA (PERSERO)]]></cell><cell><![CDATA[Kontrak Payung (COO) Pekerjaan Geophysical Survey Fungsi Surface Facilities Asset 3 Periode Tahun 2020-2022 PT. Pertamina EP Asset 3]]></cell><cell><![CDATA[100,000,000]]></cell></row>
<row><cell><![CDATA[14]]></cell><cell><![CDATA[PERTAMINA EP, ASSET 5 TANJUNG, PERTAMINA EP ASSET 5, PERTAMINA (PERSERO), PT]]></cell><cell><![CDATA[Jasa Penyediaan Tenaga Kerja Jasa Penunjang Fungsi Engineering & Planing, Workover/Well Services, Production Operation PT PErtamina EP Asset 5 Tanjung Field Periode tahun 2021-2023]]></cell><cell><![CDATA[100,000,000]]></cell></row>
<row><cell><![CDATA[15]]></cell><cell><![CDATA[PERTAMINA EP ASSET 2 FIELD ADERA, PERTAMINA EP ASSET 2, PERTAMINA EP, PERTAMINA (PERSERO)]]></cell><cell><![CDATA[Jasa Pemantauan Kualitas Lingkungan (Pelaksanaan RKL/RPL Dan UKL/UPL Dan Uji Emisi Kendaraan Tahun 2021-2022 Field Adera]]></cell><cell><![CDATA[100,000,000]]></cell></row>
<row><cell><![CDATA[16]]></cell><cell><![CDATA[PERTAMINA EP ASSET 5, PERTAMINA EP, PERTAMINA (PERSERO)]]></cell><cell><![CDATA[Jasa Front End Engineering Design (FEED) Dan Detailed Engineering Design (DED) PT Pertamina EP Asset 5]]></cell><cell><![CDATA[100,000,000]]></cell></row>
<row><cell><![CDATA[17]]></cell><cell><![CDATA[PERTAMINA EP ASSET 4, PERTAMINA EP, PERTAMINA (PERSERO)]]></cell><cell><![CDATA[Jasa Pelaksanaan Pemantauan Lingkungan Dan Analisa Laboratorium PT Pertamina EP Asset 4 Donggi Matindok Field]]></cell><cell><![CDATA[100,000,000]]></cell></row>
<row><cell><![CDATA[18]]></cell><cell><![CDATA[PERTAMINA EP, PERTAMINA (PERSERO)]]></cell><cell><![CDATA[Jasa Pengembangan Aplikasi Dan Sistem Informasi PT Pertamina EP Selama 36 Bulan]]></cell><cell><![CDATA[100,000,000]]></cell></row>
<row><cell><![CDATA[19]]></cell><cell><![CDATA[PERTAMINA EP, PERTAMINA (PERSERO)]]></cell><cell><![CDATA[Jasa Manajemen Proyek Dan Assesment Teknis SF PEP 2021 (Selama 3 Tahun)]]></cell><cell><![CDATA[100,000,000]]></cell></row>
<row><cell><![CDATA[20]]></cell><cell><![CDATA[PERTAMINA EP, PERTAMINA (PERSERO)]]></cell><cell><![CDATA[Inspeksi Subsea Trunkline Gas Bunyu-Tarakan]]></cell><cell><![CDATA[100,000,000]]></cell></row>
<row><cell><![CDATA[21]]></cell><cell><![CDATA[PERTAMINA EP, ASSET 5 TANJUNG, PERTAMINA EP ASSET 5, PERTAMINA (PERSERO), PT]]></cell><cell><![CDATA[Jasa Penyediaan Tenaga Kerja Jasa Penunjang Fungsi RAM, HSSE, HR, LR, SCM, Finance, Dan ICT Di PT Pertamina EP Asset 5 Tanjung Field Periode Tahun 2021-2023]]></cell><cell><![CDATA[100,000,000]]></cell></row>
<row><cell><![CDATA[22]]></cell><cell><![CDATA[PERTAMINA EP ASSET 5, PERTAMINA EP, PERTAMINA (PERSERO)]]></cell><cell><![CDATA[PROJECT ENGINEERING & CONSTRUCTION MANAGEMENT SERVICES DI PT PERTAMINA EP WILAYAH KERJA ASSET 5]]></cell><cell><![CDATA[100,000,000]]></cell></row>
<row><cell><![CDATA[23]]></cell><cell><![CDATA[PLN (PERSERO) TRANSMISI JAWA BAGIAN TENGAH, PLN (PERSERO) DIVISI OPERASI REGIONAL JAWA BAGIAN TENGAH, PLN (PERSERO) BISNIS REGIONAL JAWA BAGIAN TENGAH, PLN (PERSERO)]]></cell><cell><![CDATA[Jasa Sertifikasi Laik Operasi (SLO) Jaringan Transmisi Tenaga Listrik (SUTT & SUTET) dan Gardu Induk di Seluruh UPT Jawa Bagian Tengah]]></cell><cell><![CDATA[100,000,000]]></cell></row>
<row><cell><![CDATA[24]]></cell><cell><![CDATA[PELABUHAN INDONESIA III (PERSERO) CABANG SEMARANG, PELABUHAN INDONESIA III (PERSERO)]]></cell><cell><![CDATA[Pekerjaan Pemantauan Lingkungan Tahun 2021 Pelabuhan Tanjung Emas]]></cell><cell><![CDATA[350,000,000]]></cell></row>
<row><cell><![CDATA[25]]></cell><cell><![CDATA[PLN (PERSERO) AREA PENGATURAN BEBAN JAWA TENGAH DAN DIY, PLN (PERSERO) PENYALUR DAN PUSAT PENGATUR BEBAN, PLN (PERSERO)]]></cell><cell><![CDATA[Pemeliharaan Dan Pengelolaan SMK3-Biaya Sertifikasi, Perijinan Dan Retribusi (Sertifikasi Peralatan K3)]]></cell><cell><![CDATA[75,000,000]]></cell></row>
<row><cell><![CDATA[26]]></cell><cell><![CDATA[PELABUHAN INDONESIA III (PERSERO) CABANG TANJUNG INTAN, PELABUHAN INDONESIA III (PERSERO)]]></cell><cell><![CDATA[Resertifikasi Peralatan]]></cell><cell><![CDATA[250,000,000]]></cell></row>
<row><cell><![CDATA[27]]></cell><cell><![CDATA[PJB UBJOM PLTU REMBANG, PEMBANGKITAN JAWA BALI (PJB), PLN (PERSERO)]]></cell><cell><![CDATA[Jasa Survey Analisa Kuantitas dan Kualitas HSD Biodiesel Melalui Jalur Darat]]></cell><cell><![CDATA[150,000,000]]></cell></row>
<row><cell><![CDATA[28]]></cell><cell><![CDATA[PERTAMINA (PERSERO) MOR IV, PERTAMINA (PERSERO) DIREKTORAT PEMASARAN DAN NIAGA, PERTAMINA (PERSERO)]]></cell><cell><![CDATA[Jasa Penyusunan Kajian Lokasi Pertashop Tahun 2021]]></cell><cell><![CDATA[450,000,000]]></cell></row>
<row><cell><![CDATA[29]]></cell><cell><![CDATA[PJB UBJOM PLTU REMBANG, PEMBANGKITAN JAWA BALI (PJB), PLN (PERSERO)]]></cell><cell><![CDATA[Jasa Sertifikasi Kalibrasi Belt Weigher untuk Monitoring Stock Batubara Unloading]]></cell><cell><![CDATA[150,000,000]]></cell></row>
<row><cell><![CDATA[30]]></cell><cell><![CDATA[PJB UBJOM PLTU INDRAMAYU, PEMBANGKITAN JAWA BALI (PJB), PLN (PERSERO)]]></cell><cell><![CDATA[Resertifikasi Peralatan]]></cell><cell><![CDATA[450,000,000]]></cell></row>
<row><cell><![CDATA[31]]></cell><cell><![CDATA[INDONESIA POWER UP MRICA, INDONESIA POWER UNIT PEMBANGKITAN (UP), INDONESIA POWER, PLN (PERSERO)]]></cell><cell><![CDATA[Resertifikasi Peralatan]]></cell><cell><![CDATA[250,000,000]]></cell></row>
<row><cell><![CDATA[32]]></cell><cell><![CDATA[PJB UBJOM PLTU REMBANG, PEMBANGKITAN JAWA BALI (PJB), PLN (PERSERO)]]></cell><cell><![CDATA[Jasa Pengukuran Data Kualitas Lingkungan Kerja]]></cell><cell><![CDATA[50,000,000]]></cell></row>
<row><cell><![CDATA[33]]></cell><cell><![CDATA[DHARMAPALA USAHA SUKSES]]></cell><cell><![CDATA[Resertifikasi Peralatan]]></cell><cell><![CDATA[75,000,000]]></cell></row>
<row><cell><![CDATA[34]]></cell><cell><![CDATA[INDONESIA POWER UP SEMARANG, INDONESIA POWER UNIT PEMBANGKITAN (UP), INDONESIA POWER, PLN (PERSERO)]]></cell><cell><![CDATA[2021 K3L Jasa Sertifikasi Valve PRV Dan PSV Main Line Gas PLTGU]]></cell><cell><![CDATA[20,000,000]]></cell></row>
<row><cell><![CDATA[35]]></cell><cell><![CDATA[RECKITT BENCKISER INDONESIA]]></cell><cell><![CDATA[Resertifikasi Peralatan]]></cell><cell><![CDATA[50,000,000]]></cell></row>
<row><cell><![CDATA[36]]></cell><cell><![CDATA[ADHI GUNA PUTERA]]></cell><cell><![CDATA[Resertifikasi Peralatan]]></cell><cell><![CDATA[100,000,000]]></cell></row>
<row><cell><![CDATA[37]]></cell><cell><![CDATA[INDONESIA POWER UJP PLTU JAWA TENGAH 2 ADIPALA, INDONESIA POWER UNIT JASA PEMBANGKITAN (UJP), INDONESIA POWER, PLN (PERSERO)]]></cell><cell><![CDATA[Resertifikasi Peralatan]]></cell><cell><![CDATA[100,000,000]]></cell></row>
<row><cell><![CDATA[38]]></cell><cell><![CDATA[UNZA VITALIS]]></cell><cell><![CDATA[Resertifikasi Peralatan]]></cell><cell><![CDATA[50,000,000]]></cell></row>
<row><cell><![CDATA[39]]></cell><cell><![CDATA[PEMBANGKITAN JAWA BALI SERVICES, PJB SERVICES, PEMBANGKITAN JAWA BALI (PJB), PLN (PERSERO)]]></cell><cell><![CDATA[Resertifikasi Peralatan PLTU Bangka, PLTU Belitung, PLTU Tembilahan]]></cell><cell><![CDATA[450,000,000]]></cell></row>
<row><cell><![CDATA[40]]></cell><cell><![CDATA[PLN (PERSERO) SEKTOR PEMBANGKITAN TARAHAN, PLN (PERSERO) PEMBANGKITAN SUMATERA BAGIAN SELATAN, PLN (PERSERO) DIVISI OPERASI REGIONAL SUMATERA, PLN (PERSERO) BISNIS REGIONAL SUMATERA, PLN (PERSERO)]]></cell><cell><![CDATA[Sertifikasi Peralatan K3 ( Alat Angkat Angkut, Safety Valve, Bejana Bertekanan )]]></cell><cell><![CDATA[450,000,000]]></cell></row>
<row><cell><![CDATA[41]]></cell><cell><![CDATA[PLN (PERSERO) TRANSMISI JAWA BAGIAN TENGAH, PLN (PERSERO) DIVISI OPERASI REGIONAL JAWA BAGIAN TENGAH, PLN (PERSERO) BISNIS REGIONAL JAWA BAGIAN TENGAH, PLN (PERSERO)]]></cell><cell><![CDATA[Pekerjaan Survey, Pemberkasan, Dan Sosialisasi ROW SUTT 150 KV Kudus - Jepara]]></cell><cell><![CDATA[1,500,000,000]]></cell></row>
<row><cell><![CDATA[42]]></cell><cell><![CDATA[PJB UBJOM PLTU TANJUNG AWAR-AWAR, PEMBANGKITAN JAWA BALI (PJB), PLN (PERSERO)]]></cell><cell><![CDATA[Resertifikasi Peralatan]]></cell><cell><![CDATA[500,000,000]]></cell></row>
<row><cell><![CDATA[43]]></cell><cell><![CDATA[NAGABHUANA ANEKA PIRANTI]]></cell><cell><![CDATA[Pemeriksaan Kayu]]></cell><cell><![CDATA[700,000,000]]></cell></row>
<row><cell><![CDATA[44]]></cell><cell><![CDATA[KEMENTERIAN LINGKUNGAN HIDUP DAN KEHUTANAN]]></cell><cell><![CDATA[Pengawasan dan Penilaian Tanaman RHL (PO) Tahun 2021]]></cell><cell><![CDATA[419,397,000]]></cell></row>
<row><cell><![CDATA[45]]></cell><cell><![CDATA[PJB UBJOM PLTU REMBANG, PEMBANGKITAN JAWA BALI (PJB), PLN (PERSERO)]]></cell><cell><![CDATA[JASA PEMANTAUAN LINGKUNGAN KERJA FAKTOR BIOLOGI, ERGONOMI, KIMIA, FISIKA (GETARAN) DAN PSIKOLOGI]]></cell><cell><![CDATA[100,000,000]]></cell></row>
<row><cell><![CDATA[46]]></cell><cell><![CDATA[KEMENTERIAN PERENCANAAN PEMBANGGUNAN (PPN/BAPPENAS)]]></cell><cell><![CDATA[Belanja Jasa Konsultan]]></cell><cell><![CDATA[100,000,000]]></cell></row>
<row><cell><![CDATA[47]]></cell><cell><![CDATA[KEMENTERIAN KOMUNIKASI DAN INFORMATIKA]]></cell><cell><![CDATA[Penyusunan Kajian Pembentukan Kelembagaan Pusat Data Nasional]]></cell><cell><![CDATA[100,000,000]]></cell></row>
<row><cell><![CDATA[48]]></cell><cell><![CDATA[KEMENTERIAN PEKERJAAN UMUM & PERUMAHAN RAKYAT]]></cell><cell><![CDATA[Toll Road Development Of Semarang - Demak 1A]]></cell><cell><![CDATA[100,000,000]]></cell></row>
<row><cell><![CDATA[49]]></cell><cell><![CDATA[KEMENTERIAN PEKERJAAN UMUM & PERUMAHAN RAKYAT]]></cell><cell><![CDATA[Toll Road Development Of Semarang - Demak 1C]]></cell><cell><![CDATA[100,000,000]]></cell></row>
<row><cell><![CDATA[50]]></cell><cell><![CDATA[KEMENTERIAN PEKERJAAN UMUM & PERUMAHAN RAKYAT]]></cell><cell><![CDATA[Toll Road Development Of Semarang - Demak 1B]]></cell><cell><![CDATA[100,000,000]]></cell></row>
<row><cell><![CDATA[51]]></cell><cell><![CDATA[PLN (PERSERO) UP3 KAPUAS, PLN (PERSERO) PEMBANGKITAN DAN PENYALURAN KALIMANTAN, PLN (PERSERO) WILAYAH KALIMANTAN SELATAN DAN TENGAH, PLN (PERSERO) DIVISI OPERASI REGIONAL KALIMANTAN, PLN (PERSERO) BISNIS REGIONAL KALIMANTAN, PLN (PERSERO)]]></cell><cell><![CDATA[Pengadaan Jasa Penentuan Kuantitas dan Analisa Kualtias Penerimaan Batubara]]></cell><cell><![CDATA[100,000,000]]></cell></row>
<row><cell><![CDATA[52]]></cell><cell><![CDATA[PJB UBJOM PLTU TANJUNG AWAR-AWAR, PEMBANGKITAN JAWA BALI (PJB), PLN (PERSERO)]]></cell><cell><![CDATA[Eddy Current Test Tube LP Heater 5, 6, 7 dan 8 SE #1 2021]]></cell><cell><![CDATA[100,000,000]]></cell></row>
<row><cell><![CDATA[53]]></cell><cell><![CDATA[PLN (PERSERO) UPDK BENGKULU, PLN (PERSERO) WILAYAH SUMSEL, JAMBI & BENGKULU, PLN (PERSERO) DIVISI OPERASI REGIONAL SUMATERA, PLN (PERSERO) BISNIS REGIONAL SUMATERA, PLN (PERSERO)]]></cell><cell><![CDATA[Pemantauan Lingkungan PLTA Musi dan PLTA Tes 2021 (RKL - RPL)]]></cell><cell><![CDATA[100,000,000]]></cell></row>
<row><cell><![CDATA[54]]></cell><cell><![CDATA[PLN (PERSERO) TRANSMISI JAWA BAGIAN TENGAH, PLN (PERSERO) DIVISI OPERASI REGIONAL JAWA BAGIAN TENGAH, PLN (PERSERO) BISNIS REGIONAL JAWA BAGIAN TENGAH, PLN (PERSERO)]]></cell><cell><![CDATA[PELAKSANAAN PENATAAN BATAS AREAL IPPKH JALUR SUTET 500 KV BANDUNG SELATAN - MANDIRANCAN SESUAI DENGAN PEDOMAN KERJA DAN INSTRUKSI KERJA TATA BATAS NO. INS.60/BPKH.XI/2/PLA.2/9/2020 (9 POLIGON)]]></cell><cell><![CDATA[100,000,000]]></cell></row>
<row><cell><![CDATA[55]]></cell><cell><![CDATA[PLN (PERSERO) TRANSMISI JAWA BAGIAN TENGAH, PLN (PERSERO) DIVISI OPERASI REGIONAL JAWA BAGIAN TENGAH, PLN (PERSERO) BISNIS REGIONAL JAWA BAGIAN TENGAH, PLN (PERSERO)]]></cell><cell><![CDATA[PENYUSUNAN DAN PENGESAHAN LAPORAN PELAKSANAAN PENATAAN BATAS AREAL IPPKH JALUR SUTET 500 KV BANDUNG SELATAN - MANDIRANCAN OLEH KLHK]]></cell><cell><![CDATA[50,000,000]]></cell></row>
<row><cell><![CDATA[56]]></cell><cell><![CDATA[PJB UBJOM LUAR JAWA 2, PEMBANGKITAN JAWA BALI (PJB), PLN (PERSERO)]]></cell><cell><![CDATA[Welder Test dan Supervisi Re Tubbing]]></cell><cell><![CDATA[25,000,000]]></cell></row>
<row><cell><![CDATA[57]]></cell><cell><![CDATA[PJB UBJOM LUAR JAWA 2, PEMBANGKITAN JAWA BALI (PJB), PLN (PERSERO)]]></cell><cell><![CDATA[Radiography Tube Boiler PLTU Ropa Ende Flores]]></cell><cell><![CDATA[60,000,000]]></cell></row>
<row><cell><![CDATA[58]]></cell><cell><![CDATA[PJB UBJOM PLTU PAITON, PEMBANGKITAN JAWA BALI (PJB), PLN (PERSERO)]]></cell><cell><![CDATA[Jasa Konsultan Kajian Kelayakan Pengembangan Kawasan Industri Paiton PJB Pusat]]></cell><cell><![CDATA[50,000,000]]></cell></row>
<row><cell><![CDATA[59]]></cell><cell><![CDATA[PEMBANGKITAN JAWA BALI (PJB), PLN (PERSERO)]]></cell><cell><![CDATA[Penyusunan Dokumen Analisis Dampak Lalu Lintas - Cirata Floating PV Power Plant 145 MWac - PJBI - Abu Dhabi Future Energy Company PJSE - Masdar]]></cell><cell><![CDATA[50,000,000]]></cell></row>
<row><cell><![CDATA[60]]></cell><cell><![CDATA[DWIPA KONEKTRA]]></cell><cell><![CDATA[Sertifikasi Peralatan - OHC 35 Ton, Hydrant, Fire Alarm]]></cell><cell><![CDATA[13,182,000]]></cell></row></rows><rows profile='color'><head><columns><column  width='50' align='right' type='ron' hidden='false' sort='int' color=''><![CDATA[No.]]></column><column  width='220' align='left' type='ro' hidden='false' sort='str' color=''><![CDATA[ Nama Klien]]></column><column  width='300' align='left' type='ron' hidden='false' sort='int' color=''><![CDATA[ Nama Proyek]]></column><column  width='120' align='right' type='ron' hidden='false' sort='int' color=''><![CDATA[ Nilai Kontrak]]></column></columns></head>
<foot>
<columns>
<column colspan='3' ><![CDATA[TOTAL]]></column>
<column><![CDATA[]]></column>
<column><![CDATA[]]></column>
<column><![CDATA[10,537,579,000]]></column>
</columns>
</foot><row><cell><![CDATA[1]]></cell><cell><![CDATA[PERTAMINA (PERSERO) REFINERY UNIT IV CILACAP, PERTAMINA (PERSERO) DIREKTORAT PENGOLAHAN, PERTAMINA (PERSERO)]]></cell><cell><![CDATA[Sertifikasi SMK3]]></cell><cell><![CDATA[200,000,000]]></cell></row>
<row><cell><![CDATA[2]]></cell><cell><![CDATA[PJB UBJOM PLTU REMBANG, PEMBANGKITAN JAWA BALI (PJB), PLN (PERSERO)]]></cell><cell><![CDATA[Pengadaan Kontrak Payung Pemantauan Udara Dan Limbah B3 Tahun 2021]]></cell><cell><![CDATA[500,000,000]]></cell></row>
<row><cell><![CDATA[3]]></cell><cell><![CDATA[PJB UBJOM PLTU PAITON, PEMBANGKITAN JAWA BALI (PJB), PLN (PERSERO)]]></cell><cell><![CDATA[Jasa Survey Analisa Kuantitas dan Kualitas HSD Biodiesel Melalui Jalur Darat]]></cell><cell><![CDATA[50,000,000]]></cell></row>
<row><cell><![CDATA[4]]></cell><cell><![CDATA[PJB UP CIRATA, PEMBANGKITAN JAWA BALI (PJB), PLN (PERSERO)]]></cell><cell><![CDATA[Resertifikasi Alat Berat (Tadano, Loader, Crane, Forklift dan Lift Car), OHC, Penangkal Petir, Gantry, Fire Alarm, Chain Block SY, PH, & Turbin]]></cell><cell><![CDATA[50,000,000]]></cell></row>
<row><cell><![CDATA[5]]></cell><cell><![CDATA[ENI MUARA BAKAU]]></cell><cell><![CDATA[Inspection Recertification and Maintenance Service For LSA And SE For Operation]]></cell><cell><![CDATA[100,000,000]]></cell></row>
<row><cell><![CDATA[6]]></cell><cell><![CDATA[MEDCO ENERGI]]></cell><cell><![CDATA[Front End Engineering Design (FEED) Study For Flare Gas Recovery]]></cell><cell><![CDATA[100,000,000]]></cell></row>
<row><cell><![CDATA[7]]></cell><cell><![CDATA[PERTAMINA EP, ASSET 4 CEPU, PERTAMINA EP, PERTAMINA (PERSERO)]]></cell><cell><![CDATA[Jasa Tenaga Kerja Third Party Contract Utuk Mendukung Project Pengembangan Lapangan Tiung Biru]]></cell><cell><![CDATA[100,000,000]]></cell></row>
<row><cell><![CDATA[8]]></cell><cell><![CDATA[PERTAMINA EP, PERTAMINA (PERSERO)]]></cell><cell><![CDATA[Kontrak Sertifikasi, Kalibrasi, dan Assesment]]></cell><cell><![CDATA[100,000,000]]></cell></row>
<row><cell><![CDATA[9]]></cell><cell><![CDATA[PERTAMINA EP ASSET 1, PERTAMINA EP, PERTAMINA (PERSERO)]]></cell><cell><![CDATA[Project Management Consultant (PMC) Untuk Membantu Pengawasan Konstruksi & QA/QC di Fungsi Asset 1 Surface Facilities PT Pertamina EP Tahun 2020-2021]]></cell><cell><![CDATA[100,000,000]]></cell></row>
<row><cell><![CDATA[10]]></cell><cell><![CDATA[PERTAMINA EP ASSET 2, PERTAMINA EP, PERTAMINA (PERSERO)]]></cell><cell><![CDATA[Call Of Order Jasa Inspeksi dan Pengetesan di Pertamina EP Asset 2]]></cell><cell><![CDATA[100,000,000]]></cell></row>
<row><cell><![CDATA[11]]></cell><cell><![CDATA[PERTAMINA EP, ASSET 5 SANGASANGA, PERTAMINA EP ASSET 5, PERTAMINA EP, PERTAMINA (PERSERO)]]></cell><cell><![CDATA[Penyediaan Pekerja Jasa Penunjang Untuk Fungsi RAM Sangasanga Field]]></cell><cell><![CDATA[100,000,000]]></cell></row>
<row><cell><![CDATA[12]]></cell><cell><![CDATA[PERTAMINA EP ASSET 2, PERTAMINA EP, PERTAMINA (PERSERO)]]></cell><cell><![CDATA[Jasa Inpeksi COI dan Reserfikasi PLO Migas PT Pertamina EP Asset 2 Selama 2 Tahun]]></cell><cell><![CDATA[100,000,000]]></cell></row>
<row><cell><![CDATA[13]]></cell><cell><![CDATA[PERTAMINA EP ASSET 3, PERTAMINA EP, PERTAMINA (PERSERO)]]></cell><cell><![CDATA[Kontrak Payung (COO) Pekerjaan Geophysical Survey Fungsi Surface Facilities Asset 3 Periode Tahun 2020-2022 PT. Pertamina EP Asset 3]]></cell><cell><![CDATA[100,000,000]]></cell></row>
<row><cell><![CDATA[14]]></cell><cell><![CDATA[PERTAMINA EP, ASSET 5 TANJUNG, PERTAMINA EP ASSET 5, PERTAMINA (PERSERO), PT]]></cell><cell><![CDATA[Jasa Penyediaan Tenaga Kerja Jasa Penunjang Fungsi Engineering & Planing, Workover/Well Services, Production Operation PT PErtamina EP Asset 5 Tanjung Field Periode tahun 2021-2023]]></cell><cell><![CDATA[100,000,000]]></cell></row>
<row><cell><![CDATA[15]]></cell><cell><![CDATA[PERTAMINA EP ASSET 2 FIELD ADERA, PERTAMINA EP ASSET 2, PERTAMINA EP, PERTAMINA (PERSERO)]]></cell><cell><![CDATA[Jasa Pemantauan Kualitas Lingkungan (Pelaksanaan RKL/RPL Dan UKL/UPL Dan Uji Emisi Kendaraan Tahun 2021-2022 Field Adera]]></cell><cell><![CDATA[100,000,000]]></cell></row>
<row><cell><![CDATA[16]]></cell><cell><![CDATA[PERTAMINA EP ASSET 5, PERTAMINA EP, PERTAMINA (PERSERO)]]></cell><cell><![CDATA[Jasa Front End Engineering Design (FEED) Dan Detailed Engineering Design (DED) PT Pertamina EP Asset 5]]></cell><cell><![CDATA[100,000,000]]></cell></row>
<row><cell><![CDATA[17]]></cell><cell><![CDATA[PERTAMINA EP ASSET 4, PERTAMINA EP, PERTAMINA (PERSERO)]]></cell><cell><![CDATA[Jasa Pelaksanaan Pemantauan Lingkungan Dan Analisa Laboratorium PT Pertamina EP Asset 4 Donggi Matindok Field]]></cell><cell><![CDATA[100,000,000]]></cell></row>
<row><cell><![CDATA[18]]></cell><cell><![CDATA[PERTAMINA EP, PERTAMINA (PERSERO)]]></cell><cell><![CDATA[Jasa Pengembangan Aplikasi Dan Sistem Informasi PT Pertamina EP Selama 36 Bulan]]></cell><cell><![CDATA[100,000,000]]></cell></row>
<row><cell><![CDATA[19]]></cell><cell><![CDATA[PERTAMINA EP, PERTAMINA (PERSERO)]]></cell><cell><![CDATA[Jasa Manajemen Proyek Dan Assesment Teknis SF PEP 2021 (Selama 3 Tahun)]]></cell><cell><![CDATA[100,000,000]]></cell></row>
<row><cell><![CDATA[20]]></cell><cell><![CDATA[PERTAMINA EP, PERTAMINA (PERSERO)]]></cell><cell><![CDATA[Inspeksi Subsea Trunkline Gas Bunyu-Tarakan]]></cell><cell><![CDATA[100,000,000]]></cell></row>
<row><cell><![CDATA[21]]></cell><cell><![CDATA[PERTAMINA EP, ASSET 5 TANJUNG, PERTAMINA EP ASSET 5, PERTAMINA (PERSERO), PT]]></cell><cell><![CDATA[Jasa Penyediaan Tenaga Kerja Jasa Penunjang Fungsi RAM, HSSE, HR, LR, SCM, Finance, Dan ICT Di PT Pertamina EP Asset 5 Tanjung Field Periode Tahun 2021-2023]]></cell><cell><![CDATA[100,000,000]]></cell></row>
<row><cell><![CDATA[22]]></cell><cell><![CDATA[PERTAMINA EP ASSET 5, PERTAMINA EP, PERTAMINA (PERSERO)]]></cell><cell><![CDATA[PROJECT ENGINEERING & CONSTRUCTION MANAGEMENT SERVICES DI PT PERTAMINA EP WILAYAH KERJA ASSET 5]]></cell><cell><![CDATA[100,000,000]]></cell></row>
<row><cell><![CDATA[23]]></cell><cell><![CDATA[PLN (PERSERO) TRANSMISI JAWA BAGIAN TENGAH, PLN (PERSERO) DIVISI OPERASI REGIONAL JAWA BAGIAN TENGAH, PLN (PERSERO) BISNIS REGIONAL JAWA BAGIAN TENGAH, PLN (PERSERO)]]></cell><cell><![CDATA[Jasa Sertifikasi Laik Operasi (SLO) Jaringan Transmisi Tenaga Listrik (SUTT & SUTET) dan Gardu Induk di Seluruh UPT Jawa Bagian Tengah]]></cell><cell><![CDATA[100,000,000]]></cell></row>
<row><cell><![CDATA[24]]></cell><cell><![CDATA[PELABUHAN INDONESIA III (PERSERO) CABANG SEMARANG, PELABUHAN INDONESIA III (PERSERO)]]></cell><cell><![CDATA[Pekerjaan Pemantauan Lingkungan Tahun 2021 Pelabuhan Tanjung Emas]]></cell><cell><![CDATA[350,000,000]]></cell></row>
<row><cell><![CDATA[25]]></cell><cell><![CDATA[PLN (PERSERO) AREA PENGATURAN BEBAN JAWA TENGAH DAN DIY, PLN (PERSERO) PENYALUR DAN PUSAT PENGATUR BEBAN, PLN (PERSERO)]]></cell><cell><![CDATA[Pemeliharaan Dan Pengelolaan SMK3-Biaya Sertifikasi, Perijinan Dan Retribusi (Sertifikasi Peralatan K3)]]></cell><cell><![CDATA[75,000,000]]></cell></row>
<row><cell><![CDATA[26]]></cell><cell><![CDATA[PELABUHAN INDONESIA III (PERSERO) CABANG TANJUNG INTAN, PELABUHAN INDONESIA III (PERSERO)]]></cell><cell><![CDATA[Resertifikasi Peralatan]]></cell><cell><![CDATA[250,000,000]]></cell></row>
<row><cell><![CDATA[27]]></cell><cell><![CDATA[PJB UBJOM PLTU REMBANG, PEMBANGKITAN JAWA BALI (PJB), PLN (PERSERO)]]></cell><cell><![CDATA[Jasa Survey Analisa Kuantitas dan Kualitas HSD Biodiesel Melalui Jalur Darat]]></cell><cell><![CDATA[150,000,000]]></cell></row>
<row><cell><![CDATA[28]]></cell><cell><![CDATA[PERTAMINA (PERSERO) MOR IV, PERTAMINA (PERSERO) DIREKTORAT PEMASARAN DAN NIAGA, PERTAMINA (PERSERO)]]></cell><cell><![CDATA[Jasa Penyusunan Kajian Lokasi Pertashop Tahun 2021]]></cell><cell><![CDATA[450,000,000]]></cell></row>
<row><cell><![CDATA[29]]></cell><cell><![CDATA[PJB UBJOM PLTU REMBANG, PEMBANGKITAN JAWA BALI (PJB), PLN (PERSERO)]]></cell><cell><![CDATA[Jasa Sertifikasi Kalibrasi Belt Weigher untuk Monitoring Stock Batubara Unloading]]></cell><cell><![CDATA[150,000,000]]></cell></row>
<row><cell><![CDATA[30]]></cell><cell><![CDATA[PJB UBJOM PLTU INDRAMAYU, PEMBANGKITAN JAWA BALI (PJB), PLN (PERSERO)]]></cell><cell><![CDATA[Resertifikasi Peralatan]]></cell><cell><![CDATA[450,000,000]]></cell></row>
<row><cell><![CDATA[31]]></cell><cell><![CDATA[INDONESIA POWER UP MRICA, INDONESIA POWER UNIT PEMBANGKITAN (UP), INDONESIA POWER, PLN (PERSERO)]]></cell><cell><![CDATA[Resertifikasi Peralatan]]></cell><cell><![CDATA[250,000,000]]></cell></row>
<row><cell><![CDATA[32]]></cell><cell><![CDATA[PJB UBJOM PLTU REMBANG, PEMBANGKITAN JAWA BALI (PJB), PLN (PERSERO)]]></cell><cell><![CDATA[Jasa Pengukuran Data Kualitas Lingkungan Kerja]]></cell><cell><![CDATA[50,000,000]]></cell></row>
<row><cell><![CDATA[33]]></cell><cell><![CDATA[DHARMAPALA USAHA SUKSES]]></cell><cell><![CDATA[Resertifikasi Peralatan]]></cell><cell><![CDATA[75,000,000]]></cell></row>
<row><cell><![CDATA[34]]></cell><cell><![CDATA[INDONESIA POWER UP SEMARANG, INDONESIA POWER UNIT PEMBANGKITAN (UP), INDONESIA POWER, PLN (PERSERO)]]></cell><cell><![CDATA[2021 K3L Jasa Sertifikasi Valve PRV Dan PSV Main Line Gas PLTGU]]></cell><cell><![CDATA[20,000,000]]></cell></row>
<row><cell><![CDATA[35]]></cell><cell><![CDATA[RECKITT BENCKISER INDONESIA]]></cell><cell><![CDATA[Resertifikasi Peralatan]]></cell><cell><![CDATA[50,000,000]]></cell></row>
<row><cell><![CDATA[36]]></cell><cell><![CDATA[ADHI GUNA PUTERA]]></cell><cell><![CDATA[Resertifikasi Peralatan]]></cell><cell><![CDATA[100,000,000]]></cell></row>
<row><cell><![CDATA[37]]></cell><cell><![CDATA[INDONESIA POWER UJP PLTU JAWA TENGAH 2 ADIPALA, INDONESIA POWER UNIT JASA PEMBANGKITAN (UJP), INDONESIA POWER, PLN (PERSERO)]]></cell><cell><![CDATA[Resertifikasi Peralatan]]></cell><cell><![CDATA[100,000,000]]></cell></row>
<row><cell><![CDATA[38]]></cell><cell><![CDATA[UNZA VITALIS]]></cell><cell><![CDATA[Resertifikasi Peralatan]]></cell><cell><![CDATA[50,000,000]]></cell></row>
<row><cell><![CDATA[39]]></cell><cell><![CDATA[PEMBANGKITAN JAWA BALI SERVICES, PJB SERVICES, PEMBANGKITAN JAWA BALI (PJB), PLN (PERSERO)]]></cell><cell><![CDATA[Resertifikasi Peralatan PLTU Bangka, PLTU Belitung, PLTU Tembilahan]]></cell><cell><![CDATA[450,000,000]]></cell></row>
<row><cell><![CDATA[40]]></cell><cell><![CDATA[PLN (PERSERO) SEKTOR PEMBANGKITAN TARAHAN, PLN (PERSERO) PEMBANGKITAN SUMATERA BAGIAN SELATAN, PLN (PERSERO) DIVISI OPERASI REGIONAL SUMATERA, PLN (PERSERO) BISNIS REGIONAL SUMATERA, PLN (PERSERO)]]></cell><cell><![CDATA[Sertifikasi Peralatan K3 ( Alat Angkat Angkut, Safety Valve, Bejana Bertekanan )]]></cell><cell><![CDATA[450,000,000]]></cell></row>
<row><cell><![CDATA[41]]></cell><cell><![CDATA[PLN (PERSERO) TRANSMISI JAWA BAGIAN TENGAH, PLN (PERSERO) DIVISI OPERASI REGIONAL JAWA BAGIAN TENGAH, PLN (PERSERO) BISNIS REGIONAL JAWA BAGIAN TENGAH, PLN (PERSERO)]]></cell><cell><![CDATA[Pekerjaan Survey, Pemberkasan, Dan Sosialisasi ROW SUTT 150 KV Kudus - Jepara]]></cell><cell><![CDATA[1,500,000,000]]></cell></row>
<row><cell><![CDATA[42]]></cell><cell><![CDATA[PJB UBJOM PLTU TANJUNG AWAR-AWAR, PEMBANGKITAN JAWA BALI (PJB), PLN (PERSERO)]]></cell><cell><![CDATA[Resertifikasi Peralatan]]></cell><cell><![CDATA[500,000,000]]></cell></row>
<row><cell><![CDATA[43]]></cell><cell><![CDATA[NAGABHUANA ANEKA PIRANTI]]></cell><cell><![CDATA[Pemeriksaan Kayu]]></cell><cell><![CDATA[700,000,000]]></cell></row>
<row><cell><![CDATA[44]]></cell><cell><![CDATA[KEMENTERIAN LINGKUNGAN HIDUP DAN KEHUTANAN]]></cell><cell><![CDATA[Pengawasan dan Penilaian Tanaman RHL (PO) Tahun 2021]]></cell><cell><![CDATA[419,397,000]]></cell></row>
<row><cell><![CDATA[45]]></cell><cell><![CDATA[PJB UBJOM PLTU REMBANG, PEMBANGKITAN JAWA BALI (PJB), PLN (PERSERO)]]></cell><cell><![CDATA[JASA PEMANTAUAN LINGKUNGAN KERJA FAKTOR BIOLOGI, ERGONOMI, KIMIA, FISIKA (GETARAN) DAN PSIKOLOGI]]></cell><cell><![CDATA[100,000,000]]></cell></row>
<row><cell><![CDATA[46]]></cell><cell><![CDATA[KEMENTERIAN PERENCANAAN PEMBANGGUNAN (PPN/BAPPENAS)]]></cell><cell><![CDATA[Belanja Jasa Konsultan]]></cell><cell><![CDATA[100,000,000]]></cell></row>
<row><cell><![CDATA[47]]></cell><cell><![CDATA[KEMENTERIAN KOMUNIKASI DAN INFORMATIKA]]></cell><cell><![CDATA[Penyusunan Kajian Pembentukan Kelembagaan Pusat Data Nasional]]></cell><cell><![CDATA[100,000,000]]></cell></row>
<row><cell><![CDATA[48]]></cell><cell><![CDATA[KEMENTERIAN PEKERJAAN UMUM & PERUMAHAN RAKYAT]]></cell><cell><![CDATA[Toll Road Development Of Semarang - Demak 1A]]></cell><cell><![CDATA[100,000,000]]></cell></row>
<row><cell><![CDATA[49]]></cell><cell><![CDATA[KEMENTERIAN PEKERJAAN UMUM & PERUMAHAN RAKYAT]]></cell><cell><![CDATA[Toll Road Development Of Semarang - Demak 1C]]></cell><cell><![CDATA[100,000,000]]></cell></row>
<row><cell><![CDATA[50]]></cell><cell><![CDATA[KEMENTERIAN PEKERJAAN UMUM & PERUMAHAN RAKYAT]]></cell><cell><![CDATA[Toll Road Development Of Semarang - Demak 1B]]></cell><cell><![CDATA[100,000,000]]></cell></row>
<row><cell><![CDATA[51]]></cell><cell><![CDATA[PLN (PERSERO) UP3 KAPUAS, PLN (PERSERO) PEMBANGKITAN DAN PENYALURAN KALIMANTAN, PLN (PERSERO) WILAYAH KALIMANTAN SELATAN DAN TENGAH, PLN (PERSERO) DIVISI OPERASI REGIONAL KALIMANTAN, PLN (PERSERO) BISNIS REGIONAL KALIMANTAN, PLN (PERSERO)]]></cell><cell><![CDATA[Pengadaan Jasa Penentuan Kuantitas dan Analisa Kualtias Penerimaan Batubara]]></cell><cell><![CDATA[100,000,000]]></cell></row>
<row><cell><![CDATA[52]]></cell><cell><![CDATA[PJB UBJOM PLTU TANJUNG AWAR-AWAR, PEMBANGKITAN JAWA BALI (PJB), PLN (PERSERO)]]></cell><cell><![CDATA[Eddy Current Test Tube LP Heater 5, 6, 7 dan 8 SE #1 2021]]></cell><cell><![CDATA[100,000,000]]></cell></row>
<row><cell><![CDATA[53]]></cell><cell><![CDATA[PLN (PERSERO) UPDK BENGKULU, PLN (PERSERO) WILAYAH SUMSEL, JAMBI & BENGKULU, PLN (PERSERO) DIVISI OPERASI REGIONAL SUMATERA, PLN (PERSERO) BISNIS REGIONAL SUMATERA, PLN (PERSERO)]]></cell><cell><![CDATA[Pemantauan Lingkungan PLTA Musi dan PLTA Tes 2021 (RKL - RPL)]]></cell><cell><![CDATA[100,000,000]]></cell></row>
<row><cell><![CDATA[54]]></cell><cell><![CDATA[PLN (PERSERO) TRANSMISI JAWA BAGIAN TENGAH, PLN (PERSERO) DIVISI OPERASI REGIONAL JAWA BAGIAN TENGAH, PLN (PERSERO) BISNIS REGIONAL JAWA BAGIAN TENGAH, PLN (PERSERO)]]></cell><cell><![CDATA[PELAKSANAAN PENATAAN BATAS AREAL IPPKH JALUR SUTET 500 KV BANDUNG SELATAN - MANDIRANCAN SESUAI DENGAN PEDOMAN KERJA DAN INSTRUKSI KERJA TATA BATAS NO. INS.60/BPKH.XI/2/PLA.2/9/2020 (9 POLIGON)]]></cell><cell><![CDATA[100,000,000]]></cell></row>
<row><cell><![CDATA[55]]></cell><cell><![CDATA[PLN (PERSERO) TRANSMISI JAWA BAGIAN TENGAH, PLN (PERSERO) DIVISI OPERASI REGIONAL JAWA BAGIAN TENGAH, PLN (PERSERO) BISNIS REGIONAL JAWA BAGIAN TENGAH, PLN (PERSERO)]]></cell><cell><![CDATA[PENYUSUNAN DAN PENGESAHAN LAPORAN PELAKSANAAN PENATAAN BATAS AREAL IPPKH JALUR SUTET 500 KV BANDUNG SELATAN - MANDIRANCAN OLEH KLHK]]></cell><cell><![CDATA[50,000,000]]></cell></row>
<row><cell><![CDATA[56]]></cell><cell><![CDATA[PJB UBJOM LUAR JAWA 2, PEMBANGKITAN JAWA BALI (PJB), PLN (PERSERO)]]></cell><cell><![CDATA[Welder Test dan Supervisi Re Tubbing]]></cell><cell><![CDATA[25,000,000]]></cell></row>
<row><cell><![CDATA[57]]></cell><cell><![CDATA[PJB UBJOM LUAR JAWA 2, PEMBANGKITAN JAWA BALI (PJB), PLN (PERSERO)]]></cell><cell><![CDATA[Radiography Tube Boiler PLTU Ropa Ende Flores]]></cell><cell><![CDATA[60,000,000]]></cell></row>
<row><cell><![CDATA[58]]></cell><cell><![CDATA[PJB UBJOM PLTU PAITON, PEMBANGKITAN JAWA BALI (PJB), PLN (PERSERO)]]></cell><cell><![CDATA[Jasa Konsultan Kajian Kelayakan Pengembangan Kawasan Industri Paiton PJB Pusat]]></cell><cell><![CDATA[50,000,000]]></cell></row>
<row><cell><![CDATA[59]]></cell><cell><![CDATA[PEMBANGKITAN JAWA BALI (PJB), PLN (PERSERO)]]></cell><cell><![CDATA[Penyusunan Dokumen Analisis Dampak Lalu Lintas - Cirata Floating PV Power Plant 145 MWac - PJBI - Abu Dhabi Future Energy Company PJSE - Masdar]]></cell><cell><![CDATA[50,000,000]]></cell></row>
<row><cell><![CDATA[60]]></cell><cell><![CDATA[DWIPA KONEKTRA]]></cell><cell><![CDATA[Sertifikasi Peralatan - OHC 35 Ton, Hydrant, Fire Alarm]]></cell><cell><![CDATA[13,182,000]]></cell></row></rows><rows profile='color'><head><columns><column  width='50' align='right' type='ron' hidden='false' sort='int' color=''><![CDATA[No.]]></column><column  width='220' align='left' type='ro' hidden='false' sort='str' color=''><![CDATA[ Nama Klien]]></column><column  width='300' align='left' type='ron' hidden='false' sort='int' color=''><![CDATA[ Nama Proyek]]></column><column  width='120' align='right' type='ron' hidden='false' sort='int' color=''><![CDATA[ Nilai Kontrak]]></column></columns></head>
<foot>
<columns>
<column colspan='3' ><![CDATA[TOTAL]]></column>
<column><![CDATA[]]></column>
<column><![CDATA[]]></column>
<column><![CDATA[10,537,579,000]]></column>
</columns>
</foot><row><cell><![CDATA[1]]></cell><cell><![CDATA[PERTAMINA (PERSERO) REFINERY UNIT IV CILACAP, PERTAMINA (PERSERO) DIREKTORAT PENGOLAHAN, PERTAMINA (PERSERO)]]></cell><cell><![CDATA[Sertifikasi SMK3]]></cell><cell><![CDATA[200,000,000]]></cell></row>
<row><cell><![CDATA[2]]></cell><cell><![CDATA[PJB UBJOM PLTU REMBANG, PEMBANGKITAN JAWA BALI (PJB), PLN (PERSERO)]]></cell><cell><![CDATA[Pengadaan Kontrak Payung Pemantauan Udara Dan Limbah B3 Tahun 2021]]></cell><cell><![CDATA[500,000,000]]></cell></row>
<row><cell><![CDATA[3]]></cell><cell><![CDATA[PJB UBJOM PLTU PAITON, PEMBANGKITAN JAWA BALI (PJB), PLN (PERSERO)]]></cell><cell><![CDATA[Jasa Survey Analisa Kuantitas dan Kualitas HSD Biodiesel Melalui Jalur Darat]]></cell><cell><![CDATA[50,000,000]]></cell></row>
<row><cell><![CDATA[4]]></cell><cell><![CDATA[PJB UP CIRATA, PEMBANGKITAN JAWA BALI (PJB), PLN (PERSERO)]]></cell><cell><![CDATA[Resertifikasi Alat Berat (Tadano, Loader, Crane, Forklift dan Lift Car), OHC, Penangkal Petir, Gantry, Fire Alarm, Chain Block SY, PH, & Turbin]]></cell><cell><![CDATA[50,000,000]]></cell></row>
<row><cell><![CDATA[5]]></cell><cell><![CDATA[ENI MUARA BAKAU]]></cell><cell><![CDATA[Inspection Recertification and Maintenance Service For LSA And SE For Operation]]></cell><cell><![CDATA[100,000,000]]></cell></row>
<row><cell><![CDATA[6]]></cell><cell><![CDATA[MEDCO ENERGI]]></cell><cell><![CDATA[Front End Engineering Design (FEED) Study For Flare Gas Recovery]]></cell><cell><![CDATA[100,000,000]]></cell></row>
<row><cell><![CDATA[7]]></cell><cell><![CDATA[PERTAMINA EP, ASSET 4 CEPU, PERTAMINA EP, PERTAMINA (PERSERO)]]></cell><cell><![CDATA[Jasa Tenaga Kerja Third Party Contract Utuk Mendukung Project Pengembangan Lapangan Tiung Biru]]></cell><cell><![CDATA[100,000,000]]></cell></row>
<row><cell><![CDATA[8]]></cell><cell><![CDATA[PERTAMINA EP, PERTAMINA (PERSERO)]]></cell><cell><![CDATA[Kontrak Sertifikasi, Kalibrasi, dan Assesment]]></cell><cell><![CDATA[100,000,000]]></cell></row>
<row><cell><![CDATA[9]]></cell><cell><![CDATA[PERTAMINA EP ASSET 1, PERTAMINA EP, PERTAMINA (PERSERO)]]></cell><cell><![CDATA[Project Management Consultant (PMC) Untuk Membantu Pengawasan Konstruksi & QA/QC di Fungsi Asset 1 Surface Facilities PT Pertamina EP Tahun 2020-2021]]></cell><cell><![CDATA[100,000,000]]></cell></row>
<row><cell><![CDATA[10]]></cell><cell><![CDATA[PERTAMINA EP ASSET 2, PERTAMINA EP, PERTAMINA (PERSERO)]]></cell><cell><![CDATA[Call Of Order Jasa Inspeksi dan Pengetesan di Pertamina EP Asset 2]]></cell><cell><![CDATA[100,000,000]]></cell></row>
<row><cell><![CDATA[11]]></cell><cell><![CDATA[PERTAMINA EP, ASSET 5 SANGASANGA, PERTAMINA EP ASSET 5, PERTAMINA EP, PERTAMINA (PERSERO)]]></cell><cell><![CDATA[Penyediaan Pekerja Jasa Penunjang Untuk Fungsi RAM Sangasanga Field]]></cell><cell><![CDATA[100,000,000]]></cell></row>
<row><cell><![CDATA[12]]></cell><cell><![CDATA[PERTAMINA EP ASSET 2, PERTAMINA EP, PERTAMINA (PERSERO)]]></cell><cell><![CDATA[Jasa Inpeksi COI dan Reserfikasi PLO Migas PT Pertamina EP Asset 2 Selama 2 Tahun]]></cell><cell><![CDATA[100,000,000]]></cell></row>
<row><cell><![CDATA[13]]></cell><cell><![CDATA[PERTAMINA EP ASSET 3, PERTAMINA EP, PERTAMINA (PERSERO)]]></cell><cell><![CDATA[Kontrak Payung (COO) Pekerjaan Geophysical Survey Fungsi Surface Facilities Asset 3 Periode Tahun 2020-2022 PT. Pertamina EP Asset 3]]></cell><cell><![CDATA[100,000,000]]></cell></row>
<row><cell><![CDATA[14]]></cell><cell><![CDATA[PERTAMINA EP, ASSET 5 TANJUNG, PERTAMINA EP ASSET 5, PERTAMINA (PERSERO), PT]]></cell><cell><![CDATA[Jasa Penyediaan Tenaga Kerja Jasa Penunjang Fungsi Engineering & Planing, Workover/Well Services, Production Operation PT PErtamina EP Asset 5 Tanjung Field Periode tahun 2021-2023]]></cell><cell><![CDATA[100,000,000]]></cell></row>
<row><cell><![CDATA[15]]></cell><cell><![CDATA[PERTAMINA EP ASSET 2 FIELD ADERA, PERTAMINA EP ASSET 2, PERTAMINA EP, PERTAMINA (PERSERO)]]></cell><cell><![CDATA[Jasa Pemantauan Kualitas Lingkungan (Pelaksanaan RKL/RPL Dan UKL/UPL Dan Uji Emisi Kendaraan Tahun 2021-2022 Field Adera]]></cell><cell><![CDATA[100,000,000]]></cell></row>
<row><cell><![CDATA[16]]></cell><cell><![CDATA[PERTAMINA EP ASSET 5, PERTAMINA EP, PERTAMINA (PERSERO)]]></cell><cell><![CDATA[Jasa Front End Engineering Design (FEED) Dan Detailed Engineering Design (DED) PT Pertamina EP Asset 5]]></cell><cell><![CDATA[100,000,000]]></cell></row>
<row><cell><![CDATA[17]]></cell><cell><![CDATA[PERTAMINA EP ASSET 4, PERTAMINA EP, PERTAMINA (PERSERO)]]></cell><cell><![CDATA[Jasa Pelaksanaan Pemantauan Lingkungan Dan Analisa Laboratorium PT Pertamina EP Asset 4 Donggi Matindok Field]]></cell><cell><![CDATA[100,000,000]]></cell></row>
<row><cell><![CDATA[18]]></cell><cell><![CDATA[PERTAMINA EP, PERTAMINA (PERSERO)]]></cell><cell><![CDATA[Jasa Pengembangan Aplikasi Dan Sistem Informasi PT Pertamina EP Selama 36 Bulan]]></cell><cell><![CDATA[100,000,000]]></cell></row>
<row><cell><![CDATA[19]]></cell><cell><![CDATA[PERTAMINA EP, PERTAMINA (PERSERO)]]></cell><cell><![CDATA[Jasa Manajemen Proyek Dan Assesment Teknis SF PEP 2021 (Selama 3 Tahun)]]></cell><cell><![CDATA[100,000,000]]></cell></row>
<row><cell><![CDATA[20]]></cell><cell><![CDATA[PERTAMINA EP, PERTAMINA (PERSERO)]]></cell><cell><![CDATA[Inspeksi Subsea Trunkline Gas Bunyu-Tarakan]]></cell><cell><![CDATA[100,000,000]]></cell></row>
<row><cell><![CDATA[21]]></cell><cell><![CDATA[PERTAMINA EP, ASSET 5 TANJUNG, PERTAMINA EP ASSET 5, PERTAMINA (PERSERO), PT]]></cell><cell><![CDATA[Jasa Penyediaan Tenaga Kerja Jasa Penunjang Fungsi RAM, HSSE, HR, LR, SCM, Finance, Dan ICT Di PT Pertamina EP Asset 5 Tanjung Field Periode Tahun 2021-2023]]></cell><cell><![CDATA[100,000,000]]></cell></row>
<row><cell><![CDATA[22]]></cell><cell><![CDATA[PERTAMINA EP ASSET 5, PERTAMINA EP, PERTAMINA (PERSERO)]]></cell><cell><![CDATA[PROJECT ENGINEERING & CONSTRUCTION MANAGEMENT SERVICES DI PT PERTAMINA EP WILAYAH KERJA ASSET 5]]></cell><cell><![CDATA[100,000,000]]></cell></row>
<row><cell><![CDATA[23]]></cell><cell><![CDATA[PLN (PERSERO) TRANSMISI JAWA BAGIAN TENGAH, PLN (PERSERO) DIVISI OPERASI REGIONAL JAWA BAGIAN TENGAH, PLN (PERSERO) BISNIS REGIONAL JAWA BAGIAN TENGAH, PLN (PERSERO)]]></cell><cell><![CDATA[Jasa Sertifikasi Laik Operasi (SLO) Jaringan Transmisi Tenaga Listrik (SUTT & SUTET) dan Gardu Induk di Seluruh UPT Jawa Bagian Tengah]]></cell><cell><![CDATA[100,000,000]]></cell></row>
<row><cell><![CDATA[24]]></cell><cell><![CDATA[PELABUHAN INDONESIA III (PERSERO) CABANG SEMARANG, PELABUHAN INDONESIA III (PERSERO)]]></cell><cell><![CDATA[Pekerjaan Pemantauan Lingkungan Tahun 2021 Pelabuhan Tanjung Emas]]></cell><cell><![CDATA[350,000,000]]></cell></row>
<row><cell><![CDATA[25]]></cell><cell><![CDATA[PLN (PERSERO) AREA PENGATURAN BEBAN JAWA TENGAH DAN DIY, PLN (PERSERO) PENYALUR DAN PUSAT PENGATUR BEBAN, PLN (PERSERO)]]></cell><cell><![CDATA[Pemeliharaan Dan Pengelolaan SMK3-Biaya Sertifikasi, Perijinan Dan Retribusi (Sertifikasi Peralatan K3)]]></cell><cell><![CDATA[75,000,000]]></cell></row>
<row><cell><![CDATA[26]]></cell><cell><![CDATA[PELABUHAN INDONESIA III (PERSERO) CABANG TANJUNG INTAN, PELABUHAN INDONESIA III (PERSERO)]]></cell><cell><![CDATA[Resertifikasi Peralatan]]></cell><cell><![CDATA[250,000,000]]></cell></row>
<row><cell><![CDATA[27]]></cell><cell><![CDATA[PJB UBJOM PLTU REMBANG, PEMBANGKITAN JAWA BALI (PJB), PLN (PERSERO)]]></cell><cell><![CDATA[Jasa Survey Analisa Kuantitas dan Kualitas HSD Biodiesel Melalui Jalur Darat]]></cell><cell><![CDATA[150,000,000]]></cell></row>
<row><cell><![CDATA[28]]></cell><cell><![CDATA[PERTAMINA (PERSERO) MOR IV, PERTAMINA (PERSERO) DIREKTORAT PEMASARAN DAN NIAGA, PERTAMINA (PERSERO)]]></cell><cell><![CDATA[Jasa Penyusunan Kajian Lokasi Pertashop Tahun 2021]]></cell><cell><![CDATA[450,000,000]]></cell></row>
<row><cell><![CDATA[29]]></cell><cell><![CDATA[PJB UBJOM PLTU REMBANG, PEMBANGKITAN JAWA BALI (PJB), PLN (PERSERO)]]></cell><cell><![CDATA[Jasa Sertifikasi Kalibrasi Belt Weigher untuk Monitoring Stock Batubara Unloading]]></cell><cell><![CDATA[150,000,000]]></cell></row>
<row><cell><![CDATA[30]]></cell><cell><![CDATA[PJB UBJOM PLTU INDRAMAYU, PEMBANGKITAN JAWA BALI (PJB), PLN (PERSERO)]]></cell><cell><![CDATA[Resertifikasi Peralatan]]></cell><cell><![CDATA[450,000,000]]></cell></row>
<row><cell><![CDATA[31]]></cell><cell><![CDATA[INDONESIA POWER UP MRICA, INDONESIA POWER UNIT PEMBANGKITAN (UP), INDONESIA POWER, PLN (PERSERO)]]></cell><cell><![CDATA[Resertifikasi Peralatan]]></cell><cell><![CDATA[250,000,000]]></cell></row>
<row><cell><![CDATA[32]]></cell><cell><![CDATA[PJB UBJOM PLTU REMBANG, PEMBANGKITAN JAWA BALI (PJB), PLN (PERSERO)]]></cell><cell><![CDATA[Jasa Pengukuran Data Kualitas Lingkungan Kerja]]></cell><cell><![CDATA[50,000,000]]></cell></row>
<row><cell><![CDATA[33]]></cell><cell><![CDATA[DHARMAPALA USAHA SUKSES]]></cell><cell><![CDATA[Resertifikasi Peralatan]]></cell><cell><![CDATA[75,000,000]]></cell></row>
<row><cell><![CDATA[34]]></cell><cell><![CDATA[INDONESIA POWER UP SEMARANG, INDONESIA POWER UNIT PEMBANGKITAN (UP), INDONESIA POWER, PLN (PERSERO)]]></cell><cell><![CDATA[2021 K3L Jasa Sertifikasi Valve PRV Dan PSV Main Line Gas PLTGU]]></cell><cell><![CDATA[20,000,000]]></cell></row>
<row><cell><![CDATA[35]]></cell><cell><![CDATA[RECKITT BENCKISER INDONESIA]]></cell><cell><![CDATA[Resertifikasi Peralatan]]></cell><cell><![CDATA[50,000,000]]></cell></row>
<row><cell><![CDATA[36]]></cell><cell><![CDATA[ADHI GUNA PUTERA]]></cell><cell><![CDATA[Resertifikasi Peralatan]]></cell><cell><![CDATA[100,000,000]]></cell></row>
<row><cell><![CDATA[37]]></cell><cell><![CDATA[INDONESIA POWER UJP PLTU JAWA TENGAH 2 ADIPALA, INDONESIA POWER UNIT JASA PEMBANGKITAN (UJP), INDONESIA POWER, PLN (PERSERO)]]></cell><cell><![CDATA[Resertifikasi Peralatan]]></cell><cell><![CDATA[100,000,000]]></cell></row>
<row><cell><![CDATA[38]]></cell><cell><![CDATA[UNZA VITALIS]]></cell><cell><![CDATA[Resertifikasi Peralatan]]></cell><cell><![CDATA[50,000,000]]></cell></row>
<row><cell><![CDATA[39]]></cell><cell><![CDATA[PEMBANGKITAN JAWA BALI SERVICES, PJB SERVICES, PEMBANGKITAN JAWA BALI (PJB), PLN (PERSERO)]]></cell><cell><![CDATA[Resertifikasi Peralatan PLTU Bangka, PLTU Belitung, PLTU Tembilahan]]></cell><cell><![CDATA[450,000,000]]></cell></row>
<row><cell><![CDATA[40]]></cell><cell><![CDATA[PLN (PERSERO) SEKTOR PEMBANGKITAN TARAHAN, PLN (PERSERO) PEMBANGKITAN SUMATERA BAGIAN SELATAN, PLN (PERSERO) DIVISI OPERASI REGIONAL SUMATERA, PLN (PERSERO) BISNIS REGIONAL SUMATERA, PLN (PERSERO)]]></cell><cell><![CDATA[Sertifikasi Peralatan K3 ( Alat Angkat Angkut, Safety Valve, Bejana Bertekanan )]]></cell><cell><![CDATA[450,000,000]]></cell></row>
<row><cell><![CDATA[41]]></cell><cell><![CDATA[PLN (PERSERO) TRANSMISI JAWA BAGIAN TENGAH, PLN (PERSERO) DIVISI OPERASI REGIONAL JAWA BAGIAN TENGAH, PLN (PERSERO) BISNIS REGIONAL JAWA BAGIAN TENGAH, PLN (PERSERO)]]></cell><cell><![CDATA[Pekerjaan Survey, Pemberkasan, Dan Sosialisasi ROW SUTT 150 KV Kudus - Jepara]]></cell><cell><![CDATA[1,500,000,000]]></cell></row>
<row><cell><![CDATA[42]]></cell><cell><![CDATA[PJB UBJOM PLTU TANJUNG AWAR-AWAR, PEMBANGKITAN JAWA BALI (PJB), PLN (PERSERO)]]></cell><cell><![CDATA[Resertifikasi Peralatan]]></cell><cell><![CDATA[500,000,000]]></cell></row>
<row><cell><![CDATA[43]]></cell><cell><![CDATA[NAGABHUANA ANEKA PIRANTI]]></cell><cell><![CDATA[Pemeriksaan Kayu]]></cell><cell><![CDATA[700,000,000]]></cell></row>
<row><cell><![CDATA[44]]></cell><cell><![CDATA[KEMENTERIAN LINGKUNGAN HIDUP DAN KEHUTANAN]]></cell><cell><![CDATA[Pengawasan dan Penilaian Tanaman RHL (PO) Tahun 2021]]></cell><cell><![CDATA[419,397,000]]></cell></row>
<row><cell><![CDATA[45]]></cell><cell><![CDATA[PJB UBJOM PLTU REMBANG, PEMBANGKITAN JAWA BALI (PJB), PLN (PERSERO)]]></cell><cell><![CDATA[JASA PEMANTAUAN LINGKUNGAN KERJA FAKTOR BIOLOGI, ERGONOMI, KIMIA, FISIKA (GETARAN) DAN PSIKOLOGI]]></cell><cell><![CDATA[100,000,000]]></cell></row>
<row><cell><![CDATA[46]]></cell><cell><![CDATA[KEMENTERIAN PERENCANAAN PEMBANGGUNAN (PPN/BAPPENAS)]]></cell><cell><![CDATA[Belanja Jasa Konsultan]]></cell><cell><![CDATA[100,000,000]]></cell></row>
<row><cell><![CDATA[47]]></cell><cell><![CDATA[KEMENTERIAN KOMUNIKASI DAN INFORMATIKA]]></cell><cell><![CDATA[Penyusunan Kajian Pembentukan Kelembagaan Pusat Data Nasional]]></cell><cell><![CDATA[100,000,000]]></cell></row>
<row><cell><![CDATA[48]]></cell><cell><![CDATA[KEMENTERIAN PEKERJAAN UMUM & PERUMAHAN RAKYAT]]></cell><cell><![CDATA[Toll Road Development Of Semarang - Demak 1A]]></cell><cell><![CDATA[100,000,000]]></cell></row>
<row><cell><![CDATA[49]]></cell><cell><![CDATA[KEMENTERIAN PEKERJAAN UMUM & PERUMAHAN RAKYAT]]></cell><cell><![CDATA[Toll Road Development Of Semarang - Demak 1C]]></cell><cell><![CDATA[100,000,000]]></cell></row>
<row><cell><![CDATA[50]]></cell><cell><![CDATA[KEMENTERIAN PEKERJAAN UMUM & PERUMAHAN RAKYAT]]></cell><cell><![CDATA[Toll Road Development Of Semarang - Demak 1B]]></cell><cell><![CDATA[100,000,000]]></cell></row>
<row><cell><![CDATA[51]]></cell><cell><![CDATA[PLN (PERSERO) UP3 KAPUAS, PLN (PERSERO) PEMBANGKITAN DAN PENYALURAN KALIMANTAN, PLN (PERSERO) WILAYAH KALIMANTAN SELATAN DAN TENGAH, PLN (PERSERO) DIVISI OPERASI REGIONAL KALIMANTAN, PLN (PERSERO) BISNIS REGIONAL KALIMANTAN, PLN (PERSERO)]]></cell><cell><![CDATA[Pengadaan Jasa Penentuan Kuantitas dan Analisa Kualtias Penerimaan Batubara]]></cell><cell><![CDATA[100,000,000]]></cell></row>
<row><cell><![CDATA[52]]></cell><cell><![CDATA[PJB UBJOM PLTU TANJUNG AWAR-AWAR, PEMBANGKITAN JAWA BALI (PJB), PLN (PERSERO)]]></cell><cell><![CDATA[Eddy Current Test Tube LP Heater 5, 6, 7 dan 8 SE #1 2021]]></cell><cell><![CDATA[100,000,000]]></cell></row>
<row><cell><![CDATA[53]]></cell><cell><![CDATA[PLN (PERSERO) UPDK BENGKULU, PLN (PERSERO) WILAYAH SUMSEL, JAMBI & BENGKULU, PLN (PERSERO) DIVISI OPERASI REGIONAL SUMATERA, PLN (PERSERO) BISNIS REGIONAL SUMATERA, PLN (PERSERO)]]></cell><cell><![CDATA[Pemantauan Lingkungan PLTA Musi dan PLTA Tes 2021 (RKL - RPL)]]></cell><cell><![CDATA[100,000,000]]></cell></row>
<row><cell><![CDATA[54]]></cell><cell><![CDATA[PLN (PERSERO) TRANSMISI JAWA BAGIAN TENGAH, PLN (PERSERO) DIVISI OPERASI REGIONAL JAWA BAGIAN TENGAH, PLN (PERSERO) BISNIS REGIONAL JAWA BAGIAN TENGAH, PLN (PERSERO)]]></cell><cell><![CDATA[PELAKSANAAN PENATAAN BATAS AREAL IPPKH JALUR SUTET 500 KV BANDUNG SELATAN - MANDIRANCAN SESUAI DENGAN PEDOMAN KERJA DAN INSTRUKSI KERJA TATA BATAS NO. INS.60/BPKH.XI/2/PLA.2/9/2020 (9 POLIGON)]]></cell><cell><![CDATA[100,000,000]]></cell></row>
<row><cell><![CDATA[55]]></cell><cell><![CDATA[PLN (PERSERO) TRANSMISI JAWA BAGIAN TENGAH, PLN (PERSERO) DIVISI OPERASI REGIONAL JAWA BAGIAN TENGAH, PLN (PERSERO) BISNIS REGIONAL JAWA BAGIAN TENGAH, PLN (PERSERO)]]></cell><cell><![CDATA[PENYUSUNAN DAN PENGESAHAN LAPORAN PELAKSANAAN PENATAAN BATAS AREAL IPPKH JALUR SUTET 500 KV BANDUNG SELATAN - MANDIRANCAN OLEH KLHK]]></cell><cell><![CDATA[50,000,000]]></cell></row>
<row><cell><![CDATA[56]]></cell><cell><![CDATA[PJB UBJOM LUAR JAWA 2, PEMBANGKITAN JAWA BALI (PJB), PLN (PERSERO)]]></cell><cell><![CDATA[Welder Test dan Supervisi Re Tubbing]]></cell><cell><![CDATA[25,000,000]]></cell></row>
<row><cell><![CDATA[57]]></cell><cell><![CDATA[PJB UBJOM LUAR JAWA 2, PEMBANGKITAN JAWA BALI (PJB), PLN (PERSERO)]]></cell><cell><![CDATA[Radiography Tube Boiler PLTU Ropa Ende Flores]]></cell><cell><![CDATA[60,000,000]]></cell></row>
<row><cell><![CDATA[58]]></cell><cell><![CDATA[PJB UBJOM PLTU PAITON, PEMBANGKITAN JAWA BALI (PJB), PLN (PERSERO)]]></cell><cell><![CDATA[Jasa Konsultan Kajian Kelayakan Pengembangan Kawasan Industri Paiton PJB Pusat]]></cell><cell><![CDATA[50,000,000]]></cell></row>
<row><cell><![CDATA[59]]></cell><cell><![CDATA[PEMBANGKITAN JAWA BALI (PJB), PLN (PERSERO)]]></cell><cell><![CDATA[Penyusunan Dokumen Analisis Dampak Lalu Lintas - Cirata Floating PV Power Plant 145 MWac - PJBI - Abu Dhabi Future Energy Company PJSE - Masdar]]></cell><cell><![CDATA[50,000,000]]></cell></row>
<row><cell><![CDATA[60]]></cell><cell><![CDATA[DWIPA KONEKTRA]]></cell><cell><![CDATA[Sertifikasi Peralatan - OHC 35 Ton, Hydrant, Fire Alarm]]></cell><cell><![CDATA[13,182,000]]></cell></row></rows>